Workbook

Sheet Read me
A1: Translation master
A2: Every email in the project in English and in each translation, in one standard layout, with the results of the integrity checks.
A4: What each language covers
A5: Afrikaans: 117 emails (the Afrikaans batch). Translator and reviewer scores included.
A6: isiXhosa: the SAME 117 emails as Afrikaans, so Afrikaans and isiXhosa can be compared directly. The original isiXhosa batch of 120 emails was not translated.
A7: isiZulu: 120 emails (the isiZulu batch), translated in place in the original file. English restored from the batch file.
A8: isiNdebele: 120 emails (the isiNdebele batch). Only the bodies were translated; subjects are still English.
A9: Translator and reviewer scores exist only for Afrikaans, so kappa can only be calculated for Afrikaans.
A11: Sheets
A12: Summary: counts per language and issues per severity (formulas).
A13: Coverage: one row per email, showing which languages it was translated into.
A14: All records: one row per email per language (English included), in one layout.
... A19: Same email IDs as English; sender, receiver, date, label and urls unchanged; every link and email address in the body kept; body and subject actually translated; translation not much shorter than the English; translation belongs to the right email.

Sheet Summary
A1: Records per language
A2: Language | B2: Phishing | C2: Legitimate | D2: Total | E2: Fix before testing | F2: Check
A3: English | B3: =COUNTIFS('All records'!$B$2:$B$832,A3,'All records'!$E$2:$E$832,"phishing") -> 177 | C3: =COUNTIFS('All records'!$B$2:$B$832,A3,'All records'!$E$2:$E$832,"legitimate") -> 180 | D3: =B3+C3 -> 357 | E3: =COUNTIFS(Issues!$B$2:$B$26,A3,Issues!$A$2:$A$26,"Fix before testing") -> 0 | F3: =COUNTIFS(Issues!$B$2:$B$26,A3,Issues!$A$2:$A$26,"Check") -> 0
A4: Afrikaans | B4: =COUNTIFS('All records'!$B$2:$B$832,A4,'All records'!$E$2:$E$832,"phishing") -> 57 | C4: =COUNTIFS('All records'!$B$2:$B$832,A4,'All records'!$E$2:$E$832,"legitimate") -> 60 | D4: =B4+C4 -> 117 | E4: =COUNTIFS(Issues!$B$2:$B$26,A4,Issues!$A$2:$A$26,"Fix before testing") -> 0 | F4: =COUNTIFS(Issues!$B$2:$B$26,A4,Issues!$A$2:$A$26,"Check") -> 3
A5: isiXhosa | B5: =COUNTIFS('All records'!$B$2:$B$832,A5,'All records'!$E$2:$E$832,"phishing") -> 57 | C5: =COUNTIFS('All records'!$B$2:$B$832,A5,'All records'!$E$2:$E$832,"legitimate") -> 60 | D5: =B5+C5 -> 117 | E5: =COUNTIFS(Issues!$B$2:$B$26,A5,Issues!$A$2:$A$26,"Fix before testing") -> 0 | F5: =COUNTIFS(Issues!$B$2:$B$26,A5,Issues!$A$2:$A$26,"Check") -> 1
A6: isiZulu | B6: =COUNTIFS('All records'!$B$2:$B$832,A6,'All records'!$E$2:$E$832,"phishing") -> 60 | C6: =COUNTIFS('All records'!$B$2:$B$832,A6,'All records'!$E$2:$E$832,"legitimate") -> 60 | D6: =B6+C6 -> 120 | E6: =COUNTIFS(Issues!$B$2:$B$26,A6,Issues!$A$2:$A$26,"Fix before testing") -> 1 | F6: =COUNTIFS(Issues!$B$2:$B$26,A6,Issues!$A$2:$A$26,"Check") -> 9
A7: isiNdebele | B7: =COUNTIFS('All records'!$B$2:$B$832,A7,'All records'!$E$2:$E$832,"phishing") -> 60 | C7: =COUNTIFS('All records'!$B$2:$B$832,A7,'All records'!$E$2:$E$832,"legitimate") -> 60 | D7: =B7+C7 -> 120 | E7: =COUNTIFS(Issues!$B$2:$B$26,A7,Issues!$A$2:$A$26,"Fix before testing") -> 6 | F7: =COUNTIFS(Issues!$B$2:$B$26,A7,Issues!$A$2:$A$26,"Check") -> 2
A9: Emails translated into | B9: Count
A10: 1 language | B10: =COUNTIF(Coverage!$I$2:$I$358,1) -> 240
A11: 2 languages | B11: =COUNTIF(Coverage!$I$2:$I$358,2) -> 117
A13: Translation agreement (Afrikaans only) | B13: Value
A14: Cohen's kappa | B14: 0.08 | C14: Calculated with scikit-learn cohen_kappa_score on the Translator_score and Reviewer_score columns
A15: Exact agreement | B15: 0.54

Sheet All records
A1: email_id | B1: language | C1: version | D1: label | E1: label_name | F1: source_dataset | G1: sender | H1: receiver | I1: date | J1: subject | K1: body | L1: urls | M1: translator_score | N1: reviewer_score
A2: EMAIL_0001 | B2: English | C2: Original | D2: 0 | E2: legitimate | F2: SpamAssassin | G2: Conor Daly <conor.daly@oceanfree.net> | H2: social@linux.ie | I2: Wed, 07 Aug 2002 13:30:59 +0100 | J2: Re: [ILUG-Social] Anyone in Limerick want to help? | K2: Sorted. I've got someone... Thanks, Conor On Tue, Aug 06, 2002 at 03:29:38PM +0100 or so it is rumoured hereabouts, Conor Daly thought: > I've had an offer of a couple of secondhand 18" LCD monitors in Limerick. > Would anyone like to assist by going to test, purchase and store same for > a couple of weeks (I'm in dublin and going away for a bit so I won't be > able to organise collection for a while)? Please reply off-list of you > can help. -- Conor Daly <conor.daly@oceanfree.net> Domestic Sysadmin :-) --------------------- Faenor.cod.ie 1:32pm up 75 days, 22:50, 0 users, load average: 0.00, 0.00, 0.00 Hobbiton.cod.ie 1:30pm up 18 days, 19:54, 1 user, load average: 0.24, 0.12, 0.03 -- Irish Linux Users' Group Social Events: social@linux.ie http://www.linux.ie/mailman/listinfo/social for (un)subscription information. List maintainer: listmaster@linux.ie | L2: http://www.linux.ie/mailman/listinfo/social
A3: EMAIL_0001 | B3: Afrikaans | C3: Translation | D3: 0 | E3: legitimate | F3: SpamAssassin | G3: Conor Daly <conor.daly@oceanfree.net> | H3: social@linux.ie | I3: Wed, 07 Aug 2002 13:30:59 +0100 | J3: Re: [ILUG-Social] Iemand in Limerick wat wil help? | K3: Reggekry. Ek het iemand... Dankie, Conor Op Di, 06 Aug 2002 om 15:29:38 +0100, of so lui die gerugte hier rond, het Conor Daly gedink: > Ek het 'n aanbod gekry van 'n paar tweedehandse 18"-LCD-monitors in Limerick. > Sal iemand wil help deur te gaan toets, dit te koop en vir 'n paar weke > te stoor (ek is in Dublin en gaan 'n rukkie weg, so ek sal nie vir 'n > ruk afhaal kan reël nie)? Antwoord asseblief buite die lys as jy > kan help. -- Conor Daly <conor.daly@oceanfree.net> Huishoudelike stelseladministrateur :-) --------------------- Faenor.cod.ie 1:32pm up 75 days, 22:50, 0 users, load average: 0.00, 0.00, 0.00 Hobbiton.cod.ie 1:30pm up 18 days, 19:54, 1 user, load average: 0.24, 0.12, 0.03 -- Ierse Linux-gebruikersgroep se sosiale geleenthede: social@linux.ie http://www.linux.ie/mailman/listinfo/social vir inligting oor in- en uitskrywing. Lysbestuurder: listmaster@linux.ie | L3: http://www.linux.ie/mailman/listinfo/social | M3: 2 | N3: 2
A4: EMAIL_0001 | B4: isiXhosa | C4: Translation | D4: 0 | E4: legitimate | F4: SpamAssassin | G4: Conor Daly <conor.daly@oceanfree.net> | H4: social@linux.ie | I4: Wed, 07 Aug 2002 13:30:59 +0100 | J4: Ingaba ukhona umntu eLimerick ongathanda ukunceda? | K4: Ndiyifumene. Ndinomntu... Enkosi. Conor On Thu, 06 Aug 2002 ngo-15: 29: 38 + 0100, okanye ke amahemuhemu avela apha, uConor Daly wacinga: &gt; Ndifumene isibonelelo kwiimonitha eziyi-18"ze-LCD zaseLimerick. &gt; Ngaba ukhona umntu ongathanda ukunceda ngokuya kuvavanya, ukuyithenga nangeeveki ezimbalwa &gt; ukuyigcina (ndiseDublin ndize ndihambe okwethutyana, ngoko andizukuba &gt; jerk pick up ayikwazi ukulungiselela)? Nceda uphendule ngaphandle kwendlu ukuba wena &gt; ingakunceda. -- <conor.daly@oceanfree.net>Ikhaya LaseConor Daly umlawuli wenkqubo :-) --------------------- I-Faenor.cod.ie 1:32pm ukuya kutsho kwiintsuku eziyi-75, 22:50, 0 abasebenzisi, umyinge wokulayisha: 0.00, 0.00, 0.00 I-Hobbiton.cod.ie 1:30emva kwemini ukuya kutsho kwiintsuku eziyi-18, 19:54, umsebenzisi omnye, umyinge wokulayisha: 0.24, 0.12, 0.03 -- Imicimbi yentlalo yeqela lomsebenzisi weLinux waseIreland: social@linux.ie http://www.linux.ie/mailman/listinfo/social yolwazi lokungena nokuphuma. Umphathi Woluhlu: listmaster@linux.ie | L4: http://www.linux.ie/mailman/listinfo/social
A5: EMAIL_0005 | B5: English | C5: Original | D5: 0 | E5: legitimate | F5: SpamAssassin | G5: Fox <lds0062@cdc.net> | H5: razor-users@example.sourceforge.net | I5: Mon, 26 Aug 2002 16:14:04 -0400 | J5: [Razor-users] Preproc erasing message | K5: The following razor debugging sequence show my mail going from 9295 bytes to 0 bytes after the preproc runs, which gives me an exit code that is not 0. I included the message below. Fox Razor-Log: No /etc/razor/razor-agent.conf found, skipping. Razor-Log: No razor-agent.conf found, using defaults. Aug 26 10:28:09.225237 check[3469]: [ 1] [bootup] Logging initiated LogDebugLevel=9 to stdout Aug 26 10:28:09.225890 check[3469]: [ 5] computed razorhome=/etc/razor, conf=, ident=/etc/razor/identity Aug 26 10:28:09.226006 check[3469]: [ 2] Razor-Agents v2.14 starting razor-check -d -home=/etc/razor Aug 26 10:28:09.229704 check[3469]: [ 9] uname -a: Linux qmail.mckee.com 2.4.8-34.1mdk #1 Mon Nov 19 12:40:39 MST 2001 i686 unknown Aug 26 10:28:09.230155 check[3469]: [ 8] reading straight RFC822 mail from Aug 26 10:28:09.231524 check[3469]: [ 6] read 1 mail Aug 26 10:28:09.231923 check[3469]: [ 8] Client supported_engines: 1 2 3 4 Aug 26 10:28:09.233017 check[3469]: [ 8] prep_mail done: mail 1 headers=631, mime0=9295 Aug 26 10:28:09.233434 check[3469]: [ 6] skipping whitelist file (empty?): /etc/razor/razor-whitelist Aug 26 10:28:09.233995 check[3469]: [ 5] read_file: 1 items read from /etc/razor/servers.discovery.lst Aug 26 10:28:09.234369 check[3469]: [ 5] read_file: 1 items read from /etc/razor/servers.nomination.lst Aug 26 10:28:09.234697 check[3469]: [ 5] read_file: 3 items read from /etc/razor/servers.catalogue.lst Aug 26 10:28:09.235184 check[3469]: [ 9] Assigning defaults to honor.cloudmark.com Aug 26 10:28:09.235415 check[3469]: [ 9] Assigning defaults to truth.cloudmark.com Aug 26 10:28:09.235624 check[3469]: [ 9] Assigning defaults to fire.cloudmark.com Aug 26 10:28:09.235830 check[3469]: [ 9] Assigning defaults to apt.cloudmark.com Aug 26 10:28:09.236715 check[3469]: [ 5] read_file: 11 items read from /etc/razor/server.truth.cloudmark.com.conf Aug 26 10:28:09.237368 check[3469]: [ 5] read_file: 11 items read from /etc/razor/server.fire.cloudmark.com.conf Aug 26 10:28:09.237825 check[3469]: [ 5] 149643 seconds before closest server discovery Aug 26 10:28:09.238135 check[3469]: [ 6] truth.cloudmark.com is a Catalogue Server srl 51; computed min_cf=1, Server se: 0B Aug 26 10:28:09.238414 check[3469]: [ 8] Computed supported_engines: 1 2 4 Aug 26 10:28:09.238656 check[3469]: [ 8] Using next closest server truth.cloudmark.com:2703, cached info srl 51 Aug 26 10:28:09.238871 check[3469]: [ 8] mail 1 Subject: New Freeware Download Aug 26 10:28:09.290618 check[3469]: [ 6] preproc: mail 1.0 went from 9295 bytes to 0, erasing Aug 26 10:28:09.291100 check[3469]: [ 5] Connecting to truth.cloudmark.com ... Aug 26 10:28:09.505431 check[3469]: [ 8] Connection established Aug 26 10:28:09.505662 check[3469]: [ 4] truth.cloudmark.com >> 29 server greeting: sn=C&srl=51&ep4=7542-10&a=l Aug 26 10:28:09.506086 check[3469]: [ 6] truth.cloudmark.com is a Catalogue Server srl 51; computed min_cf=1, Server se: 0B Aug 26 10:28:09.506342 check[3469]: [ 8] Computed supported_engines: 1 2 4 Aug 26 10:28:09.506604 check[3469]: [ 8] mail 1.0 skipped in check Aug 26 10:28:09.506686 check[3469]: [ 5] No queries, no spam Aug 26 10:28:09.506787 check[3469]: [ 5] disconnecting from server truth.cloudmark.com Aug 26 10:28:09.507071 check[3469]: [ 4] truth.cloudmark.com << 5 Aug 26 10:28:09.507155 check[3469]: [ 6] a=q Aug 26 10:28:09.507959 check[3469]: [ 8] razor-check finished successfully. >>From bounce-html-sales1-21787251@lyris.execsoft.com Mon Aug 26 14:28:10 2002 Return-Path: <bounce-html-sales1-21787251@lyris.execsoft.com> Delivered-To: log@qmail.mckee.com Received: (qmail 3472 invoked from network); 26 Aug 2002 14:28:10 -0000 Received: from unknown (HELO port-216-3073879-ds200.devices.datareturn.net) (216.46.231.87) by 10.97.5.1 with SMTP; 26 Aug 2002 14:28:05 -0000 X-Mailer: Lyris Web Interface Date: Sat, 24 Aug 2002 09:45:48 -0700 Subject: New Freeware Download - Jammed: eric_koester@ccmail.mckee.com To: <trollbox@dustpuppy.mckee.com> From: "Diskeeper Product Manager, Executive Software" <executive@executive.com> List-Unsubscribe: <mailto:leave-html-sales1-21787251A@lyris.execsoft.com> Reply-To: executive@executive.com Message-Id: <LYRIS-21787251-20123-2002.08.24-09.47.15--eric_koester#ccmail.mckee.com@lyr is.execsoft.com> MIME-Version: 1.0 Content-Type: text/html; charset=us-ascii Spam-File: Envelope-Recipient: eric_koester@ccmail.mckee.com <!------------------------------------------------------------ Is Maximum System Performance and Reliablilty Important to you? Find out what you are missing! New Diskeeper Lite for Windows. IT'S FREE! * Includes the same advanced defragmentation technology used in Diskeeper 7.0. * Is much faster than the previous Diskeeper Lite and all built-in defragmenters. * Now runs on Windows NT®/98/2000/XP. Millions of downloads attest to the popularity of Diskeeper Lite, but it only ran on Windows NT 4.0. Now it's been updated for all Windows operating systems from Windows 98 onward.
A6: EMAIL_0005 | B6: isiNdebele | C6: Translation | D6: 0 | E6: legitimate | F6: SpamAssassin | G6: Fox <lds0062@cdc.net> | H6: razor-users@example.sourceforge.net | I6: Mon, 26 Aug 2002 16:14:04 -0400 | J6: [Razor-users] Preproc erasing message | K6: Ukulandelana kokulungisa amaphutha okulandelako kutjengisa imeyili yami ukusuka kuma-9295 wamabhayithi ukuya ku- 0 amabhayithi ngemva kokuthi i-preproc isebenze, okunginikela ikhodi yokuphuma engekho 0. Ngifake umlayezo ongezansi. Udahla I-Razor-Log: Akukho /etc/razor/razor-agent.conf etholakalako, yeqa. I-Razor-Log: Akukho razor-agent.conf etholakeleko, kusetjenziswa okujayelekileko. Aug 26 10:28:09.225237 check[3469]: [ 1] [bootup] Ukuloga kuthomile LogDebugLevel=9 ukuya ku-stdout Aug 26 10:28:09.225890 check[3469]: [ 5] computed razorhome=/etc/razor, conf=, ident=/etc/razor/identity Aug 26 10:28:09.226006 check[3469]: [ 2] Razor-Agents v2.14 ethoma razor-check -d -home=/etc/razor Aug 26 10:28:09.229704 check[3469]: [ 9] uname -a: Linux qmail.mckee.com 2.4.8-34.1mdk #1 Mon Nov 19 12:40:39 MST 2001 i686 akaziwa Aug 26 10:28:09.230155 hlola[3469]: [8] ukufunda i-RFC822 imeyili evela Aug 26 10:28:09.231524 hlola[3469]: [ 6] funda imeyili eyodwa Aug 26 10:28:09.231923 hlola[3469]: [8] Iinjini ezisekelwe_iklayenti: 1 2 3 4 Aug 26 10:28:09.233017 check[3469]: [ 8] prep_mail done: mail 1 headers=631, mime0=9295 Aug 26 10:28:09.233434 hlola[3469]: [6] ukweqa ifayela elimhlophe (elingenalutho?): /etc/razor/razor-whitelist Aug 26 10:28:09.233995 check[3469]: [ 5] read_file: 1 into efundwa ukusuka /etc/razor/servers.discovery.lst Aug 26 10:28:09.234369 check[3469]: [ 5] read_file: 1 into efundwa ukusuka /etc/razor/servers.nomination.lst Aug 26 10:28:09.234697 check[3469]: [ 5] read_file: 3 izinto ezifundwa ukusuka /etc/razor/servers.catalogue.lst Aug 26 10:28:09.235184 check[3469]: [ 9] Ukwabela ama-default ku honor.cloudmark.com Aug 26 10:28:09.235415 check[3469]: [ 9] Ukwabela ama-default ku truth.cloudmark.com Aug 26 10:28:09.235624 check[3469]: [ 9] Ukwabela ama-default ku fire.cloudmark.com Aug 26 10:28:09.235830 check[3469]: [ 9] Ukwabela ama-default ku apt.cloudmark.com Aug 26 10:28:09.236715 check[3469]: [ 5] read_file: 11 izinto ezifundwa ukusuka /etc/razor/server.truth.cloudmark.com.conf Aug 26 10:28:09.237368 check[3469]: [ 5] read_file: 11 izinto ezifundwa ukusuka /etc/razor/server.fire.cloudmark.com.conf Aug 26 10:28:09.237825 hlola[3469]: [5] 149643 imizuzwana ngaphambi kokutjhidela ukutholwa kweseva Aug 26 10:28:09.238135 check[3469]: [ 6] truth.cloudmark.com yikhathalogu Iseva srl ​​51; kubalwa i-min_cf=1, Iseva se: 0B Aug 26 10:28:09.238414 check[3469]: [ 8] Computed supported_engines: 1 2 4 Aug 26 10:28:09.238656 check[3469]: [ 8] Ukusebenzisa iseva eseduze truth.cloudmark.com:2703, cached info srl 51 Aug 26 10:28:09.238871 check[3469]: [ 8] imeyili 1 Isihloko: Ihlelo elitjha lamahhala Dawunlowuda Aug 26 10:28:09.290618 check[3469]: [ 6] preproc: iposi 1.0 yasuka ku-9295 amabhayithi ukuya ku-0, ukusula Aug 26 10:28:09.291100 check[3469]: [ 5] Ukuxhuma ku-truth.cloudmark.com ... Aug 26 10:28:09.505431 check[3469]: [ 8] Ukuxhumana kusungulwe Aug 26 10:28:09.505662 check[3469]: [ 4] truth.cloudmark.com >> 29 iseva ukubingelela: sn=C&srl=51&ep4=7542-10&a=l Aug 26 10:28:09.506086 check[3469]: [ 6] truth.cloudmark.com yikhathalogu Iseva srl ​​51; kubalwa i-min_cf=1, Iseva se: 0B Aug 26 10:28:09.506342 check[3469]: [ 8] Computed supported_engines: 1 2 4 Aug 26 10:28:09.506604 check[3469]: [ 8] imeyili 1.0 yeqiwe Aug 26 10:28:09.506686 check[3469]: [ 5] Akukho mibuzo, akukho spam Aug 26 10:28:09.506787 hlola[3469]: [5] ukuvala iseva truth.cloudmark.com Aug 26 10:28:09.507071 check[3469]: [ 4] truth.cloudmark.com << 5 Aug 26 10:28:09.507155 hlola[3469]: [ 6] a=q Aug 26 10:28:09.507959 hlola[3469]: [ 8] ukuhlola ngensingo kuqediwe ngempumelelo. >>Kusuka ku-bounce-html-sales1-21787251@lyris.execsoft.com ngoMvulo Aug 26 14:28:10 2002 Indlela yokubuya: <bounce-html-sales1-21787251@lyris.execsoft.com> Ithunyelwe-Ku: log@qmail.mckee.com Kwamukelwe: (i-qmail 3472 ebizwe kunethiwekhi); 26 Aug 2002 14:28:10 -0000 Yamukelwe: evela kongaziwako (HELO port-216-3073879-ds200.devices.datareturn.net) (216.46.231.87) ngo-10.97.5.1 nge-SMTP; 26 Aug 2002 14:28:05 -0000 I-X-Mailer: I-Lyris Web Interface Ilanga: uMgqibelo, mhlana ama-24 kuRhoboyi wee-2002 09:45:48 -0700 Isihloko: Ukudawuniloda kwe-Freeware etja - Jammed: eric_koester@ccmail.mckee.com Ku: <trollbox@dustpuppy.mckee.com> Ukusuka ku: "Umphathi womkhiqizo we-Diskeeper, i-Executive Software" <executive@executive.com> List-Unsubscribe: <mailto:leave-html-sales1-21787251A@lyris.execsoft.com> Phendula-ku: executive@executive.com Umlayezo-Id: <LYRIS-21787251-20123-2002.08.24-09.47.15--eric_koester#ccmail.mckee.com@lyr is.execsoft.com> I-MIME-Version: 1.0 Umhlobo wokuqukethwe: umtlolo/html; charset=us-ascii Ifayela le-Spam: Umamukeli wemvilophu: eric_koester@ccmail.mckee.com <!---------------------------------------------------------- Ingabe ukusebenza okuphezulu kwesistimu nokuthembeka kuqakathekile kuwe? Thola bona yini oyitlhogako! I-Diskieper etja ye-Windows. KUMAHHALA! * Ifaka hlangana ithekhnoloji efanako yokuhlukanisa ingcenye esetjenziswe ku- Isivikeli 7.0. * Ikhawuleza khulu kune-Diskeeper Lite yangaphambilini nayo yoke ama-defragmenters akhiwe ngaphakathi. * Nje isebenza ku-Windows NT®/98/2000/XP. Iingidigidi zokulandwa zifakazela ukuthandwa kwe-Diskeeper Lite, kodwana beyisebenza ku-Windows NT 4.0 kwaphela. Nje sele ivuselelwe kibo boke Iinhlelo zokusebenza ze-Windows ukusuka ku-Windows 98 ukuya phambili.
A7: EMAIL_0006 | B7: English | C7: Original | D7: 0 | E7: legitimate | F7: SpamAssassin | G7: "Joseph S. Barrera III" <joe@barrera.org> | H7: Eugen Leitl <eugen@leitl.org> | I7: Tue, 23 Jul 2002 14:46:04 -0700 | J7: Re: spam maps | K7: Eugen Leitl wrote: > P.S. We hate you, too. "Fuck you, sir," came the familiar tired chorus. "Louder!" "FUCK YOU, SIR!" Damn, I love that book (_Forever War_). - Joe http://xent.com/mailman/listinfo/fork | L7: http://xent.com/mailman/listinfo/fork
A8: EMAIL_0006 | B8: isiZulu | C8: Translation | D8: 0 | E8: legitimate | F8: SpamAssassin | G8: "Joseph S. Barrera III" <joe@barrera.org> | H8: Eugen Leitl <eugen@leitl.org> | I8: Tue, 23 Jul 2002 14:46:04 -0700 | J8: Mayelana: namamephu e-spam | K8: U-Eugen Leitl wabhala: > P.S. Nathi siyakuzonda. "Fuck you, sir," kwaphendula izwi elilodwa elijwayelekile nelikhathele. "Ngokuzwakalayo!" "FUCK YOU, SIR!" Hawu, ngiyayithanda leyo ncwadi (_Forever War_). - Joe http://xent.com/mailman/listinfo/fork | L8: http://xent.com/mailman/listinfo/fork
A9: EMAIL_0007 | B9: English | C9: Original | D9: 0 | E9: legitimate | F9: SpamAssassin | G9: Matthias Saou <matthias@rpmforge.net> | H9: rpm-zzzlist@freshrpms.net | I9: Mon, 07 Oct 2002 18:54:30 +0200 | J9: Re: transcode build problem (was: RH 8 no DMA for DVD drive) | K9: Once upon a time, Alvie wrote : > This is only the last part of it.I used 'rpmbuild --rebuild --without > avifile transcode.0.6.1-fr2.src.rpm'. > af6_decore.cpp:305: 'WAVEFORMATEX' > is used as a type, but is not defined as a > type. > af6_decore.cpp:306: parse error before `if' [...] All of these "af6" are related to avifile6 support :-/ Normally, my 0.6.1-fr2 build of transcode defaults to *not* use avifile, but you can use "--with avifile6" to force recompiling against it. Do you have an old avifile installed maybe? Can you check the "./configure ..." line run at the beginning of the rebuild process to see if it does include the "--without-avifile6" option? Matthias -- Clean custom Red Hat Linux rpm packages : http://freshrpms.net/ Red Hat Linux release 7.3 (Valhalla) running Linux kernel 2.4.18-10acpi Load : 0.23 0.14 0.14 _______________________________________________ RPM-List mailing list <RPM-List@freshrpms.net> http://lists.freshrpms.net/mailman/listinfo/rpm-list | L9: http://freshrpms.net/, http://lists.freshrpms.net/mailman/listinfo/rpm-list
A10: EMAIL_0007 | B10: isiZulu | C10: Translation | D10: 0 | E10: legitimate | F10: SpamAssassin | G10: Matthias Saou <matthias@rpmforge.net> | H10: rpm-zzzlist@freshrpms.net | I10: Mon, 07 Oct 2002 18:54:30 +0200 | J10: Mayelana: Inkinga yokwakha i-transcode (okwakuyi: i-RH 8 ayinayo i-DMA yedrayivu ye-DVD) | K10: Ngelinye ilanga, u-Alvie wabhala : > Le yingxenye yokugcina kuphela. Ngisebenzise 'rpmbuild --rebuild --without > avifile transcode.0.6.1-fr2.src.rpm'. > af6_decore.cpp:305: 'WAVEFORMATEX' > isetshenziswa njengohlobo (type), kodwa ayichazwanga njengo- > hlobo. > af6_decore.cpp:306: iphutha lokufunda ikhodi (parse error) ngaphambi kuka-`if' [...] Konke lokhu okungu-"af6" kuhlobene nokusekelwa kwe-avifile6 :-/ Ngokujwayelekile, uhlobo lwami lwe-transcode olungu-0.6.1-fr2 aluyisebenzisi i-avifile ngokuzenzakalelayo, kodwa ungasebenzisa u-"--with avifile6" ukuze uphoqelele ukuthi iphinde yakhiwe (recompile) isebenzisa yona. Ingabe kungenzeka ukuthi une-avifile endala efakiwe? Ungakwazi yini ukuhlola umugqa othi "./configure ..." osebenze ekuqaleni kwenqubo yokwakha kabusha ukuze ubone ukuthi uqukethe yini inketho ethi "--without-avifile6"? Matthias -- Amaphakethe e-rpm e-Red Hat Linux enziwe ngokwezifiso futhi ahlanzekile : http://freshrpms.net/ I-Red Hat Linux release 7.3 (Valhalla) esebenzisa i-Linux kernel 2.4.18-10acpi Umthwalo (Load) : 0.23 0.14 0.14 _______________________________________________ RPM-List mailing list <RPM-List@freshrpms.net> http://lists.freshrpms.net/mailman/listinfo/rpm-list | L10: http://freshrpms.net/, http://lists.freshrpms.net/mailman/listinfo/rpm-list
A11: EMAIL_0008 | B11: English | C11: Original | D11: 0 | E11: legitimate | F11: SpamAssassin | G11: David Wheeler <dwheeler@ida.org> | H11: Giorgio Zoppi <deneb@penguin.it>, secprog@securityfocus.com | I11: Fri, 30 Aug 2002 10:29:13 -0400 | J11: Re: Storing passwords | K11: If you need to store a database password, then clearly the first step is to store the text outside the web tree. You can encrypt it and store the encryption key elsewhere, so that at least an attacker has to get two different things. Also, don't get full privileges - create a user account that is GRANTed very limited access. However, you can often do better than this if security is critical. Create a separate program which has these database keys (as noted above), and make the web program contact IT. Create a very limited protocol that ONLY lets you do the operations you need (you can add specific operations later). There's a performance hit, which you're trading for improved data isolation. Giorgio Zoppi wrote: > On Fri, Aug 23, 2002, David Wheeler wrote: > > >>The standard way to store passwords is... not to >>store passwords. Instead, store a salted hash of >>the password in a database. When you get a purported >>password, you re-salt it, compute the hash, and >>determine if they are the same. This is how >>Unix has done it for years. You want bigger hashes >>and salts than the old Unix systems, and you still want >>to prevent reading from those files (to foil password crackers). >>More info is in my book at: >> http://www.dwheeler.com/secure-programs >> > > Well...but this cannot be applied to database password, which most > web apps use. The only solution I figure is store in clear outside web > tree, any other ideas feasible? > > Ciao, > Giorgio. > > -- > Never is Forever - deneb@penguin.it > Homepage: http://www.cli.di.unipi.it/~zoppi/index.html > -- > > > -- --- David A. Wheeler dwheeler@ida.org | L11: http://www.cli.di.unipi.it/~zoppi/index.html, http://www.dwheeler.com/secure-programs
A12: EMAIL_0008 | B12: isiNdebele | C12: Translation | D12: 0 | E12: legitimate | F12: SpamAssassin | G12: David Wheeler <dwheeler@ida.org> | H12: Giorgio Zoppi <deneb@penguin.it>, secprog@securityfocus.com | I12: Fri, 30 Aug 2002 10:29:13 -0400 | J12: Re: Storing passwords | K12: Nawufuna ukugcina iphasiwedi yedathabeyisi, khona-ke ngokusobala igadango lokuthoma kukugcina umtlolo ngaphandle umuthi wewebhu. Ungayibethela bese ubeka ikhiye yokubethela kwenye indawo, ukwenzela bona okungenani umhlaseli kufuze athole izinto ezimbili ezihlukileko. Godu, ungatholi amalungelo apheleleko - yenza i-akhawundi yomsebenzisi INIKEZWE ukufinyelela okulinganiselwe khulu. Kodwana, kanengi ungenza ngcono kunalokhu nangabe ukuphepha kuqakathekile. Yenza ihlelo elihlukileko elinalokhu iinkinobho zedathabeyisi (njengombana kutjhiwo ngehla), bese wenza ihlelo lewebhu thintana ne-IT. Yenza iphrothokholi elinganiselwe khulu ethi KUPHELA ikuvumela bona wenze imisebenzi oyitlhogako (ungangeza okuthileko imisebenzi ngemva kwesikhathi). Kunokudlala okukhulu, okwenza ukurhweba ukuthuthukisa ukuhlukaniswa kwedatha. U-Giorgio Zoppi watlola: > NgeLesihlanu, mhlazi-23 kuRhoboyi wee-2002, u-David Wheeler watlola: > > >>Indlela ejayelekileko yokugcina amaphasiwedi... ingasi >>gcina amaphasiwedi. Esikhundleni salokho, gcina i-hash enetswayi ye- >>iphasiwedi kudathabeyisi. Nawufumana >>iphasiwedi, uyifaka isawudo godu, ubale i-hash, bese >>hlola bona ziyafana na. Le yindlela >>I-Unix sele ikwenzile iminyaka eminengi. Ufuna ama-hash amakhulu >>namatswayi ukudlula amasistimu we-Unix amadala, begodu usafuna >>ukukhandela ukufundwa kilawo mafayela (ukukhandela ukuqeda iphasiwedi). >>Ilwazi elinabileko lisencwadini yami ku: >> http://www.dwheeler.com/secure-programs >> > > Kulungile...kodwana lokhu angeze kwasetjenziswa kuphasiwedi yedathabheyisi, okuyinto enengi > ukusetjenziswa kwama-app wewebhu. Isisombululo sodwa engicabangako sigcina ngaphandle kwewebhu ecacileko > umuthi, ikhona eminye imibono engenzekako? > > Ciao, > Giorgio. > > -- > Never is Forever - deneb@penguin.it > Ikhasi lokuthoma: http://www.cli.di.unipi.it/~zoppi/index.html > -- > > > -- --- U-David A. Wheeler dwheeler@ida.org | L12: http://www.cli.di.unipi.it/~zoppi/index.html, http://www.dwheeler.com/secure-programs
A13: EMAIL_0011 | B13: English | C13: Original | D13: 0 | E13: legitimate | F13: SpamAssassin | G13: scripting <rssfeeds@example.com> | H13: yyyy@example.com | I13: Thu, 26 Sep 2002 08:01:30 -0000 | J13: Jeremy Bowers: "None of the trackback mechanisms has reached the critical m | K13: URL: http://scriptingnews.userland.com/backissues/2002/09/25#When:5:12:19AM Date: Wed, 25 Sep 2002 12:12:19 GMT Jeremy Bowers[1]: "None of the trackback mechanisms has reached the critical mass necessary to see the negative effects experienced in all other community models." [1] http://www.jerf.org/irights/2002/09/25.html#a2231 | L13: http://scriptingnews.userland.com/backissues/2002/09/25#When:5:12:19AM, http://www.jerf.org/irights/2002/09/25.html#a2231
A14: EMAIL_0011 | B14: isiZulu | C14: Translation | D14: 0 | E14: legitimate | F14: SpamAssassin | G14: scripting <rssfeeds@example.com> | H14: yyyy@example.com | I14: Thu, 26 Sep 2002 08:01:30 -0000 | J14: UJeremy Bowers: "Azikho izindlela zokulandela umkhondo ezifinyelele ku-m | K14: URL: http://scriptingnews.userland.com/backissues/2002/09/25#When:5:12:19AM Usuku: NgoLwesithathu, 25 Septhemba 2002 12:12:19 GMT Jeremy Bowers[1]: "Ayikho neyodwa yezindlela ze-'trackback' esifinyelele ezingeni elibalulekile elidingekayo ukuze kubonakale imiphumela emibi ebonakala kuzo zonke ezinye izinhlobo zemiphakathi." [1] http://www.jerf.org/irights/2002/09/25.html#a2231 | L14: http://scriptingnews.userland.com/backissues/2002/09/25#When:5:12:19AM, http://www.jerf.org/irights/2002/09/25.html#a2231
A15: EMAIL_0013 | B15: English | C15: Original | D15: 0 | E15: legitimate | F15: SpamAssassin | G15: mb/vipul@dcs.qmul.ac.uk | H15: Joe Berry <joe@topshot.com> | I15: Mon, 26 Aug 2002 21:04:35 +0100 | J15: Re[2]: [Razor-users] Reducing impact from tons of email | K15: On Aug 25 Joe Berry wrote: >Very good advice given above. Yes :) >One more problem solved. No. One more problem in some software worked around by using tricks in another piece of software. The solution is the aggregator. ------------------------------------------------------- This sf.net email is sponsored by: OSDN - Tired of that same old cell phone? Get a new here for FREE! https://www.inphonic.com/r.asp?r=sourceforge1&refcode1=vs3390 _______________________________________________ Razor-users mailing list Razor-users@lists.sourceforge.net https://lists.sourceforge.net/lists/listinfo/razor-users | L15: https://lists.sourceforge.net/lists/listinfo/razor-users, https://www.inphonic.com/r.asp?r=sourceforge1&refcode1=vs3390
A16: EMAIL_0013 | B16: isiZulu | C16: Translation | D16: 0 | E16: legitimate | F16: SpamAssassin | G16: mb/vipul@dcs.qmul.ac.uk | H16: Joe Berry <joe@topshot.com> | I16: Mon, 26 Aug 2002 21:04:35 +0100 | J16: Re[2]: [Razor-users] Ukunciphisa umthelela wenqwaba yama-imeyili | K16: Ngo-Agasti 25 uJoe Berry wabhala: >Iseluleko esihle kakhulu esinikezwe ngenhla. Yebo :) >Enye inkinga ixazululiwe. Cha. Enye inkinga kuhlelo oluthile lwekhompyutha ixazululwe ngokusebenzisa amaqhinga kolunye uhlelo. Isixazululo siwuhlelo oluhlanganisayo (aggregator). ------------------------------------------------------- Le-imeyili ye-sf.net ixhaswe yi: OSDN - Ukhathele yilelo foni yakudala? Thola entsha lapha mahhala! https://www.inphonic.com/r.asp?r=sourceforge1&refcode1=vs3390 _______________________________________________ Uhlu lwama-imeyili lwabasebenzisi be-Razor Razor-users@lists.sourceforge.net https://lists.sourceforge.net/lists/listinfo/razor-users | L16: https://lists.sourceforge.net/lists/listinfo/razor-users, https://www.inphonic.com/r.asp?r=sourceforge1&refcode1=vs3390
A17: EMAIL_0014 | B17: English | C17: Original | D17: 0 | E17: legitimate | F17: SpamAssassin | G17: bugzilla-daemon@hughes-family.org | H17: spamassassin-devel@example.sourceforge.net | I17: Sat, 21 Sep 2002 16:37:55 -0700 | J17: [SAdev] [Bug 886] Add a rule to detect Content-type message/partial | K17: http://www.hughes-family.org/bugzilla/show_bug.cgi?id=886 ------- Additional Comments From jm@jmason.org 2002-09-21 16:37 ------- I'd prefer to wait and see if spammers do anything about it. my guess is they will not, as it'd mean modifying their spamware to send >1 msg per recipient. I vote WONTFIX as a result ;) ------- You are receiving this mail because: ------- You are the assignee for the bug, or are watching the assignee. ------------------------------------------------------- This sf.net email is sponsored by:ThinkGeek Welcome to geek heaven. http://thinkgeek.com/sf _______________________________________________ Spamassassin-devel mailing list Spamassassin-devel@lists.sourceforge.net https://lists.sourceforge.net/lists/listinfo/spamassassin-devel | L17: http://thinkgeek.com/sf, http://www.hughes-family.org/bugzilla/show_bug.cgi?id=886, https://lists.sourceforge.net/lists/listinfo/spamassassin-devel
A18: EMAIL_0014 | B18: isiZulu | C18: Translation | D18: 0 | E18: legitimate | F18: SpamAssassin | G18: bugzilla-daemon@hughes-family.org | H18: spamassassin-devel@example.sourceforge.net | I18: Sat, 21 Sep 2002 16:37:55 -0700 | J18: [SAdev] [Iphutha 886] Faka umthetho wokuthola i-Content-type ethi umyalezo/okuyingxenye | K18: http://www.hughes-family.org/bugzilla/show_bug.cgi?id=886 ------- Amazwana engeziwe avela ku-jm@jmason.org 2002-09-21 16:37 ------- Ngingakhetha ukulinda ngibone ukuthi abathumela imiyalezo engafuneki (spammers) benza okuthile ngakho yini. Ngicabanga ukuthi ngeke bakwenze lokho, ngoba kungasho ukushintsha isofthiwe yabo ukuze bathumele imiyalezo engaphezu koyedwa kumamukeli ngamunye. Ngakho-ke ngivotela inketho ethi WONTFIX ;) ------- Uthola le-imeyili ngoba: ------- Ungumuntu owabelwe ukulungisa le nkinga (bug), noma uqaphe lowo oyabelwe yona. ------------------------------------------------------- Le-imeyili ye-sf.net ixhaswe yi-ThinkGeek Siyakwamukela ezweni lamaphupho labathandi bobuchwepheshe (geek heaven). http://thinkgeek.com/sf _______________________________________________ Uhlu lwe-imeyili lwe-Spamassassin-devel Spamassassin-devel@lists.sourceforge.net https://lists.sourceforge.net/lists/listinfo/spamassassin-devel | L18: http://thinkgeek.com/sf, http://www.hughes-family.org/bugzilla/show_bug.cgi?id=886, https://lists.sourceforge.net/lists/listinfo/spamassassin-devel
... A22: EMAIL_0016 | B22: isiNdebele | C22: Translation | D22: 0 | E22: legitimate | F22: SpamAssassin | G22: Kenn Humborg <kenn@linux.ie> | H22: John Gay <johngay@eircom.net> | I22: Sun, 21 Jul 2002 19:16:30 +0100 | J22: Re: [ILUG] Optimising for PentiumMMX? | K22: NgeSonto, mhlazi-21 kuNtaka 2002 nge-07:06:06PM +0100, u-John Gay watlola: > Ngiyazibuza bona i-C, namanye amalayibhrari kufanele akhiwe kabutjha? Bangakghona na > sebenzisa ithuba lemiyalo ye-Pentium ne-MMX malungana nokusebenza kwesistimu? > Begodu ingabe lokhu kutlhoga ukwakhiwa kabutjha kwe-gcc nayo? i-glibc ngumuntu ongakhethwa. > Ngenothi ehlobene, ngiyazi bona ngike ngakhuluma lapha ngaphambilini, kodwana ngisafuna > ye-Slot 1 550Mhz PIII. Irherho lami elijayelekileko yi-Dual PII350 kanye ne-440BX > M/B angathatha ama-PIII. Ngikghone ukuthola izandla zami kwenye. Ukube bengingathola enye > Ngingafaka ama-PIII amabili ebhokisini bese ngihlanganisa i-X ukusebenzisa i- > Imilayo ye-SSE/Katmai ku-PIII. Angicabangi bona kufanele ukubuyiselwa esikhundleni > ama-PII amabili nge-PIII eyodwa. Ngiyazi bona azisekho esitokisini, begodu ngiyazibukela > i-Buy-N-Sell qobe, kodwana ngaphandle kokuthenga ihlelo elizeleko le-PIII, angikaze > waba netjhudu elikhulu. Hlala uqale i-eBay. Okunye okucasulako nge-eBay kukuthi abathengisi abanengi bathi "bazo ukuthunyelwa e-US kwaphela". Kodwana, ngifumene bona nangabe ubuza kuhle, bazo kuvamise ukuthunyelwa lapha. Ukubhadela, yenza i-akhawunti ye-paypal nofana thumela umthengisi idrafti yebhanka yedola le-US. Nginezinto ezinengi ezincani begodu iingcenye ngaleyo ndlela (ngokwesibonelo, ekugcineni ngathola ikhithi yokubeka i-rackmount ye- iseva yami yetheminali ye-DECserver 700 ebengisolo ngiyifuna iminyaka eminengi, isamba se-US$15). Lokha, Kenn -- Isiqhema sabasebenzisi be-Irish Linux: ilug@linux.ie http://www.linux.ie/mailman/listinfo/ilug ukuthola ilwazi lokubhalisa. Umgcini woluhlu: listmaster@linux.ie | L22: http://www.linux.ie/mailman/listinfo/ilug
A23: EMAIL_0017 | B23: English | C23: Original | D23: 0 | E23: legitimate | F23: SpamAssassin | G23: yyyy@example.com | H23: Gary Lawrence Murphy <garym@canada.com> | I23: Tue, 17 Sep 2002 17:50:23 +0100 | J23: Re: Slaughter in the Name of God | K23: Gary Lawrence Murphy said: > >>>>> "S" == Stephen D Williams <sdw@lig.net> writes: > S> A) Which religion is it that can claim no foul actions in its > S> past? Certainly not Christianity, Islam, etc. > Rastafari. > That is, if you concede that of the two founding branches, only the > one founded by the Nyabingi were legit and the others were > thinly-veneered anti-colonial hooligans. > There is also Vietnamese Buddhism, unless you count setting fire to > oneself as a "foul action". What about Tibetan Buddhism BTW? They seem like an awfully nice bunch of chaps (and chapesses). > When we launched the Native Net in 1989, one of the first things we > noticed on networking aboriginal groups around the world is that the > British Army, with the US Army as a proxy by extension, were the > common thread. Where neither was present (physically or through > influence) there /tended/ to be less violence. > > The issue in Ireland is complex, but rest assured that religious > aspects are only a co-incidence of the invader/colonials being > predominantly members of the Royal-headed Anglicans and the aboriginal > population being predominantly members of the Pope-headed Catholics. > The conflict itself has nothing to do with ideology or practice, since > the Anglican Church is a near-identical clone of Catholicism. > > (now I bet that's going to attract some healthy debate ;) Man, I'm not going *there* again ;) I'll agree, though, that the ideology or practices of the religions have very little to do with the conflict. > The same is true of street-gangs: When people are disenfranchised, > it's easier to offer them the Triad as a new family. You get > cellphones, cars, a dry place to live. Triad, biker gangs, mafia, the > IRA, Al Queda ... we've been fighting the War on Terrorism for as long > as there's been commerce, so you'd think we'd /realize/ that > escalation of violence is not a solution. Well said! --j.
A24: EMAIL_0017 | B24: Afrikaans | C24: Translation | D24: 0 | E24: legitimate | F24: SpamAssassin | G24: yyyy@example.com | H24: Gary Lawrence Murphy <garym@canada.com> | I24: Tue, 17 Sep 2002 17:50:23 +0100 | J24: Re: Slagting in die Naam van God | K24: Gary Lawrence Murphy het gesê: > >>>>> "S" == Stephen D Williams <sdw@lig.net> skryf: > S> A) Watter godsdiens kan beweer dat dit geen gemene dade in sy > S> verlede het nie? Beslis nie die Christendom, Islam, ens. nie. > Rastafari. > Dit is, as jy toegee dat van die twee stigtingstakke net die > een wat deur die Nyabingi gestig is, eg was en die ander > antikoloniale boewe met 'n dun lagie vernis was. > Daar is ook Viëtnamese Boeddhisme, tensy jy om jouself aan die brand te steek > as 'n "gemene daad" tel. Wat van Tibettaanse Boeddhisme terloops? Hulle lyk na 'n verskriklik gawe klomp ouens (en meisies). > Toe ons die Native Net in 1989 bekendgestel het, was een van die eerste dinge wat ons > opgemerk het toe ons inheemse groepe regoor die wêreld in 'n netwerk verbind het, dat die > Britse Weermag, met die Amerikaanse Weermag by uitbreiding as plaasvervanger, die > gemeenskaplike draad was. Waar nie een van die twee teenwoordig was nie (fisies of deur > invloed) was daar /gewoonlik/ minder geweld. > > Die kwessie in Ierland is kompleks, maar wees verseker dat godsdienstige > aspekte slegs 'n toeval is van die feit dat die indringers/koloniste > hoofsaaklik lede was van die Anglikane met die koning aan die hoof, en die inheemse > bevolking hoofsaaklik lede van die Katolieke met die Pous aan die hoof. > Die konflik self het niks met ideologie of praktyk te doen nie, aangesien > die Anglikaanse Kerk 'n byna identiese kloon van Katolisisme is. > > (nou wed ek dit gaan 'n gesonde debat uitlok ;) Man, ek gaan nie weer *daarheen* nie ;) Ek sal egter saamstem dat die ideologie of praktyke van die godsdienste baie min met die konflik te doen het. > Dieselfde geld vir straatbendes: wanneer mense ontmagtig is, > is dit makliker om hulle die Triade as 'n nuwe familie aan te bied. Jy kry > selfone, motors, 'n droë plek om te woon. Triades, motorfietsbendes, die mafia, die > IRA, Al Qaeda ... ons veg die Oorlog teen Terreur al so lank > as wat daar handel is, so 'n mens sou dink ons sou /besef/ dat > die eskalasie van geweld nie 'n oplossing is nie. Goed gesê! --j. | M24: 2 | N24: 2
A25: EMAIL_0017 | B25: isiXhosa | C25: Translation | D25: 0 | E25: legitimate | F25: SpamAssassin | G25: yyyy@example.com | H25: Gary Lawrence Murphy <garym@canada.com> | I25: Tue, 17 Sep 2002 17:50:23 +0100 | J25: Re: Ukubulawa eGameni likaThixo | K25: UGary Lawrence Murphy wathi: > >>>>> "S" == Stephen D Williams <sdw@lig.net> ubhala wathi: > S> A) Yiyiphi inkolo enokubanga ukuba ayinazenzo zimbi kwixesha layo > S> elidlulileyo? Ngokuqinisekileyo asiloKrestu, ubuSilamsi, njl. > Rastafari. > Oko kukuthi, ukuba uyavuma ukuba kumasebe amabini asungulayo, kuphela > lelo elasekwa yi-Nyabingi elaliyinyani kwaye amanye ayengamaphukuphuku > alwa nobukoloniyali anengubo ecekethekileyo. > Kukwakho nobuBhedha baseVietnam, ngaphandle kokuba uthatha ukuzitshisa > njenge-"senzo esibi". Kuthekani ngobuBhedha baseTibet ngokunjalo? Babonakala beliqela lamadoda (namabhinqa) anobubele kakhulu. > Xa sasungula i-Native Net ngo-1989, enye yezinto zokuqala esaziqaphelayo > xa sasidibanisa amaqela emveli kwihlabathi liphela yayikukuba > uMkhosi waseBritani, kunye noMkhosi wase-US njengommeli ngokwandiswa, yayingumsonto oqhelekileyo. Apho kungekho namnye kubo (ngokwenyama okanye > ngempembelelo) kwakukholisa ukubakho ubundlobongela obuncinci. > > Umba ose-Ireland unzima, kodwa qiniseka ukuba iinkalo zenkolo > ziziganeko nje zokuhambelana kwenyani yokuba abahlaseli/abakoloniyali > babengamalungu e-Anglikani ekhokelwa nguKumkani kwaye abemi bomthonyama > babengamalungu amaKatolika akhokelwa nguPopu. > Imbambano ngokwayo ayinanto yakwenza nengcamango okanye ukwenza, kuba > iCawa yase-Anglikani iphantse yafana nqo nobuKatolika. > > (ngoku ndiyabheja ukuba oku kuza kutsala ingxoxo-mpikiswano ephilileyo ;) Mfondini, andizukuya *apho* kwakhona ;) Nangona kunjalo ndiyavuma ukuba ingcamango okanye izenzo zeenkolo zinenxaxheba encinci kakhulu kule mbambano. > Kukwanjalo nakwimigulukudu yasezitalatweni: Xa abantu behluthiwe amalungelo, > kulula ukubanika i-Triad njengosapho olutsha. Ufumana > iiselfowuni, iimoto, indawo eyomileyo yokuhlala. I-Triad, imigulukudu yezithuthuthu, i-mafia, i-IRA, > i-Al Qaeda ... kudala silwa iMfazwe noBunqolobi ukusukela oko > kwabakho urhwebo, ngoko ungacinga ukuba siyakwazi ukubona ukuba > ukonyuka kobundlobongela asisosicazululo. Kuthethwe kakuhle! --j.
A26: EMAIL_0018 | B26: English | C26: Original | D26: 0 | E26: legitimate | F26: SpamAssassin | G26: Panu Matilainen <pmatilai@welho.com> | H26: rpm-zzzlist@freshrpms.net | I26: Tue, 08 Oct 2002 11:43:09 +0300 | J26: Re: a problem with apt-get | K26: On Mon, 7 Oct 2002, Thomas Vander Stichele wrote: > Hi, > > In my build scripts, I have problems with some of the kernel packages. > > For kernel-sources, I get : > > Package kernel-source is a virtual package provided by: > kernel-source#2.4.18-3 2.4.18-3 > kernel-source#2.4.18-3 2.4.18-3 > > on running apt-get install kernel-source > > Now, first of all, this doesn't really tell me what the two options are ;) > Second, is there some way I can tell apt-get to install either ? This is > done from automatic build scripts so I'd like it to proceed anyway. That's just apt's way of telling you the package is in "AllowDuplicated", meaning multiple versions of the package can be installed at the same time. Yes the output is a bit strange.. especially when there's only one version available. 'apt-get install kernel-source#2.4.18-3' will install it... -- - Panu - _______________________________________________ RPM-List mailing list <RPM-List@freshrpms.net> http://lists.freshrpms.net/mailman/listinfo/rpm-list | L26: http://lists.freshrpms.net/mailman/listinfo/rpm-list
A27: EMAIL_0018 | B27: Afrikaans | C27: Translation | D27: 0 | E27: legitimate | F27: SpamAssassin | G27: Panu Matilainen <pmatilai@welho.com> | H27: rpm-zzzlist@freshrpms.net | I27: Tue, 08 Oct 2002 11:43:09 +0300 | J27: Re: 'n probleem met apt-get | K27: Op Ma, 7 Okt 2002, het Thomas Vander Stichele geskryf: > Hallo, > > In my bouskripte het ek probleme met sommige van die kernpakkette. > > Vir kernel-sources kry ek: > > Package kernel-source is a virtual package provided by: > kernel-source#2.4.18-3 2.4.18-3 > kernel-source#2.4.18-3 2.4.18-3 > > wanneer ek apt-get install kernel-source laat loop > > Nou, eerstens sê dit nie regtig vir my wat die twee opsies is nie ;) > Tweedens, is daar 'n manier waarop ek apt-get kan sê om enigeen te installeer? Dit word > vanuit outomatiese bouskripte gedoen, so ek wil hê dit moet in elk geval voortgaan. Dit is net apt se manier om jou te sê dat die pakket in "AllowDuplicated" is, wat beteken dat veelvuldige weergawes van die pakket terselfdertyd geïnstalleer kan word. Ja, die uitvoer is 'n bietjie vreemd.. veral wanneer daar net een weergawe beskikbaar is. 'apt-get install kernel-source#2.4.18-3' sal dit installeer... -- - Panu - _______________________________________________ RPM-List-poslys <RPM-List@freshrpms.net> http://lists.freshrpms.net/mailman/listinfo/rpm-list | L27: http://lists.freshrpms.net/mailman/listinfo/rpm-list | M27: 2 | N27: 3
A28: EMAIL_0018 | B28: isiXhosa | C28: Translation | D28: 0 | E28: legitimate | F28: SpamAssassin | G28: Panu Matilainen <pmatilai@welho.com> | H28: rpm-zzzlist@freshrpms.net | I28: Tue, 08 Oct 2002 11:43:09 +0300 | J28: Re: ingxaki nge-apt-get | K28: NgoMvulo, 7 Okt 2002, uThomas Vander Stichele wabhala: > Molo, > > Kwizikripthi zam zokwakha, ndineengxaki ngezinye zeepakheji ze-kernel. > > Kwi-kernel-sources ndifumana: > > Package kernel-source is a virtual package provided by: > kernel-source#2.4.18-3 2.4.18-3 > kernel-source#2.4.18-3 2.4.18-3 > > xa ndiqhuba i-apt-get install kernel-source > > Ngoku, okokuqala oku akundixeleli ngokwenene ukuba zeziphi iinketho ezimbini ;) > Okwesibini, ingaba ikho indlela endifanele ndixelele ngayo i-apt-get ukuba ifakele nokuba yeyiphi na? Oku kwenziwa > kwizikripthi zokwakha ezizenzekelayo, ngoko ndingathanda ukuba iqhubeke nokuba kungenjani. Yindlela nje ye-apt yokukuxelela ukuba iphakheji ikwi-"AllowDuplicated", oku kuthetha ukuba iinguqulelo ezininzi zephakheji zinokufakelwa ngaxeshanye. Ewe, imveliso iyamangalisa kancinci.. ngakumbi xa kukho kuphela inguqulelo enye ekhoyo. 'apt-get install kernel-source#2.4.18-3' iya kuyifakela... -- - Panu - _______________________________________________ Uluhlu lwemeyile lwe-RPM-List <RPM-List@freshrpms.net> http://lists.freshrpms.net/mailman/listinfo/rpm-list | L28: http://lists.freshrpms.net/mailman/listinfo/rpm-list
A29: EMAIL_0019 | B29: English | C29: Original | D29: 0 | E29: legitimate | F29: SpamAssassin | G29: Chris Haun <chris@noskillz.com> | H29: Gregory Alan Bolcer <gbolcer@endeavors.com> | I29: Sat, 28 Sep 2002 12:21:17 -0400 | J29: Re: EBusiness Webforms: cluetrain has left the station | K29: I'll agree that webforms are a pain in the ass, however it would seem to me that the problem with passport is the same one you noted with the autoform function, providing more info than you want to. That and some entity would be holding the passport info, thus have all that data in the first place. Personally i'd never trust them not to at least use it internally to market to me, if not sell/rent out. Just think of the ability they'd have to build a profile for you since everything you went to was tracked to you. And thats just the marketing side of it. Chris On Sat, 28 Sep 2002, Gregory Alan Bolcer wrote: > What's wrong with doing business over the Web? Web forms. There's > promising replacements forms, but this is the current state of the > industry: > > o You find something that you want to fill out. It's a partnership form, > a signup for a Web seminar, a request for more information, anything. > o You start wasting time typing in all those stupid fields and spend > about 10 minutes going through all their stupid qualification hoops > just to get a small piece of information , whitepaper, or a callback > when halfway through, you start to wonder if it's really worth your > time to forever be stuck on their stupid prospect list. > o Pull down tags are never put in order of use instead of alphabetized. > I was on a site just now that had every single country in the world > listed; the selection of your country was absolutely critical for you > to hit submit, but due to the layout, the "more>" tag on the second > row was offscreen so it was impossible to select any country except > about two dozen third world countries. > o Even worse, ever time you hit submit, all forms based things complain > about using the universal country phone number format and will cause > you to re-enter dashes instead of dots. > o When you get something that's not entered right, you will go back and > enter it right, but then some other field or most likely pulldown will > automatically get reset to the default value so that you will have to > go back and resent that freaking thing too. Finally after all combinations > of all pulldowns, you may get a successful submit. > o You wait freaking forever just to get a confirmation. > o Sometimes, like today, you won't be able to ever submit anything due > to it being impossible to ever submit a valid set of information that > is internally non-conflicting according to whatever fhead wrote their > forms submission. > > What's wrong with this picture? The company is screwing you by wasting > your time enforcing their data collection standards on you. I'm sure there's > someone in that company that would be willing to accept "US", "U.S", "USA" > "United States", "U of A", "America", etc. and would know exactly which > freaking country the interested party was from instead of forcing them > to waste even more time playing Web form geography. > > I'm starting to see the light of Passport. You want more information? Hit > this passport button. Voila. IE6 and Netscape 6,7 have pre-forms sutff, > but I always turn it off because you never know when there's that one field > that you don't want to submit to the person you are submitting to that > automatically gets sent, i.e. the privacy stuff is well beyond the > average user who will get screwed on privacy stuff. > > So, if crappy forms-based submission is the state of practice for > business enablement on the Web, I can't see this whole data submission > and hurry up and wait for us to get back to you business process as > working all that well. > > > Greg >
A30: EMAIL_0019 | B30: isiZulu | C30: Translation | D30: 0 | E30: legitimate | F30: SpamAssassin | G30: Chris Haun <chris@noskillz.com> | H30: Gregory Alan Bolcer <gbolcer@endeavors.com> | I30: Sat, 28 Sep 2002 12:21:17 -0400 | J30: Mayelana nama-Webform e-EBusiness: isitimela sesihambile | K30: Ngiyavuma ukuthi amafomu aku-inthanethi ayacasula kakhulu, kodwa kimi kubonakala sengathi inkinga nge-Passport iyafana naleyo oyiphawule ngomsebenzi we-autoform, okungukuthi unikeza ulwazi olungaphezu kwalolo ofuna ukulunikeza. Ngaphezu kwalokho, kukhona inhlangano ezobe iphethe imininingwane ye-Passport, ngakho-ke izobe inayo yonke leyo mininingwane kwasekuqaleni. Ngokwami, ngeke ngibathembe ukuthi ngeke bayisebenzise okungenani ngaphakathi enhlanganweni yabo ukungikhangisela izinto, noma bayidayise noma bayiqashise kwabanye. Cabanga nje ngekhono abangaba nalo lokwakha iphrofayili yakho njengoba yonke into oyivakashelayo yayilandelelwa kuwe. Futhi lokho kunguhlangothi lokukhangisa kuphela lwale ndaba. Chris NgoMgqibelo, mhla zingama-28 kuMandulo (September) 2002, uGregory Alan Bolcer wabhala: Yini inkinga ngokwenza ibhizinisi nge-inthanethi? Amafomu aku-inthanethi. Kukhona izindlela ezintsha ezithembisayo zokuthatha indawo yawo, kodwa yilesi isimo samanje salomkhakha: o Uthola into ofuna ukuyigcwalisa. Kungaba ifomu lobambiswano, ukubhalisela isemina eku-inthanethi, isicelo solwazi olwengeziwe, noma yini. o Uqala ukuchitha isikhathi uthayipha yonke leyo migqa engenangqondo futhi uchitha cishe imizuzu eyi-10 udlula kuzo zonke izinqubo zabo eziyinkimbinkimbi nezingenangqondo ukuze nje uthole ulwazi oluncane, umbiko (whitepaper), noma ucingo olubuyayo, kanti phakathi nendawo, uqala ukuzibuza ukuthi ingabe kuyafanele yini ukuchitha isikhathi sakho ukuze uhlale unomphela ohlwini lwabo lwamakhasimende angaba khona. o Amamenyu okukhetha (pulldown menus) awahlelwa ngokwendlela asetshenziswa ngayo, kodwa ahlelwa ngokwe-alfabhethi. Bengisanda kuvakashela iwebhusayithi ebifaka amazwe wonke omhlaba; ukukhetha izwe lakho bekubaluleke kakhulu ukuze ukwazi ukucindezela inkinobho yokuthumela (submit), kodwa ngenxa yokwakheka kwekhasi, inketho ethi "more>" (okwengeziwe) emgqeni wesibili ibingabonakali esikrinini, ngakho bekungenakwenzeka ukukhetha noma yiliphi izwe ngaphandle kwamazwe ambalwa asathuthuka. o Okubi nakakhulu, njalo uma ucindezela inkinobho yokuthumela, uhlelo lukhononda ngendlela yokubhala inombolo yocingo (ifomethi yamazwe ngamazwe) futhi lukuphoqa ukuthi ufake imigqa emincane (dashes) esikhundleni samachashazi. o Uma kukhona okungafakwanga kahle, ubuyela emuva ukuyilungisa, kodwa bese omunye umugqa noma imenyu yokukhetha ibuyela esimweni sayo sokuqala ngokuzenzakalelayo, okukwenza uphinde ubuyele emuva ukuyilungisa nayo leyo nto ecasulayo. Ekugcineni, ngemva kokuzama zonke izinketho, mhlawumbe uyaphumelela ukuthumela ulwazi. o Ulinda isikhathi eside ngokwedlulele ukuze nje uthole isiqinisekiso. > o Kwesinye isikhathi, njenganamuhla, ngeke ukwazi ukuthumela lutho ngenxa > yokuthi akunakwenzeka ukuthumela imininingwane efanele engangqubuzani > ngaphakathi, kuye ngokuthi ubani lowo owenza uhlelo lokugcwalisa amafomu. > > Yini engalungile ngalokhu? Inkampani ikwenza ube nesikhathi esinzima ngokuchitha > isikhathi sakho ikuphoqa ukuthi ulandele izindinganiso zayo zokuqoqa imininingwane. > Ngiyaqiniseka ukuthi kukhona umuntu kuleyo nkampani ongavuma ukwamukela okuthi > "US", "U.S", "USA", "United States", "U of A", "America", njll., futhi ozoqonda > kahle ukuthi lelo qembu elithintekayo livela kuliphi izwe, kunokuba libaphoqe > ukuthi bachithe isikhathi esengeziwe bedlala umdlalo wokucabanga indawo > ukuze bagcwalise amafomu e-inthanethi. > > Sengiqala ukubona izinzuzo ze-Passport. Ufuna imininingwane eyengeziwe? > Cindezela le nkinobho ye-passport. Sekulungile. I-IE6 ne-Netscape 6, 7 zinazo > izici zokugcwalisa amafomu kusengaphambili, kodwa ngihlale ngizivala ngoba > awusoze wazi ukuthi ikhona yini leyo nkambu (field) ongayifuni ukuyithumela > kumuntu oyithumelela imininingwane kodwa ithunyelwa ngokuzenzakalelayo; > okusho ukuthi izindaba zobumfihlo ziyinkimbinkimbi kakhulu kumsebenzisi > ojwayelekile, okungenzeka ukuthi uzolahlekelwa yilungelo lakhe lobumfihlo. > > Ngakho-ke, uma ukuthumela imininingwane ngamafomu angenamsebenzi kuyindlela > ejwayelekile yokwenza ibhizinisi ku-inthanethi, angiboni sengathi le nqubo > yokuthumela imininingwane bese ulinda isikhathi eside ukuthi babuye kuwe > izosebenza kahle ngempela. > > > Greg >
A31: EMAIL_0020 | B31: English | C31: Original | D31: 0 | E31: legitimate | F31: SpamAssassin | G31: Mark Derricutt <mark@talios.com> | H31: freshrpms <rpm-zzzlist@freshrpms.net> | I31: Sun, 03 Feb 2002 10:19:27 +1300 | J31: creating rpms with subdirs (install command) | K31: Hi, I'm building an rpm for the resin webserver, and I basically want to install the entire tarball under a diretory, but, the tarball includes subdirectorys, in my spec i have: install -s -m 755 %{name}-%{version}.%{release}/* \ $RPM_BUILD_ROOT/usr/local/resin and I'm getting: install: `resin-2.0.5/bin' is a directory install: `resin-2.0.5/conf' is a directory Is there a proper/nice way I should handle this? -- \m/ -- "...if I seem super human I have been misunderstood." (c) Dream Theater mark@talios.com - ICQ: 1934853 JID: talios@myjabber.net _______________________________________________ RPM-List mailing list <RPM-List@freshrpms.net> http://lists.freshrpms.net/mailman/listinfo/rpm-list | L31: http://lists.freshrpms.net/mailman/listinfo/rpm-list
A32: EMAIL_0020 | B32: Afrikaans | C32: Translation | D32: 0 | E32: legitimate | F32: SpamAssassin | G32: Mark Derricutt <mark@talios.com> | H32: freshrpms <rpm-zzzlist@freshrpms.net> | I32: Sun, 03 Feb 2002 10:19:27 +1300 | J32: rpms met subgidse skep (install-opdrag) | K32: Hallo, ek bou 'n rpm vir die resin-webbediener, en ek wil basies die hele tarball onder 'n gids installeer, maar die tarball sluit subgidse in. In my spec het ek: install -s -m 755 %{name}-%{version}.%{release}/* \ $RPM_BUILD_ROOT/usr/local/resin en ek kry: install: `resin-2.0.5/bin' is a directory install: `resin-2.0.5/conf' is a directory Is daar 'n behoorlike/netjiese manier waarop ek dit moet hanteer? -- \m/ -- "...as ek bomenslik lyk, word ek verkeerd verstaan." (c) Dream Theater mark@talios.com - ICQ: 1934853 JID: talios@myjabber.net _______________________________________________ RPM-List-poslys <RPM-List@freshrpms.net> http://lists.freshrpms.net/mailman/listinfo/rpm-list | L32: http://lists.freshrpms.net/mailman/listinfo/rpm-list | M32: 2 | N32: 3
A33: EMAIL_0020 | B33: isiXhosa | C33: Translation | D33: 0 | E33: legitimate | F33: SpamAssassin | G33: Mark Derricutt <mark@talios.com> | H33: freshrpms <rpm-zzzlist@freshrpms.net> | I33: Sun, 03 Feb 2002 10:19:27 +1300 | J33: ukudala ii-rpm ezineenkovu ezingaphantsi (umyalelo we-install) | K33: Molo, ndakha i-rpm yeseva yewebhu ye-resin, kwaye ndifuna ukufakela yonke i-tarball phantsi kolawulo lwefolda, kodwa, i-tarball ibandakanya iifolda ezingaphantsi, kwi-spec yam ndine: install -s -m 755 %{name}-%{version}.%{release}/* \ $RPM_BUILD_ROOT/usr/local/resin kwaye ndifumana: install: `resin-2.0.5/bin' is a directory install: `resin-2.0.5/conf' is a directory Ingaba ikho indlela efanelekileyo/entle endifanele ndikusingathe ngayo oku? -- \m/ -- "...ukuba ndibonakala ndingaphezulu komntu ndiye ndingaqondwa kakuhle." (c) Dream Theater mark@talios.com - ICQ: 1934853 JID: talios@myjabber.net _______________________________________________ Uluhlu lwemeyile lwe-RPM-List <RPM-List@freshrpms.net> http://lists.freshrpms.net/mailman/listinfo/rpm-list | L33: http://lists.freshrpms.net/mailman/listinfo/rpm-list
A34: EMAIL_0021 | B34: English | C34: Original | D34: 0 | E34: legitimate | F34: SpamAssassin | G34: zawodny <rssfeeds@spamassassin.taint.org> | H34: yyyy@spamassassin.taint.org | I34: Tue, 01 Oct 2002 08:01:56 -0000 | J34: FreeBSD or Linux for your MySQL Server? | K34: URL: http://jeremy.zawodny.com/blog/archives/000203.html Date: 2002-09-30T17:22:34-08:00 This is an issue that comes up all the time at work. It is an issue for roughly four reasons: Yahoo is a FreeBSD shop Someone has heard that MySQL runs better on Linux Someone knows that we run some... | L34: http://jeremy.zawodny.com/blog/archives/000203.html
A35: EMAIL_0021 | B35: isiZulu | C35: Translation | D35: 0 | E35: legitimate | F35: SpamAssassin | G35: zawodny <rssfeeds@spamassassin.taint.org> | H35: yyyy@spamassassin.taint.org | I35: Tue, 01 Oct 2002 08:01:56 -0000 | J35: I-FreeBSD noma i-Linux yeseva yakho ye-MySQL? | K35: I-URL: http://jeremy.zawodny.com/blog/archives/000203.html Usuku: 2002-09-30T17:22:34-08:00 Lolu wudaba oluvela njalo emsebenzini. Kuyinkinga ngenxa yezizathu ezicishe zibe zine: I-Yahoo isebenzisa i-FreeBSD; kukhona oye wezwa ukuthi i-MySQL isebenza kangcono ku-Linux; kukhona owaziyo ukuthi sisebenzisa... | L35: http://jeremy.zawodny.com/blog/archives/000203.html
A36: EMAIL_0023 | B36: English | C36: Original | D36: 0 | E36: legitimate | F36: SpamAssassin | G36: "Rose, Bobby" <brose@med.wayne.edu> | H36: razor-users@example.sourceforge.net | I36: Wed, 02 Oct 2002 23:59:01 -0400 | J36: RE: [Razor-users] Fire.cloudmark.com is having issues | K36: What does this mean? I set up procmailrc for a spamtrap but I'm getting an error. I also am reporting to pyzor and dcc and they aren't registering an error. What's weird is that it works sometimes. . Oct 02 23:46:11.470523 report[14051]: [ 4] honor.cloudmark.com >> 20 Oct 02 23:46:11.470805 report[14051]: [ 6] response to sent.3 -res=1 err=230 . Oct 02 23:46:11.471825 report[14051]: [ 5] mail 1, orig_email, special case eng 1: Server accept ed report. Oct 02 23:46:11.472228 report[14051]: [ 8] mail 1.0, eng 4: err 230 - server wants mail ------------------------------------------------------- This sf.net email is sponsored by:ThinkGeek Welcome to geek heaven. http://thinkgeek.com/sf _______________________________________________ Razor-users mailing list Razor-users@lists.sourceforge.net https://lists.sourceforge.net/lists/listinfo/razor-users | L36: http://thinkgeek.com/sf, https://lists.sourceforge.net/lists/listinfo/razor-users
A37: EMAIL_0023 | B37: isiNdebele | C37: Translation | D37: 0 | E37: legitimate | F37: SpamAssassin | G37: "Rose, Bobby" <brose@med.wayne.edu> | H37: razor-users@example.sourceforge.net | I37: Wed, 02 Oct 2002 23:59:01 -0400 | J37: RE: [Razor-users] Fire.cloudmark.com is having issues | K37: Kutjho ukuthini lokhu? Ngisethe i-procmailrc ye-spamtrap kodwana ngithola iphutha. Ngibuye ngibike ku-pyzor ne-dcc kodwana abanjalo ukurejista iphutha. Okumangalisako kukuthi kuyasebenza kesinye isikhathi. . Oct 02 23:46:11.470523 umbiko[14051]: [ 4] honor.cloudmark.com >> 20 Oct 02 23:46:11.470805 umbiko[14051]: [ 6] ipendulo yokuthunyelwa.3 -res=1 err=230 . Oct 02 23:46:11.471825 umbiko[14051]: [ 5] imeyili 1, orig_email, ekhethekileko icala eng 1: Iseva yamukela umbiko ed. Oct 02 23:46:11.472228 umbiko[14051]: [ 8] imeyili 1.0, eng 4: err 230 - iseva ifuna iposi ------------------------------------------------------ I-imeyili ye-sf.net isekelwe yi:ThinkGeek Siyakwamukela ezulwini lama-geek. http://thinkgeek.com/sf _______________________________________________________ Irhelo lokuposa labasebenzisi be-Razor Razor-users@lists.sourceforge.net https://lists.sourceforge.net/lists/listinfo/razor-users | L37: http://thinkgeek.com/sf, https://lists.sourceforge.net/lists/listinfo/razor-users
A38: EMAIL_0024 | B38: English | C38: Original | D38: 0 | E38: legitimate | F38: SpamAssassin | G38: Jesus Climent <jesus.climent@hispalinux.es> | H38: SpamAssassin-devel@example.sourceforge.net | I38: Wed, 28 Aug 2002 22:27:56 +0200 | J38: Re: [SAdev] 2.40: ready for release? *NO* | K38: On Wed, Aug 28, 2002 at 07:42:13PM +0100, Justin Mason wrote: > OK guys -- I reckon it's now Good Enough, modulo some minor score > tweaking, or commenting of some more broken/high-FP-ing rules. > Some make test errors here, too: Failed 6/20 test scripts, 70.00% okay. 17/182 subtests failed, 90.66% okay. J -- Jesus Climent | Unix System Admin | Helsinki, Finland. http://www.HispaLinux.es/~data/ | data.pandacrew.org ------------------------------------------------------ Please, encrypt mail address to me: GnuPG ID: 86946D69 FP: BB64 2339 1CAA 7064 E429 7E18 66FC 1D7F 8694 6D69 ------------------------------------------------------ Registered Linux user #66350 Debian 3.0 & Linux 2.4.19 Look at my fingers: four stones, four crates. Zero stones? ZERO CRATES! --Zorg (The Fifth Element) | L38: http://www.HispaLinux.es/~data/
A39: EMAIL_0024 | B39: isiZulu | C39: Translation | D39: 0 | E39: legitimate | F39: SpamAssassin | G39: Jesus Climent <jesus.climent@hispalinux.es> | H39: SpamAssassin-devel@example.sourceforge.net | I39: Wed, 28 Aug 2002 22:27:56 +0200 | J39: Mayelana ne-[SAdev] 2.40: isilungele ukukhishwa? *CHA* | K39: NgoLwesithathu, mhla zingama-28 ku-Agasti 2002 ngo-07:42:13PM +0100, uJustin Mason wabhala: > Kulungile bafowethu -- Ngicabanga ukuthi sekukuhle ngokwanele, > kudingeka nje ukulungisa kancane amaphuzu, noma ukufaka amazwana > emithethweni engasebenzi kahle noma ekhiqiza imiphumela engalungile (FP) ephezulu. > Kukhona namaphutha okuhlolwa (test errors) lapha: Imibhalo yokuhlola (test scripts) engu-6 kwengama-20 ayiphumelelanga, u-70.00% ulungile. Izivivinyo ezingaphansi (subtests) ezingu-17 kwezingama-182 aziphumelelanga, u-90.66% ulungile. J -- Jesus Climent | Umphathi Wohlelo lwe-Unix | Helsinki, Finland. http://www.HispaLinux.es/~data/ | data.pandacrew.org ------------------------------------------------------ Ngicela ufake ikhodi (encrypt) ekhelini lami le-imeyili: GnuPG ID: 86946D69 FP: BB64 2339 1CAA 7064 E429 7E18 66FC 1D7F 8694 6D69 ------------------------------------------------------ Umsebenzisi we-Linux obhalisiwe #66350 Debian 3.0 & Linux 2.4.19 Bheka iminwe yami: amatshe amane, amabhokisi amane. Awekho amatshe? Awekho namabhokisi! --Zorg (The Fifth Element) | L39: http://www.HispaLinux.es/~data/
A40: EMAIL_0025 | B40: English | C40: Original | D40: 0 | E40: legitimate | F40: SpamAssassin | G40: Anders Eriksson <aeriksson@fastmail.fm> | H40: Chris Garrigues <cwg-dated-1027805573.3ce2ae@DeepEddy.Com>, exmh-workers@redhat.com | I40: Wed, 24 Jul 2002 11:34:52 +0200 | J40: PATCH (was: Re: Another bug) | K40: cwg-dated-1027805573.3ce2ae@DeepEddy.Com said: > I just checked in a code cleanup which doesn't address this issue, > but does take a machete to code right around it. You ought to 'cvs > update' and see if your issue becomes any clearer with all the > brush removed. > My patch notes that 'msgid' and 'line' are redundant with one > another and removes one or the other from functions which takes > both. The callers are then changed to pass what the function > expects. In the case of Msg_Change, the 'line' argument is removed > and we only have the msgid argument. Ftoc_ClearCurrent is now the > first line of MsgChange. The following patch removes Ftoc_RescanLine in favour of a Ftoc_RescanLines. It runs scan(1) on a list of lines and updates ftoc accordingly. The patch also changes all the callers to make use of it. It also changes Ftoc_ClearCurrent to work of an argument instead of falsily clearing a message that's still Current on disk. All in an effort to get a one-to-one disk-display correspondence. It does add ~30 -- ~ 75 ms (~<10%) to the execution time depending on folder size due to the invocation of scan. However this version does not try to second guess the mh version of scan so if you have exotic scanlines it tells the truth. As a side effect the '+' sign now corresponds better to what's on disk. Comments appreciated. I'm going to be offlike for a couple of days, so I send the cvs diff rather than putting it in the cvs. /Anders
A41: EMAIL_0025 | B41: isiZulu | C41: Translation | D41: 0 | E41: legitimate | F41: SpamAssassin | G41: Anders Eriksson <aeriksson@fastmail.fm> | H41: Chris Garrigues <cwg-dated-1027805573.3ce2ae@DeepEddy.Com>, exmh-workers@redhat.com | I41: Wed, 24 Jul 2002 11:34:52 +0200 | J41: Isilungisi (bekuyi: Re: Enye iphutha) | K41: U-cwg-dated-1027805573.3ce2ae@DeepEddy.Com uthe: > Ngisanda kufaka izinguquko zokuhlanza ikhodi ezingayixazululi le nkinga, > kodwa zisusa izingxenye ezingadingekile zekhodi ezizungeze yona. Kufanele wenze i-'cvs > update' ubone ukuthi inkinga yakho icaca kangcono yini ngemva kokususwa > kwalezo zingxenye ezingadingekile. > I-patch yami ikhombisa ukuthi i-'msgid' ne-'line' ziyaphindaphindeka > futhi isusa enye yazo emisebenzini (functions) edinga zombili. > Izingxenye ezibiza lo msebenzi (callers) ziyashintshwa ukuze zidlulisele > lokho okulindelekile ngumsebenzi. Endabeni ye-Msg_Change, i-argument ethi > 'line' iyasuswa futhi siba ne-argument ethi msgid kuphela. I-Ftoc_ClearCurrent > manje isiwumugqa wokuqala we-MsgChange. Le patch elandelayo isusa i-Ftoc_RescanLine bese ifaka i- Ftoc_RescanLines esikhundleni sayo. Isebenzisa i-scan(1) ohlwini lwemigqa futhi ibuyekeza i-ftoc ngokufanele. Le patch iphinde iguqule zonke izindawo ezibiza lo msebenzi ukuze ziwusebenzise. Iphinde iguqule i-Ftoc_ClearCurrent ukuze isebenze nge-argument esikhundleni sokususa ngephutha umyalezo osese-Current kudiski. Konke lokhu kwenzelwa ukwenza kube nokuhambisana okuqondile phakathi kwediski nokuboniswayo. Yengeza cishe u-30 kuya ku-75 ms (cishe <10%) esikhathini sokusebenza kuye ngobukhulu befolda ngenxa yokusebenzisa i-scan. Nokho, le nguqulo ayizami ukuqagela indlela i-mh esebenzisa ngayo i-scan, ngakho uma unemigqa ye-scan engajwayelekile, inikeza imiphumela eyiyo. Njengomphumela, uphawu oluthi '+' manje luhambisana kangcono nalokho okukudiski. Ngiyazisa imibono yenu. Ngizobe ngingekho ku-inthanethi izinsuku ezimbalwa, ngakho ngithumela i-cvs diff esikhundleni sokuyifaka ngqo ku-cvs. /Anders
A42: EMAIL_0026 | B42: English | C42: Original | D42: 0 | E42: legitimate | F42: SpamAssassin | G42: Peter Peltonen <pisara@iki.fi> | H42: rpm-zzzlist@freshrpms.net | I42: Wed, 06 Feb 2002 18:51:52 +0200 | J42: Re: Apt problems | K42: On Wed, Feb 06, 2002 at 04:14:27PM +0100, Matthias Saou wrote: > Strange... all my openssh packages don't explicitly requires a version of > openssl. What version of openssh do you have? Is it an official Red Hat > package? I suppose it isn't, and using Red Hat's rpms will solve your > problem. openssh-3.0.2p1-1 I think that is directly from openssh site. It's from the RH 6.2 that I upgraded to 7.2 (6.2 doesn't ship with openssh...). I probably should downgrade to the versoin RH provides except I can't do that as I don't have physical access to that box and downgrading ssh packages over ssh doesn't sound like a bright idea... -- Peter _______________________________________________ RPM-List mailing list <RPM-List@freshrpms.net> http://lists.freshrpms.net/mailman/listinfo/rpm-list | L42: http://lists.freshrpms.net/mailman/listinfo/rpm-list
A43: EMAIL_0026 | B43: isiZulu | C43: Translation | D43: 0 | E43: legitimate | F43: SpamAssassin | G43: Peter Peltonen <pisara@iki.fi> | H43: rpm-zzzlist@freshrpms.net | I43: Wed, 06 Feb 2002 18:51:52 +0200 | J43: Mayelana nezinkinga zefulethi | K43: NgoLwesithathu, mhla zi-6 kuNhlolanja (Feb) 2002 ngo-04:14:27 PM +0100, uMatthias Saou wabhala: > Kuyamangaza... wonke amaphakheji ami e-openssh awadingi ngokuqondile uhlobo oluthile > lwe-openssl. Uhlobo luni lwe-openssh onalo? Ingabe yiphakheji esemthethweni yakwa-Red Hat? > Ngicabanga ukuthi akuyona, futhi ukusebenzisa ama-rpm akwa-Red Hat kuzoxazulula inkinga yakho. openssh-3.0.2p1-1 Ngicabanga ukuthi lokho kuqondile kusayithi le-openssh. Kuvela ku-RH 6.2 engayithuthukisela ku-7.2 (i-6.2 ayizi ne-openssh...). Mhlawumbe kufanele ngibuyele emuva ohlotsheni olunikezwa yi-RH, kodwa angikwazi ukwenza lokho ngoba angikwazi ukufinyelela ngqo kuleyo khompyutha, futhi ukwehlisa uhlobo (downgrade) lwamaphakheji e-ssh usebenzisa i-ssh akuzwakali njengombono omuhle... -- Peter _______________________________________________ Uhlu lwe-imeyili lwe-RPM-List <RPM-List@freshrpms.net> http://lists.freshrpms.net/mailman/listinfo/rpm-list | L43: http://lists.freshrpms.net/mailman/listinfo/rpm-list
A44: EMAIL_0027 | B44: English | C44: Original | D44: 0 | E44: legitimate | F44: SpamAssassin | G44: guardian <rssfeeds@spamassassin.taint.org> | H44: yyyy@spamassassin.taint.org | I44: Mon, 07 Oct 2002 08:00:50 -0000 | J44: Tory leader risks all on 80s revival | K44: URL: http://www.newsisfree.com/click/-1,8622116,215/ Date: 2002-10-07T03:53:00+01:00 Iain Duncan Smith will this week gamble his political future on a return to the Thatcher revolution of the 80s. | L44: http://www.newsisfree.com/click/-1,8622116,215/
A45: EMAIL_0027 | B45: Afrikaans | C45: Translation | D45: 0 | E45: legitimate | F45: SpamAssassin | G45: guardian <rssfeeds@spamassassin.taint.org> | H45: yyyy@spamassassin.taint.org | I45: Mon, 07 Oct 2002 08:00:50 -0000 | J45: Tory-leier waag alles op herlewing van die 80's | K45: URL: http://www.newsisfree.com/click/-1,8622116,215/ Datum: 2002-10-07T03:53:00+01:00 Iain Duncan Smith sal hierdie week sy politieke toekoms waag op 'n terugkeer na die Thatcher-rewolusie van die 80's. | L45: http://www.newsisfree.com/click/-1,8622116,215/ | M45: 3 | N45: 3
A46: EMAIL_0027 | B46: isiXhosa | C46: Translation | D46: 0 | E46: legitimate | F46: SpamAssassin | G46: guardian <rssfeeds@spamassassin.taint.org> | H46: yyyy@spamassassin.taint.org | I46: Mon, 07 Oct 2002 08:00:50 -0000 | J46: Inkokeli yama-Tory ibeka yonke into emngciphekweni ekuvuseleleni iminyaka yoo-80 | K46: I-URL: http://www.newsisfree.com/click/-1,8622116,215/ Umhla: 2002-10-07T03:53:00+01:00 UIain Duncan Smith kule veki uza kubeka ikamva lakhe lezopolitiko emngciphekweni ngokubuyela kwinguquko ka-Thatcher yeminyaka yoo-80. | L46: http://www.newsisfree.com/click/-1,8622116,215/
A47: EMAIL_0028 | B47: English | C47: Original | D47: 0 | E47: legitimate | F47: SpamAssassin | G47: Skip Montanaro <skip@pobox.com> | H47: Daniel Quinlan <quinlan@pathname.com> | I47: Thu, 29 Aug 2002 00:44:53 -0500 | J47: Re: [SAtalk] O.T. Habeus -- Why? | K47: DanQ> I think it would make more sense to start Habeas with a less DanQ> aggressive score (one which will not give spammers a quick path DanQ> into everyone's inbox) and after we've seen evidence that the DanQ> system works, then we can increase the magnitude of the score. Better yet, let the GA figure out the correct score. ;-) That will obviously take awhile since you'll have to acquire enough messages with it, but it should give you a good idea if the presence of Habeus headers are good spam indicators or not. If they are, my guess is that Habeus will probably not succeed. Taking things further off-topic: Does Habeus charge a license fee to organizations who want to use their copyrighted material or is their sole revenue stream to come from legal judgements? On the one hand, if they charge license fees, I'd worry that when times got tough they'd be somewhat less critical of organizations we'd call spammers today in order to generate license fees. If not, I'd worry the pendulum would swing the other way and they'd go after legitimate businesses in an attempt to generate more revenues from judgements and/or out of court settlements. Either way, it seems like they have an interesting tightrope to walk. -- Skip Montanaro skip@pobox.com consulting: http://manatee.mojam.com/~skip/resume.html ------------------------------------------------------- This sf.net email is sponsored by:ThinkGeek Welcome to geek heaven. http://thinkgeek.com/sf _______________________________________________ Spamassassin-talk mailing list Spamassassin-talk@lists.sourceforge.net https://lists.sourceforge.net/lists/listinfo/spamassassin-talk | L47: http://manatee.mojam.com/~skip/resume.html, http://thinkgeek.com/sf, https://lists.sourceforge.net/lists/listinfo/spamassassin-talk
A48: EMAIL_0028 | B48: Afrikaans | C48: Translation | D48: 0 | E48: legitimate | F48: SpamAssassin | G48: Skip Montanaro <skip@pobox.com> | H48: Daniel Quinlan <quinlan@pathname.com> | I48: Thu, 29 Aug 2002 00:44:53 -0500 | J48: Re: [SAtalk] Van die onderwerp af: Habeus -- hoekom? | K48: DanQ> Ek dink dit sal meer sin maak om Habeas met 'n minder DanQ> aggressiewe telling te begin (een wat nie vir strooiposers 'n vinnige pad DanQ> na almal se inkassie sal gee nie) en nadat ons bewys gesien het dat die DanQ> stelsel werk, kan ons die grootte van die telling verhoog. Nog beter, laat die GA die korrekte telling uitwerk. ;-) Dit sal natuurlik 'n rukkie neem omdat jy genoeg boodskappe daarmee sal moet bekom, maar dit behoort jou 'n goeie idee te gee of die teenwoordigheid van Habeus-opskrifte goeie strooipos- aanwysers is of nie. As dit so is, is my raaiskoot dat Habeus waarskynlik nie sal slaag nie. Om dinge verder van die onderwerp af te neem: Vra Habeus 'n lisensiefooi van organisasies wat hul materiaal met kopiereg wil gebruik, of moet hul enigste inkomstestroom uit hofuitsprake kom? Aan die een kant, as hulle lisensiefooie vra, sal ek bekommerd wees dat hulle, wanneer tye moeilik raak, ietwat minder krities sal wees teenoor organisasies wat ons vandag strooiposers sou noem, om lisensiefooie te genereer. Indien nie, sal ek bekommerd wees dat die slinger na die ander kant sal swaai en hulle wettige ondernemings sal agtervolg in 'n poging om meer inkomste uit hofuitsprake en/of skikkings buite die hof te genereer. Hoe dit ook al sy, dit lyk of hulle 'n interessante koord moet loop. -- Skip Montanaro skip@pobox.com konsultasie: http://manatee.mojam.com/~skip/resume.html ------------------------------------------------------- Hierdie sf.net-e-pos word geborg deur: ThinkGeek Welkom in die geek-hemel. http://thinkgeek.com/sf _______________________________________________ Spamassassin-talk-poslys Spamassassin-talk@lists.sourceforge.net https://lists.sourceforge.net/lists/listinfo/spamassassin-talk | L48: http://manatee.mojam.com/~skip/resume.html, http://thinkgeek.com/sf, https://lists.sourceforge.net/lists/listinfo/spamassassin-talk | M48: 3 | N48: 2
A49: EMAIL_0028 | B49: isiXhosa | C49: Translation | D49: 0 | E49: legitimate | F49: SpamAssassin | G49: Skip Montanaro <skip@pobox.com> | H49: Daniel Quinlan <quinlan@pathname.com> | I49: Thu, 29 Aug 2002 00:44:53 -0500 | J49: Re: [SAtalk] Ngaphandle komxholo: Habeus -- Kutheni? | K49: DanQ> Ndicinga ukuba kuya kuba nengqondo ngakumbi ukuqala i-Habeas ngamanqaku angengoburhalarhume DanQ> (alawo angayi kunika abathumeli be-spam indlela ekhawulezayo DanQ> eya kwi-inbox yomntu wonke) kwaye emva kokuba sibone ubungqina bokuba inkqubo DanQ> iyasebenza, ngoko sinokwandisa ubukhulu bamanqaku. Kungcono kakhulu, vumela i-GA ifumane amanqaku achanekileyo. ;-) Oko kuya kuthatha ixesha elithile ngokuqinisekileyo kuba kuya kufuneka ufumane imiyalezo eyaneleyo nayo, kodwa kufanele kukunike umbono olungileyo wokuba ubukho bezihloko ze-Habeus zizikhombisi ezilungileyo ze-spam okanye hayi. Ukuba zinjalo, uqikelelo lwam lelokuba i-Habeus ayiyi kuphumelela mhlawumbi. Ukuthatha izinto ngaphaya komxholo: Ingaba i-Habeus ibiza umrhumo welayisensi kwiintlangano ezifuna ukusebenzisa izinto zabo ezinamalungelo okukhuphela okanye ingeniso yabo kuphela iphuma kwizigwebo zasenkundleni? Kwelinye icala, ukuba babiza irhafu yelayisensi, ndiza kukhathazeka kukuba xa amaxesha eba nzima baya kuba kancinci okugxeka imibutho esinokuyibiza ngokuba ngabathumeli be-spam namhlanje ukuze bafumane imirhumo yelayisensi. Ukuba akunjalo, ndiza kukhathazeka kukuba ipendulum iza kujikela kwelinye icala kwaye baya kulandela amashishini asemthethweni ngenzame zokufumana ingeniso engakumbi kwizigwebo kunye/okanye kwiindawo zokuhlala ezingaphandle kwenkundla. Nokuba yeyiphi na indlela, kubonakala ngathi banentambo enomdla ekufuneka behambe kuyo. -- Skip Montanaro skip@pobox.com ukucebisa: http://manatee.mojam.com/~skip/resume.html ------------------------------------------------------- Le imeyile ye-sf.net ixhaswe ngu: ThinkGeek Wamkelekile kwizulu le-geek. http://thinkgeek.com/sf _______________________________________________ Uluhlu lwemeyile lwe-Spamassassin-talk Spamassassin-talk@lists.sourceforge.net https://lists.sourceforge.net/lists/listinfo/spamassassin-talk | L49: http://manatee.mojam.com/~skip/resume.html, http://thinkgeek.com/sf, https://lists.sourceforge.net/lists/listinfo/spamassassin-talk
A50: EMAIL_0029 | B50: English | C50: Original | D50: 0 | E50: legitimate | F50: SpamAssassin | G50: Peter Peltonen <pisara@iki.fi> | H50: rpm-zzzlist@freshrpms.net | I50: Mon, 04 Feb 2002 23:30:01 +0200 | J50: Re: About apt, kernel updates and dist-upgrade | K50: On Mon, Feb 04, 2002 at 04:53:14PM +0100, Matthias Saou wrote: > It skips it. See the /etc/apt/apt.conf file for this. In my apt.conf reads: --<snip>-- RPM { // Leave list empty to disable AllowedDupPkgs {"^kernel$"; "kernel-smp"; "kernel-enterprise"; }; HoldPkgs {"kernel-source"; "kernel-headers"; }; } --</snip>-- If I understand this correctly, then only kernel-source and kernel-headers are held from being installed, but kernel will be installed, right? Maybe I should test this on some vanilla system... -- Peter _______________________________________________ RPM-List mailing list <RPM-List@freshrpms.net> http://lists.freshrpms.net/mailman/listinfo/rpm-list | L50: http://lists.freshrpms.net/mailman/listinfo/rpm-list
A51: EMAIL_0029 | B51: isiZulu | C51: Translation | D51: 0 | E51: legitimate | F51: SpamAssassin | G51: Peter Peltonen <pisara@iki.fi> | H51: rpm-zzzlist@freshrpms.net | I51: Mon, 04 Feb 2002 23:30:01 +0200 | J51: Mayelana ne-apt, izibuyekezo ze-kernel kanye ne-dist-upgrade | K51: NgoMsombuluko, mhla zi-4 kuNhlolanja (Feb) 2002 ngo-04:53:14 ntambama +0100, uMatthias Saou wabhala: > Iyayeqa lokho. Bheka ifayela elithi /etc/apt/apt.conf ngalokhu. Kufayela lami le-apt.conf kulotshwe kanje: --<snip>-- RPM { // Shiya uhlu lungenalutho ukuze uluvale (disable) AllowedDupPkgs {"^kernel$"; "kernel-smp"; "kernel-enterprise"; }; HoldPkgs {"kernel-source"; "kernel-headers"; }; } --</snip>-- Uma ngikuqonda kahle lokhu, kusho ukuthi yi-kernel-source ne-kernel-headers kuphela ezivinjelwe ukuthi zingafakwa, kodwa i-kernel yona izofakwa, akunjalo? Mhlawumbe kufanele ngikuhlole lokhu ohlelweni olujwayelekile (olungashintshiwe)... -- Peter _______________________________________________ Uhlu lwe-imeyili lwe-RPM-List <RPM-List@freshrpms.net> http://lists.freshrpms.net/mailman/listinfo/rpm-list | L51: http://lists.freshrpms.net/mailman/listinfo/rpm-list
A52: EMAIL_0030 | B52: English | C52: Original | D52: 0 | E52: legitimate | F52: SpamAssassin | G52: James Rogers <jamesr@best.com> | H52: fork@spamassassin.taint.org | I52: Wed, 31 Jul 2002 16:02:01 -0700 | J52: Re: What's cool about doing nothing | K52: On Wed, 2002-07-31 at 15:16, Elias Sinderson wrote: > Heh. Never mind the perfectly good desert in the southwest, right? Or is > that area too hot for desert warfare training? I'll never understand. The primary desert warfare facilities and schools ARE in the Southwest, most notably Fort Irwin deep in the Mojave/Anza Borrego (the headquarters and core training facilities for all things desert warfare related), and have been for a long time. There are two reasons that immediately come to mind as to why they do not use the Fort Irwin, Edwards AFB, and other expanses of desert that they have traditionally used for desert warfare training and exercises. The first is logistical: Virtually all the mechanized infantry units are located east of the Rockies, and it must be very expensive to move entire heavy combat divisions a couple thousand miles every time they want to run training exercises. This is particularly true since so much of our military is made up of reserve components these days, meaning that you can't move the soldiers to where the training facilities are. The second is environmental lawsuits and pending judicial action and injunctions. The desert training facilities in the Southwest deserts have been aggressively assaulted by environmental organizations who are making the case that heavy mechanized units zipping back and forth across the deep desert endanger the desert tortoise and a bunch of other theoretically endangered species that are concentrated in the southwest deserts. The ability of the military to use the desert facilities has been significantly impeded these days while all the lawsuits and whatnot with the various environmental groups are being sorted out. -James Rogers jamesr@best.com http://xent.com/mailman/listinfo/fork | L52: http://xent.com/mailman/listinfo/fork
A53: EMAIL_0030 | B53: isiZulu | C53: Translation | D53: 0 | E53: legitimate | F53: SpamAssassin | G53: James Rogers <jamesr@best.com> | H53: fork@spamassassin.taint.org | I53: Wed, 31 Jul 2002 16:02:01 -0700 | J53: Mayelana: Yini ehle ngokungenzi lutho | K53: NgoLwesithathu, 2002-07-31 ngo-15:16, u-Elias Sinderson wabhala: > Heh. Ungalokothi ucabange ngogwadule oluhle kakhulu eningizimu-ntshonalanga, akunjalo? Noma kunjalo > leyo ndawo ishisa kakhulu ekuqeqesheni impi yasogwadule? Angisoze ngaqonda. Izikhungo zempi zasogwadule kanye nezikole ZIseNingizimu-ntshonalanga, ikakhulukazi i-Fort Irwin ejulile ku-Mojave/Anza Borrego (the indlunkulu kanye nezikhungo zokuqeqesha eziyinhloko zazo zonke izinto ze-desert war okuhlobene), futhi sekunesikhathi eside. Kunezizathu ezimbili zokuthi ngokushesha ufika engqondweni ukuthi kungani bengasebenzisi i-Fort Irwin, Edwards AFB, nezinye izindawo eziwugwadule abanazo ngokwesiko esetshenziselwa ukuqeqeshwa kwempi yasogwadule kanye nokuzivocavoca. Owokuqala ungowokusebenza: Cishe wonke amayunithi ahamba ngemishini anjalo etholakala empumalanga yamaRockies, futhi kufanele kubize kakhulu ukuhambisa yonke imikhakha yokulwa esindayo izinkulungwane ezimbalwa zamamayela njalo lapho bafuna ukugijima izivivinyo zokuqeqesha. Lokhu kuyiqiniso ikakhulukazi kusukela kakhulu wezempi yethu yakhiwe izingxenye reserve kulezi zinsuku, okusho ukuthi awukwazi ukuhambisa amasosha lapho kukhona izikhungo zokuqeqesha. Okwesibili amacala emvelo kanye nezinyathelo zokwahlulela ezisalindile kanye imiyalelo. Izikhungo zokuqeqesha ogwadule ezinkangala eziseNingizimu-ntshonalanga bahlaselwe kabuhlungu yizinhlangano zezemvelo ezi ukwenza icala ukuthi amayunithi esindayo mechanized zipping emuva naphambili ngaphesheya kogwadule olujulile beka engozini ufudu lwasogwadule kanye nenqwaba yezinye ngokomcabango izilwane ezisengozini yokushabalala ezigxile eningizimu-ntshonalanga izingwadule. Ikhono lezempi lokusebenzisa izindawo zasogwadule linakho kuphazamiseke kakhulu kulezi zinsuku ngenkathi wonke amacala kanye nokunye namaqembu ahlukahlukene emvelo ayalungiswa. - UJames Rogers jamesr@best.com http://xent.com/mailman/listinfo/fork | L53: http://xent.com/mailman/listinfo/fork
A54: EMAIL_0031 | B54: English | C54: Original | D54: 0 | E54: legitimate | F54: SpamAssassin | G54: Jesse Keating <hosting@j2solutions.net> | H54: rpm-zzzlist@freshrpms.net | I54: Mon, 07 Oct 2002 10:38:31 -0700 | J54: Re: RH 8 no DMA for DVD drive | K54: On Mon, 7 Oct 2002 19:28:51 +0200 Matthias Saou <matthias@rpmforge.net> wrote: # I've never heard of any CD-ROM or DVD-ROM drive having problems with # DMA... although there probably is since Red Hat decided to default # disabling it a few releases back :-/ When I worked as a PC repair tech for a Computer store chain, I did run across quite a few DVD drives that would lock up if DMA was enabled. It's more of a chipset/drive problem than a Drive by itself. -- Jesse Keating j2Solutions.net Mondo DevTeam (www.mondorescue.org) Was I helpful? Let others know: http://svcs.affero.net/rm.php?r=jkeating _______________________________________________ RPM-List mailing list <RPM-List@freshrpms.net> http://lists.freshrpms.net/mailman/listinfo/rpm-list | L54: http://lists.freshrpms.net/mailman/listinfo/rpm-list, http://svcs.affero.net/rm.php?r=jkeating
A55: EMAIL_0031 | B55: isiZulu | C55: Translation | D55: 0 | E55: legitimate | F55: SpamAssassin | G55: Jesse Keating <hosting@j2solutions.net> | H55: rpm-zzzlist@freshrpms.net | I55: Mon, 07 Oct 2002 10:38:31 -0700 | J55: Mayelana ne-RH 8: Akukho DMA yedrayivu ye-DVD | K55: NgoMsombuluko, mhla zi-7 kuMfumfu 2002 19:28:51 +0200 U-Matthias Saou <matthias@rpmforge.net> wabhala: # Angikaze ngizwe ngedrayivu ye-CD-ROM noma ye-DVD-ROM enezinkinga nge- # DMA... nakuba kungenzeka ukuthi zikhona njengoba i-Red Hat yanquma ukuyivala # ngokuzenzakalelayo ezinhlelweni ezimbalwa ezedlule :-/ Ngesikhathi ngisebenza njengochwepheshe wokulungisa amakhompyutha esitolo esikhulu samakhompyutha, ngahlangabezana namadrayivu e-DVD amaningana ayeyeka ukusebenza (lock up) uma i-DMA ivuliwe. Kuyinkinga ehlobene ne-chipset/idrayivu kunokuba kube yinkinga yedrayivu uqobo lwayo. -- Jesse Keating j2Solutions.net Mondo DevTeam (www.mondorescue.org) Ingabe ngisizile? Yazisa abanye: http://svcs.affero.net/rm.php?r=jkeating _______________________________________________ Uhlu lwe-imeyili lwe-RPM-List <RPM-List@freshrpms.net> http://lists.freshrpms.net/mailman/listinfo/rpm-list | L55: http://lists.freshrpms.net/mailman/listinfo/rpm-list, http://svcs.affero.net/rm.php?r=jkeating
A56: EMAIL_0032 | B56: English | C56: Original | D56: 0 | E56: legitimate | F56: SpamAssassin | G56: John Hall <johnhall@evergo.net> | H56: FoRK <fork@spamassassin.taint.org> | I56: Mon, 23 Sep 2002 20:56:41 -0700 | J56: liberal defnitions | K56: Depends on how much over spending vs. how much (and what type) over regulation. The biggest problem with over regulation is the costs can be invisible. It also has the ability to single out particular people, while over spending spreads the damage more evenly. Rent control would be an example of a regulation solution that is in general worse than spending tons of money on public housing. As for the definition of a liberal being someone who seeks to impose both, I find no fault in that definition whatsoever. The opinion that EITHER we are spending too much OR we have too much regulation is pretty much anathema to liberal politics. Finally, those who argue that there are private replacements for much government regulation are not saying that a state of nature (no private replacements, no government regulation) is better than government regulation itself. And in my experience people who label themselves 'Green' (which does not include everyone who loves trees and thinks smokestacks are ugly) is a watermelon. > -----Original Message----- > From: fork-admin@xent.com [mailto:fork-admin@xent.com] On Behalf Of Geege > Schuman > > funny. i read it as green = red, as in accounting, as in fiscally > irresponsible. which do you think is the worse indictment - > overregulation > or overspending? there are many (dickheads) who buy into the > neo-conservative media's (fox's) definiton of "liberal" as "one who seeks > to > impose both."
A57: EMAIL_0032 | B57: isiNdebele | C57: Translation | D57: 0 | E57: legitimate | F57: SpamAssassin | G57: John Hall <johnhall@evergo.net> | H57: FoRK <fork@spamassassin.taint.org> | I57: Mon, 23 Sep 2002 20:56:41 -0700 | J57: liberal defnitions | K57: Kuya ngokuthi usebenzise imali engakanani ngokudlula umthethomgomo. Inkinga ekulu ngokulawula khulu kukuthi iindleko zingabonakali. Ibuye ibe nekghono lokukhetha abantu abathileko, ngesikhathi ukusebenzisa imali kurhatjha umonakalo ngokulinganako. Ukulawulwa kwerenti kungaba isibonelo sesisombululo somthetho esibi ukudlula ukusebenzisa imali amathani wemali yezindlu zomphakathi. Malungana nehlathululo yomuntu okhululekileko njengomuntu ofuna ukugandelela kokubili, angitholi iphutha kiyo leyo ncazelo. Umbono othi NOMA sisebenzisa imali enengi khulu NOFANA sinemithetho enengi khulu kuhle ukuhlambalaza okukhulu kwepolotiki ekhululekileko. Ekugcineni, labo abaphikisana ngokuthi kunezinto ezingasese ezijamiselelako ezinengi imithetho karhulumende ayitjho bona ubujamo bemvelo (akukho ngasese ukuthatha indawo, akukho mthetho karhulumende) kungcono kukarhulumende umthetho ngokwawo. Begodu ngokuhlangabezanwe nakho kwami ​​abantu abazibiza ngokuthi 'Baluhlaza' (okungasi faka woke umuntu othanda imithi begodu ucabanga bona ama-smokestacks mabi) ikhabe. > -----Umlayezo wekuthomeni----- > Kusuka ku: fork-admin@xent.com [mailto:fork-admin@xent.com] Egameni le Geege > Schuman > > kuyahlekisa. ngiyifunde njengohlaza = obomvu, njenge-akhawunti, njenge-zezimali > ukungabi nomthwalo wemfanelo. ucabanga bona ngiliphi icala elimbi khulu - > ukulawula ngokweqileko > nofana ukusebenzisa imali ngokweqileko? banengi (ama-dickheads) abathenga > ihlathululo ye-neo-conservative media's (fox) "liberal" "njengomuntu ufuna > ukuya > beka kokubili."
A58: EMAIL_0033 | B58: English | C58: Original | D58: 0 | E58: legitimate | F58: SpamAssassin | G58: Vipul Ved Prakash <mail@vipul.net> | H58: Marc Perkel <marc@perkel.com> | I58: Fri, 02 Aug 2002 15:11:50 -0700 | J58: Re: [Razor-users] False Positives on EFF Messages | K58: Hi Marc, There have been several changes in the trust system recently. We'll start seeing confidence values published with signatures from tomorrow morning (around 4AM). This should be resolved then. Please revoke anything you don't consider spam. It reduces the trust of the person who reported it as well as the confidence of the signature. cheers, vipul. On Fri, Aug 02, 2002 at 03:01:42PM -0700, Marc Perkel wrote: > Hi everyone, > > I'm the systems admin for the Electronic Frontier Foundation and I'm using razor > running under spam assassin there and one my own personal server. Generally it > works fine with near 0 false positives - except - that almost all the false > positives I've seen are on messages that originated at EFF. > > So - I am wondering why RAZOR is catching EFF email and how is this happening. > Below is an example of what I'm talking about. > > --------------------------------- > > Envelope-to: pcn@virtualrecordings.com > X-Sender: robin@mail.eff.org > X-Mailer: QUALCOMM Windows Eudora Version 5.1 > To: eff-ip@eff.org > From: Robin Gross <robin@eff.org> > Subject: [E-IP] HP backs off DMCA threat - CNET.com > Sender: eff-ip-admin@eff.org > X-BeenThere: eff-ip@eff.org > X-Mailman-Version: 2.0.11 > List-Unsubscribe: <https://www.eff.org/mailman/listinfo/eff-ip>, > <mailto:eff-ip-request@eff.org?subject=unsubscribe> > List-Id: Intelectual Property <eff-ip.eff.org> > List-Post: <mailto:eff-ip@eff.org> > List-Help: <mailto:eff-ip-request@eff.org?subject=help> > List-Subscribe: <https://www.eff.org/mailman/listinfo/eff-ip>, > <mailto:eff-ip-request@eff.org?subject=subscribe> > List-Archive: <https://www.eff.org/mailman/private/eff-ip/> > X-Original-Date: Fri, 02 Aug 2002 10:15:12 -0700 > Date: Fri, 02 Aug 2002 10:15:12 -0700 > X-Spam-Status: Yes, hits=7.1 required=5.0 > tests=MAILTO_LINK,RAZOR_CHECK > version=2.40 > X-Spam-Flag: YES > X-Spam-Level: ******* > X-Spam-Checker-Version: SpamAssassin 2.40 (devel $Id: SpamAssassin.pm,v 1.108 > 2002/07/29 16:25:10 jmason Exp $) > X-Spam-Report: Detailed Report > SPAM: -------------------- Start SpamAssassin results ---------------------- > SPAM: This mail is probably spam. The original message has been altered > SPAM: so you can recognise or block similar unwanted mail in future. > SPAM: See http://spamassassin.org/tag/ for more details. > SPAM: > SPAM: Content analysis details: (7.1 hits, 5 required) > SPAM: MAILTO_LINK (0.1 points) BODY: Includes a URL link to send an > email > SPAM: RAZOR_CHECK (7.0 points) Listed in Razor, see > http://razor.sourceforge.net/ > SPAM: > SPAM: -------------------- End of SpamAssassin results --------------------- > X-Spam: [SPAM] - Spam Assassin > > > > http://news.com.com/2100-1023-947740.html > > Document: HP backs off DMCA threat > > By CNET News.com Staff > August 1, 2002, 6:10 PM PT > > Hewlett-Packard Thursday abandoned legal threats it made against security > analysts who publicized flaws in the company's software. > > In a statement released late Thursday, HP said it would not use the Digital > Millennium Copyright Act (DMCA), a controversial copyright law, to pursue a > loosely-organized team of researchers who demonstrated a bug in the company's > Tru64 Unix operating system. > > The following is the company's statement: > > 1) HP is committed to protecting our customer's security environments. > > 2) We have verified that there is a security vulnerability with Tru64 UNIX, the > details of which were brought to our attention July 18. The problem has now been > isolated and HP has been preparing a fix, which will be available within the > next 48 hours. > > 3) We won't comment on the specifics of our discussions with SnoSoft. However, > we take our customers' security requirements very seriously and have a strong > track record following industry-standard security practices. > > 4) Where and how the DMCA should be applied is a matter of great controversy. > The reported letter to SnoSoft was not consistent or indicative of HP's policy. > We can say emphatically that HP will not use the DMCA to stifle research or > impede the flow of information that would benefit our customers and improve > their system security. > > > > ~~~~~~~~~~~~~~~~~~~~~~~~~~~~~~~~~~~~~~~~~~~~~~~~~~~~~~ > Robin D. Gross - Cyberspace Attorney @ Law - Intellectual Property > Director - Campaign for Audiovisual Free Expression (CAFE) > Electronic Frontier Foundation > 454 Shotwell Street, San Francisco, CA 94110 > e: robin@eff.org w: http://www.eff.org > p: 415.863.5459 f: 415.436.9993 > http://www.eff.org/cafe > http://www.eff.org/IP/Open_licenses > ~~~~~~~~~~~~~~~~~~~~~~~~~~~~~~~~~~~~~~~~~~~~~~~~~~~~~~~ > > > > > > > ------------------------------------------------------- > This sf.net email is sponsored by:ThinkGeek > Welcome to geek heaven. > http://thinkgeek.com/sf > _________________________________ | L58: http://news.com.com/2100-1023-947740.html, http://razor.sourceforge.net/, http://spamassassin.org/tag/, http://thinkgeek.com/sf, http://www.eff.org, http://www.eff.org/IP/Open_licenses, http://www.eff.org/cafe, https://www.eff.org/mailman/listinfo/eff-ip, https://www.eff.org/mailman/private/eff-ip/
A59: EMAIL_0033 | B59: Afrikaans | C59: Translation | D59: 0 | E59: legitimate | F59: SpamAssassin | G59: Vipul Ved Prakash <mail@vipul.net> | H59: Marc Perkel <marc@perkel.com> | I59: Fri, 02 Aug 2002 15:11:50 -0700 | J59: Re: [Razor-users] Vals positiewe op EFF-boodskappe | K59: Hallo Marc, Daar was onlangs verskeie veranderinge in die vertrouenstelsel. Ons sal vanaf môreoggend (omtrent 04:00) sien dat vertrouenswaardes saam met handtekeninge gepubliseer word. Dit behoort dan opgelos te wees. Herroep asseblief enigiets wat jy nie as strooipos beskou nie. Dit verminder die vertroue in die persoon wat dit gerapporteer het, asook die vertroue in die handtekening. groete, vipul. Op Vr, 02 Aug 2002 om 15:01:42 -0700 het Marc Perkel geskryf: > Hallo almal, > > Ek is die stelseladministrateur vir die Electronic Frontier Foundation en ek gebruik Razor > onder SpamAssassin daar en op my eie persoonlike bediener. Oor die algemeen > werk dit goed met byna 0 vals positiewe, behalwe dat byna al die vals > positiewe wat ek gesien het op boodskappe is wat by EFF ontstaan het. > > Ek wonder dus hoekom RAZOR EFF-e-pos vang en hoe dit gebeur. > Hieronder is 'n voorbeeld van waarvan ek praat. > > --------------------------------- > > Envelope-to: pcn@virtualrecordings.com > X-Sender: robin@mail.eff.org > X-Mailer: QUALCOMM Windows Eudora Version 5.1 > To: eff-ip@eff.org > From: Robin Gross <robin@eff.org> > Subject: [E-IP] HP backs off DMCA threat - CNET.com > Sender: eff-ip-admin@eff.org > X-BeenThere: eff-ip@eff.org > X-Mailman-Version: 2.0.11 > List-Unsubscribe: <https://www.eff.org/mailman/listinfo/eff-ip>, > <mailto:eff-ip-request@eff.org?subject=unsubscribe> > List-Id: Intelectual Property <eff-ip.eff.org> > List-Post: <mailto:eff-ip@eff.org> > List-Help: <mailto:eff-ip-request@eff.org?subject=help> > List-Subscribe: <https://www.eff.org/mailman/listinfo/eff-ip>, > <mailto:eff-ip-request@eff.org?subject=subscribe> > List-Archive: <https://www.eff.org/mailman/private/eff-ip/> > X-Original-Date: Fri, 02 Aug 2002 10:15:12 -0700 > Date: Fri, 02 Aug 2002 10:15:12 -0700 > X-Spam-Status: Yes, hits=7.1 required=5.0 > tests=MAILTO_LINK,RAZOR_CHECK > version=2.40 > X-Spam-Flag: YES > X-Spam-Level: ******* > X-Spam-Checker-Version: SpamAssassin 2.40 (devel $Id: SpamAssassin.pm,v 1.108 > 2002/07/29 16:25:10 jmason Exp $) > X-Spam-Report: Detailed Report > SPAM: -------------------- Start SpamAssassin results ---------------------- > SPAM: This mail is probably spam. The original message has been altered > SPAM: so you can recognise or block similar unwanted mail in future. > SPAM: See http://spamassassin.org/tag/ for more details. > SPAM: > SPAM: Content analysis details: (7.1 hits, 5 required) > SPAM: MAILTO_LINK (0.1 points) BODY: Includes a URL link to send an > email > SPAM: RAZOR_CHECK (7.0 points) Listed in Razor, see > http://razor.sourceforge.net/ > SPAM: > SPAM: -------------------- End of SpamAssassin results --------------------- > X-Spam: [SPAM] - Spam Assassin > > > > http://news.com.com/2100-1023-947740.html > > Dokument: HP trek terug van DMCA-dreigement > > Deur CNET News.com-personeel > 1 augustus 2002, 18:10 PT > > Hewlett-Packard het donderdag regsdreigemente laat vaar wat dit gemaak het teen sekuriteits- > ontleders wat foute in die maatskappy se sagteware bekend gemaak het. > > In 'n verklaring wat laat donderdag uitgereik is, het HP gesê dit sal nie die Digital > Millennium Copyright Act (DMCA), 'n omstrede kopieregwet, gebruik om 'n > los georganiseerde span navorsers te vervolg wat 'n fout in die maatskappy se > Tru64 Unix-bedryfstelsel gedemonstreer het nie. > > Die volgende is die maatskappy se verklaring: > > 1) HP is daartoe verbind om ons kliënte se sekuriteitsomgewings te beskerm. > > 2) Ons het bevestig dat daar 'n sekuriteitskwesbaarheid in Tru64 UNIX is, waarvan > die besonderhede op 18 julie onder ons aandag gebring is. Die probleem is nou > geïsoleer en HP berei 'n regstelling voor wat binne die volgende 48 uur > beskikbaar sal wees. > > 3) Ons sal nie kommentaar lewer op die besonderhede van ons gesprekke met SnoSoft nie. Ons > neem egter ons kliënte se sekuriteitsvereistes baie ernstig op en het 'n sterk > rekord van die nakoming van sekuriteitspraktyke volgens bedryfstandaarde. > > 4) Waar en hoe die DMCA toegepas moet word, is 'n saak van groot omstredenheid. > Die berigte brief aan SnoSoft was nie in ooreenstemming met of aanduidend van HP se beleid nie. > Ons kan met klem sê dat HP nie die DMCA sal gebruik om navorsing te smoor of > die vloei van inligting te belemmer wat ons kliënte sal bevoordeel en > hul stelselsekuriteit sal verbeter nie. > > > > ~~~~~~~~~~~~~~~~~~~~~~~~~~~~~~~~~~~~~~~~~~~~~~~~~~~~~~ > Robin D. Gross - Kuberruimte-prokureur - Intellektuele eiendom > Direkteur - Campaign for Audiovisual Free Expression (CAFE) > Electronic Frontier Foundation > 454 Shotwell Street, San Francisco, CA 94110 > e: robin@eff.org w: http://www.eff.org > t: 415.863.5459 f: 415.436.9993 > http://www.eff.org/cafe > http://www.eff.org/IP/Open_licenses > ~~~~~~~~~~~~~~~~~~~~~~~~~~~~~~~~~~~~~~~~~~~~~~~~~~~~~~~ > > > > > > > ------------------------------------------------------- > Hierdie sf.net-e-pos word geborg deur: ThinkGeek > Welkom in die geek-hemel. > http://thinkgeek.com/sf > _________________________________ | L59: http://news.com.com/2100-1023-947740.html, http://razor.sourceforge.net/, http://spamassassin.org/tag/, http://thinkgeek.com/sf, http://www.eff.org, http://www.eff.org/IP/Open_licenses, http://www.eff.org/cafe, https://www.eff.org/mailman/listinfo/eff-ip, https://www.eff.org/mailman/private/eff-ip/ | M59: 3 | N59: 2
A60: EMAIL_0033 | B60: isiXhosa | C60: Translation | D60: 0 | E60: legitimate | F60: SpamAssassin | G60: Vipul Ved Prakash <mail@vipul.net> | H60: Marc Perkel <marc@perkel.com> | I60: Fri, 02 Aug 2002 15:11:50 -0700 | J60: Re: [Razor-users] Iziphumo ezingachanekanga ezingezizo kwimiyalezo ye-EFF | K60: Molo Marc, Kukho utshintsho oluninzi kwinkqubo yokuthenjwa kutshanje. Siza kuqala ukubona amaxabiso okuthenjwa epapashwa kunye notyikityo ukusuka ngomso kusasa (malunga no-4AM). Oku kufanele kusonjululwe ngelo xesha. Nceda urhoxise nantoni na ongayithatheli njenge-spam. Kunciphisa ukuthenjwa komntu oyixxelileyo kunye nokuthenjwa kotyikityo. imbuliso, vipul. NgoLwesihlanu, 02 Aug 2002 ngo-15:01:42 -0700 uMarc Perkel wabhala: > Molo nonke, > > Ndingumlawuli weenkqubo we-Electronic Frontier Foundation kwaye ndisebenzisa i-razor > eqhuba phantsi kwe-spam assassin apho nakwiseva yam yobuqu. Ngokubanzi > isebenza kakuhle ngaphandle kwezigidi ezingamanga ze-0 - ngaphandle kokuba - phantse zonke > ezibonwe zingezizo zikwimiyalezo evela kwi-EFF. > > Ke ngoko - ndiyazibuza ukuba kutheni i-RAZOR ibamba i-imeyile ye-EFF kwaye kwenzeka njani oku. > Apha ngezantsi ngumzekelo wento endithetha ngayo. > > --------------------------------- > > Envelope-to: pcn@virtualrecordings.com > X-Sender: robin@mail.eff.org > X-Mailer: QUALCOMM Windows Eudora Version 5.1 > To: eff-ip@eff.org > From: Robin Gross <robin@eff.org> > Subject: [E-IP] HP backs off DMCA threat - CNET.com > Sender: eff-ip-admin@eff.org > X-BeenThere: eff-ip@eff.org > X-Mailman-Version: 2.0.11 > List-Unsubscribe: <https://www.eff.org/mailman/listinfo/eff-ip>, > <mailto:eff-ip-request@eff.org?subject=unsubscribe> > List-Id: Intelectual Property <eff-ip.eff.org> > List-Post: <mailto:eff-ip@eff.org> > List-Help: <mailto:eff-ip-request@eff.org?subject=help> > List-Subscribe: <https://www.eff.org/mailman/listinfo/eff-ip>, > <mailto:eff-ip-request@eff.org?subject=subscribe> > List-Archive: <https://www.eff.org/mailman/private/eff-ip/> > X-Original-Date: Fri, 02 Aug 2002 10:15:12 -0700 > Date: Fri, 02 Aug 2002 10:15:12 -0700 > X-Spam-Status: Yes, hits=7.1 required=5.0 > tests=MAILTO_LINK,RAZOR_CHECK > version=2.40 > X-Spam-Flag: YES > X-Spam-Level: ******* > X-Spam-Checker-Version: SpamAssassin 2.40 (devel $Id: SpamAssassin.pm,v 1.108 > 2002/07/29 16:25:10 jmason Exp $) > X-Spam-Report: Detailed Report > SPAM: -------------------- Start SpamAssassin results ---------------------- > SPAM: This mail is probably spam. The original message has been altered > SPAM: so you can recognise or block similar unwanted mail in future. > SPAM: See http://spamassassin.org/tag/ for more details. > SPAM: > SPAM: Content analysis details: (7.1 hits, 5 required) > SPAM: MAILTO_LINK (0.1 points) BODY: Includes a URL link to send an > email > SPAM: RAZOR_CHECK (7.0 points) Listed in Razor, see > http://razor.sourceforge.net/ > SPAM: > SPAM: -------------------- End of SpamAssassin results --------------------- > X-Spam: [SPAM] - Spam Assassin > > > > http://news.com.com/2100-1023-947740.html > > Uxwebhu: I-HP iyabuyela umva kwisisongelo se-DMCA > > Ngabasebenzi be-CNET News.com > 1 Agasti 2002, 18:10 PT > > U-Hewlett-Packard ngoLwesine ulahlile izisongelo zomthetho ezenziweyo ngokuchasene nabahlalutyi > bokhuseleko abapapashe iziphene kwisoftware yenkampani. > > Kwingxelo ekhutshwe kade ngoLwesine, i-HP ithe ayizukusebenzisa i-Digital > Millennium Copyright Act (DMCA), umthetho wamalungelo okukhuphela oxoxwayo, ukutshutshisa > iqela labaphandi ababonise isiphoso kwinkqubo yokusebenza ye-Tru64 Unix yenkampani. > > Oku kulandelayo yingxelo yenkampani: > > 1) I-HP izibophelele ekukhuseleni iindawo zokhuseleko zabathengi bethu. > > 2) Siqinisekisile ukuba kukho ubuthathaka bokhuseleko kwi-Tru64 UNIX, iinkcukacha > zayo ezaziswe kuthi ngo-18 Julayi. Ingxaki ngoku > yahlulwe kwaye i-HP ilungiselela ukulungiswa okuya kufumaneka kwiiyure ezingama-48 ezizayo. > > 3) Asizukugqabaza ngeenkcukacha zeengxoxo zethu ne-SnoSoft. Nangona kunjalo, sithatha iimfuno zokhuseleko > zabathengi bethu ngokungathandabuzekiyo kwaye sinerekhodi eyomeleleyo yokulandela iindlela zokhuseleko zomgangatho weshishini. > > 4) Apho kwaye njani i-DMCA kufuneka isetyenziswe ngumba wempikiswano enkulu. > Ileta echaziweyo eya ku-SnoSoft ibingahambelani okanye ibonise umgaqo-nkqubo we-HP. > Singatsho ngokugxininisa ukuba i-HP ayizukusebenzisa i-DMCA ukucinezela uphando okanye > ukuthintela ukuhamba kolwazi oluya kuxhamlisa abathengi bethu kwaye luphucule ukhuseleko lwenkqubo yabo. > > > > ~~~~~~~~~~~~~~~~~~~~~~~~~~~~~~~~~~~~~~~~~~~~~~~~~~~~~~ > Robin D. Gross - Igqwetha le-Cyberspace - Ipropathi yengqondo > Umlawuli - Campaign for Audiovisual Free Expression (CAFE) > Electronic Frontier Foundation > 454 Shotwell Street, San Francisco, CA 94110 > e: robin@eff.org w: http://www.eff.org > t: 415.863.5459 f: 415.436.9993 > http://www.eff.org/cafe > http://www.eff.org/IP/Open_licenses > ~~~~~~~~~~~~~~~~~~~~~~~~~~~~~~~~~~~~~~~~~~~~~~~~~~~~~~~ > > > > > > > ------------------------------------------------------- > Le imeyile ye-sf.net ixhaswe ngu: ThinkGeek > Wamkelekile kwizulu le-geek. > http://thinkgeek.com/sf > _________________________________ | L60: http://news.com.com/2100-1023-947740.html, http://razor.sourceforge.net/, http://spamassassin.org/tag/, http://thinkgeek.com/sf, http://www.eff.org, http://www.eff.org/IP/Open_licenses, http://www.eff.org/cafe, https://www.eff.org/mailman/listinfo/eff-ip, https://www.eff.org/mailman/private/eff-ip/
A61: EMAIL_0034 | B61: English | C61: Original | D61: 0 | E61: legitimate | F61: SpamAssassin | G61: Ben Liblit <liblit@eecs.berkeley.edu> | H61: rpm-zzzlist@freshrpms.net | I61: Tue, 08 Oct 2002 12:57:53 -0700 | J61: Re: RedHat 8.0 and his own freetype | K61: Matthias Haase wrote: > The bytecode-interpreter *is* disabled on RH8, defined at line 3 in > the Specfile of the SRPM. Right you are. The SRPM includes a patch to enable it, but then the specfile defaults to not applying that patch. I saw the former but missed the later. Egad, what a convoluted maze. Sorry for the misinformation! _______________________________________________ RPM-List mailing list <RPM-List@freshrpms.net> http://lists.freshrpms.net/mailman/listinfo/rpm-list | L61: http://lists.freshrpms.net/mailman/listinfo/rpm-list
A62: EMAIL_0034 | B62: isiNdebele | C62: Translation | D62: 0 | E62: legitimate | F62: SpamAssassin | G62: Ben Liblit <liblit@eecs.berkeley.edu> | H62: rpm-zzzlist@freshrpms.net | I62: Tue, 08 Oct 2002 12:57:53 -0700 | J62: Re: RedHat 8.0 and his own freetype | K62: U-Matthias Haase watlola: > I-bytecode-interpreter *ivaliwe* ku-RH8, echazwe emgqeni 3 ku- > ifayela elikhethekileko le-SRPM. Uqinisile. I-SRPM ifaka hlangana i-patch ukuyivumela, kodwana ifayela elithileko liyazikhethela bona alisebenzisi iphatjhi leyo. Ngibone eyangaphambilini kodwana waphuthelwa ngemva kwesikhathi. Egad, yindlela ephitheneko. Ngiyacolisa ngolwazi olungakalungi! _______________________________________________________ RPM-List mailing list <RPM-List@freshrpms.net> http://lists.freshrpms.net/mailman/listinfo/rpm-list | L62: http://lists.freshrpms.net/mailman/listinfo/rpm-list
A63: EMAIL_0035 | B63: English | C63: Original | D63: 0 | E63: legitimate | F63: SpamAssassin | G63: John Hall <johnhall@evergo.net> | H63: fork@spamassassin.taint.org | I63: Mon, 12 Aug 2002 14:33:02 -0700 | J63: RE: David Friedman: Mail Me the Money! | K63: As a practical matter, I doubt the value sold in such situations ever adds up to the value lost. And the non-pecuiary since of violation, loss, and trouble has to get in there somewhere if we are really picky. I don't think considering marginal utility of dollars has value in this situation. We aren't debating whether the thief is better off -- he is. I'm not a lawyer either. I played one on TV once but I didn't play a very good one and they canceled it after the first episode ... The situtation I described came from my recollection of Epstein's 'Takings'. He was specifically rejecting the idea of absolute property right found in Liberation theology and was using the idea -- that in an emergency where my life depends upon it I'm entitled to violate your property rights and (more) you are forbidden from using unreasonable force to defend them (particularly if you aren't around). Maybe I did get it all wrong, but that particular recollection is relatively strong precisely because it gave a good reason why my libertarian theology needed to be modified. He was also analyzing what the common law had come up with, which might not be the statuatory law in a particular jurisdiction. > -----Original Message----- > From: fork-admin@xent.com [mailto:fork-admin@xent.com] On Behalf Of > Russell Turpin > Sent: Monday, August 12, 2002 2:15 PM > To: fork@spamassassin.taint.org > Subject: RE: David Friedman: Mail Me the Money! > > John Hall: > >The case against theft also acknowledges that the value to the thief is > >often far less than the value to the victim. Stealing my $1,000 stereo > and > >then fencing it for $50 does not result in 'no loss' to the economy > >overall. .. > > That depends on the value placed on it by the fellow > who buys it from the pawn shop. And if you take > into account the marginal utility of dollars, the > thief may value his lucre more than his victim. > > >On the flip side of this, common law allows a breach of property law in > >precisely the type of scenarios where a net social gain is recorded but > >the owner's availability to make a contract was problematic. Breaking > into > >your isolated cabin because I'm starving, for example, is permissible if > I > >later offer restitution for the damage I caused and the food I ate. > > I am not a lawyer, but I think this is an incorrect > analysis of what the law allows in emergencies. I > can break into your cabin, take your rifle, grab a > box of your ammo, and shoot the bear that is mauling > a poor hiker, without having committed the crimes of > breaking and entering, theft, hunting out of season, > and killing an endangered species, whether or not I > later offer to pay for your window and ammunition. > The law simply puts a higher priority on saving > human life in emergency than on these other things. > > Now yes, you can turn around and sue me for > recompense. But that is a civil issue, not a > criminal one. Crime requires mens rea. And when I > shot the bear, I wasn't thinking about who owned > the bullet. > > > > _________________________________________________________________ > MSN Photos is the easiest way to share and print your photos: > http://photos.msn.com/support/worldwide.aspx > > http://xent.com/mailman/listinfo/fork http://xent.com/mailman/listinfo/fork | L63: http://photos.msn.com/support/worldwide.aspx, http://xent.com/mailman/listinfo/fork
A64: EMAIL_0035 | B64: Afrikaans | C64: Translation | D64: 0 | E64: legitimate | F64: SpamAssassin | G64: John Hall <johnhall@evergo.net> | H64: fork@spamassassin.taint.org | I64: Mon, 12 Aug 2002 14:33:02 -0700 | J64: RE: David Friedman: Pos vir my die geld! | K64: In die praktyk twyfel ek of die waarde wat in sulke situasies verkoop word ooit opweeg teen die waarde wat verlore gaan. En die nie-geldelike gevoel van skending, verlies en moeite moet êrens in berekening gebring word as ons regtig puntenerig is. Ek dink nie dit het waarde om die marginale nut van dollars in hierdie situasie te oorweeg nie. Ons debatteer nie of die dief beter daaraan toe is nie; hy is. Ek is ook nie 'n prokureur nie. Ek het een keer een op TV gespeel, maar ek het nie 'n baie goeie een gespeel nie en hulle het dit ná die eerste episode gekanselleer ... Die situasie wat ek beskryf het, kom uit my herinnering van Epstein se 'Takings'. Hy het spesifiek die idee van absolute eiendomsreg wat in Bevrydingsteologie voorkom, verwerp en die idee gebruik dat ek in 'n noodgeval waar my lewe daarvan afhang, geregtig is om jou eiendomsregte te skend en (verder) dat dit vir jou verbode is om onredelike geweld te gebruik om hulle te verdedig (veral as jy nie daar is nie). Miskien het ek dit alles verkeerd verstaan, maar daardie spesifieke herinnering is relatief sterk juis omdat dit 'n goeie rede gegee het waarom my libertariese teologie aangepas moes word. Hy het ook ontleed waarmee die gemenereg vorendag gekom het, wat dalk nie die statutêre reg in 'n bepaalde jurisdiksie is nie. > -----Oorspronklike boodskap----- > Van: fork-admin@xent.com [mailto:fork-admin@xent.com] Namens > Russell Turpin > Gestuur: maandag 12 augustus 2002 14:15 > Aan: fork@spamassassin.taint.org > Onderwerp: RE: David Friedman: Pos vir my die geld! > > John Hall: > >Die saak teen diefstal erken ook dat die waarde vir die dief > >dikwels veel minder is as die waarde vir die slagoffer. Om my $1 000- stereo > te steel > en > >dit dan vir $50 te verkwansel, lei nie tot 'geen verlies' vir die ekonomie > >in die geheel nie. .. > > Dit hang af van die waarde wat die ou > wat dit by die pandjieswinkel koop, daaraan heg. En as jy > die marginale nut van dollars in ag neem, kan die > dief sy buit meer waardeer as sy slagoffer. > > >Aan die ander kant laat die gemenereg 'n oortreding van die eiendomsreg toe in > >presies die soort scenario's waar 'n netto sosiale wins aangeteken word, maar > >die eienaar se beskikbaarheid om 'n kontrak aan te gaan problematies was. Om > in > >jou afgeleë kajuit in te breek omdat ek verhonger, is byvoorbeeld toelaatbaar as > ek > >later vergoeding aanbied vir die skade wat ek veroorsaak het en die kos wat ek geëet het. > > Ek is nie 'n prokureur nie, maar ek dink dit is 'n verkeerde > ontleding van wat die reg in noodgevalle toelaat. Ek > kan in jou kajuit inbreek, jou geweer vat, 'n > boks van jou ammunisie gryp en die beer skiet wat 'n > arme stapper verskeur, sonder dat ek die misdade van > inbraak, diefstal, jag buite die seisoen > en die doodmaak van 'n bedreigde spesie gepleeg het, of ek > later aanbied om vir jou venster en ammunisie te betaal of nie. > Die reg plaas eenvoudig 'n hoër prioriteit op die redding van > menselewe in 'n noodgeval as op hierdie ander dinge. > > Nou ja, jy kan omdraai en my vir > vergoeding dagvaar. Maar dit is 'n siviele kwessie, nie 'n > strafregtelike een nie. Misdaad vereis mens rea. En toe ek > die beer geskiet het, het ek nie gedink oor wie die > koeël besit nie. > > > > _________________________________________________________________ > MSN Photos is die maklikste manier om jou foto's te deel en te druk: > http://photos.msn.com/support/worldwide.aspx > > http://xent.com/mailman/listinfo/fork http://xent.com/mailman/listinfo/fork | L64: http://photos.msn.com/support/worldwide.aspx, http://xent.com/mailman/listinfo/fork | M64: 3 | N64: 3
A65: EMAIL_0035 | B65: isiXhosa | C65: Translation | D65: 0 | E65: legitimate | F65: SpamAssassin | G65: John Hall <johnhall@evergo.net> | H65: fork@spamassassin.taint.org | I65: Mon, 12 Aug 2002 14:33:02 -0700 | J65: RE: UDavid Friedman: Ndithumelele Imali! | K65: Ngokomcimbi osebenzayo, ndiyathandabuza ukuba ixabiso elithengisiweyo kwiimeko ezinjalo lakha ladibana nexabiso elilahlekileyo. Kwaye imvakalelo engeyiyo eyemali yokophulwa, yelahleko, kunye nenkathazo kufuneka ifakwe ndawo ithile ukuba singabantu abakhetha kakhulu. Andicingi ukuba ukuqwalasela ukusebenza kwe-marginal dollars kunexabiso kule meko. Asixoxi ngokuba ngaba isela lingcono na -- linjalo. Andinguye negqwetha ngokunjalo. Ndakhe ndadlala elinye kumabonwakude kanye kodwa andikhange ndidlale elilungileyo kakhulu baza bayirhoxisa emva kwesiqendu sokuqala ... Imeko endiyichazileyo ivela kwinkumbulo yam ye-'Takings' ka-Epstein. Wayichasa ngokukodwa ingcamango yelungelo lobunini elipheleleyo elifumaneka kwimfundiso ye-Liberation theology kwaye wayesebenzisa ingcamango -- yokuba kwimeko engxamisekileyo apho ubomi bam buxhomekeke kuyo ndinelungelo lokwaphula amalungelo akho epropathi kwaye (ngaphezulu) awuvumelekanga ukuba usebenzise amandla angenangqondo ukuwakhusela (ngakumbi ukuba awukho ngakumbi). Mhlawumbi ndandiphazame ngokupheleleyo, kodwa loo nkumbulo ikhethekileyo yomelele kakhulu ngenxa yokuba yanika isizathu esihle sokuba kutheni imfundiso yam ye-libertarian yayifuna ukulungiswa. Wayekwaphonononga oko umthetho oqhelekileyo wawufikile kuko, nto leyo enokungabi ngumthetho omiselweyo kummandla othile wolawulo. > -----Umyalezo woQobo----- > Isuka ku: fork-admin@xent.com [mailto:fork-admin@xent.com] Egameni lika > Russell Turpin > Ithunyelwe: NgoMvulo, 12 Agasti 2002 14:15 > Iya ku: fork@spamassassin.taint.org > Umxholo: RE: David Friedman: Mail Me the Money! > > UJohn Hall: > >Ityala elichasene nobusela likwaqonda ukuba ixabiso kwisela > >lidla ngokuba lincinci kakhulu kunexabiso kwixhoba. Ukuba i-stereo yam ye-$1,000 > >baza kuyithengisa nge-$50 akukhokeleli kwi-'lahleko engekho' kuqoqosho > >ngokubanzi. .. > > Loo nto ixhomekeke kwixabiso elibekwa ngulowo > oyithenga kwivenkile yezibambiso. Kwaye ukuba uthatha > ingqalelo ukusebenziseka kwemali, isela > lisenokuxabisa impahla yalo ebiweyo ngaphezu kwexhoba lalo. > > >Kwelinye icala loku, umthetho oqhelekileyo uvumela ukwaphulwa komthetho wepropathi > >kwiindidi ezichanekileyo zeemeko apho inzuzo yentlalo iyonke irekhodwa > >kodwa ukufumaneka komnini wokwenza isivumelwano kwakuyingxaki. Ukugqekeza > >kwindlu yakho ekwanti ngenxa yokuba ndilambile, umzekelo, kuvumelekile ukuba > >kamva ndinikezela ngembuyekezo ngomonakalo endiwubangeleyo kunye nokutya endikutyileyo. > > Andinguye igqwetha, kodwa ndicinga ukuba olu luhlaziyo olungachanekanga > lwento umthetho oyivumelayo kwiimeko ezingxamisekileyo. Ndingagqekeza > endlwini yakho, ndithathe umpu wakho, ndibambe ibhokisi yembumbulu zakho, ndize ndidubule ibhere egxotha umhambi ohluphekileyo, ngaphandle kokwenza ulwaphulo-mthetho lokugqekeza nokungena, ubusela, ukuzingela ngaphandle kwexesha, kunye nokubulala iintlobo ezisengozini, nokuba ndiyathembisa kamva okuhlawulela ifestile nembumbulu zakho okanye hayi. Umthetho ubeka nje phambili ukusindiswa kobomi bomntu kwimeko engxamisekileyo kunezi ezinye izinto. > > Ngoku ewe, ungajika undimangalele ngembuyekezo. Kodwa lo ngumba wembambano yamakhaya, hayi owolwaphulo-mthetho. Ulwaphulo-mthetho lufuna i-mens rea. Kwaye xa ndandidubula ibhere, ndandingacingi ngokuba ngubani ongumnini wembumbulu. > > > > _________________________________________________________________ > I-MSN Photos yeyona ndlela ilula yokwabelana nokuprinta iifoto zakho: > http://photos.msn.com/support/worldwide.aspx > > http://xent.com/mailman/listinfo/fork http://xent.com/mailman/listinfo/fork | L65: http://photos.msn.com/support/worldwide.aspx, http://xent.com/mailman/listinfo/fork
A66: EMAIL_0036 | B66: English | C66: Original | D66: 0 | E66: legitimate | F66: SpamAssassin | G66: Chuck Murcko <chuck@topsail.org> | H66: Russell Turpin <deafbox@hotmail.com> | I66: Thu, 19 Sep 2002 11:01:49 -0700 | J66: Re: Hanson's Sept 11 message in the National Review | K66: What I meant was that neither he nor anyone else has any *authority* to say something can or can't be published, and make that stick, at least in the US, and from some descriptions, France. Of course he can say anything he wants. And I can choose to ignore it, or not. Works both ways. Fscking semantics. Chuck On Thursday, September 19, 2002, at 06:41 AM, Russell Turpin wrote: > Robert Harley: >>> BTW, I wasn't aware that the 1st Amendment mandated that crap must be >>> FoRKed. > > Chuck Murcko <chuck@topsail.org>: >> It doesn't, BTW. It says the right to free speech shall not be >> abridged. That means *you* can't say anything may not be FoRKed or >> printed or whatever. > > Actually, it means just the opposite. The first > amendment guarantees Harley's right to say just > that. For the outlets where he has editorial > control, it even guarantees his right to CENSOR > content published through those outlets. The > first amendment doesn't limit Harley's speech, > and it is neutral with regard to the selection > policies of FoRK and other private venues. > > > > _________________________________________________________________ > MSN Photos is the easiest way to share and print your photos: > http://photos.msn.com/support/worldwide.aspx > | L66: http://photos.msn.com/support/worldwide.aspx
A67: EMAIL_0036 | B67: isiZulu | C67: Translation | D67: 0 | E67: legitimate | F67: SpamAssassin | G67: Chuck Murcko <chuck@topsail.org> | H67: Russell Turpin <deafbox@hotmail.com> | I67: Thu, 19 Sep 2002 11:01:49 -0700 | J67: Mayelana nomyalezo kaHanson wangomhla ka-11 kuMandulo ku-National Review | K67: Bengiqonde ukuthi akekho yena noma omunye umuntu onegunya lokuthi asho ukuthi kukhona okungashicilelwa noma okungashicilelwa, futhi enze lokho kwenzeke ngempela, okungenani e-US, futhi ngokwezinye izincazelo, eFrance. Yebo, angasho noma yini ayifunayo. Futhi ngingakhetha ukungayinaki, noma ngiyinake. Kusebenza kuzo zombili izinhlangothi. Ukudlala ngamagama nje okucasulayo. Chuck NgoLwesine, Septhemba 19, 2002, ngo-06:41 ekuseni, uRussell Turpin wabhala: > Robert Harley: >>> Ngendlela, bengingazi ukuthi i-1st Amendment (uMthetho Oyisisekelo Wokuqala) >>> yayiyala ukuthi udoti kumele u-FoRKed (ushicilelwe ku-FoRK). > > Chuck Murcko <chuck@topsail.org>: >> Ayiyali lokho, ngendlela. Ithi ilungelo lokukhuluma ngokukhululeka >> akumele livinjelwe. Lokho kusho ukuthi *wena* awukwazi ukusho >> ukuthi kukhona okungakwazi ukuba yi-FoRKed noma kushicilelwe noma yini enye. > > Empeleni, kusho okuphambene nalokho. I-First > Amendment iqinisekisa ilungelo likaHarley lokusho > lokho kanye. Ezinkundleni lapho enegunya > lokulawula okuqukethwe khona, iqinisekisa nelungelo lakhe lokuvimba (CENSOR) > okuqukethwe okushicilelwa ngalezo zinkundla. I-First > Amendment ayiwuvimbi umbono kaHarley, > futhi ayithathi hlangothi mayelana nezinqubomgomo > zokukhetha ze-FoRK nezinye izinkundla ezizimele. > > > > _________________________________________________________________ > I-MSN Photos iyindlela elula yokwabelana nokunyathelisa izithombe zakho: > http://photos.msn.com/support/worldwide.aspx > | L67: http://photos.msn.com/support/worldwide.aspx
A68: EMAIL_0037 | B68: English | C68: Original | D68: 0 | E68: legitimate | F68: SpamAssassin | G68: Chris Kloiber <ckloiber@ckloiber.com> | H68: rpm-zzzlist@freshrpms.net | I68: Tue, 08 Oct 2002 23:27:10 -0400 | J68: Re: Zoot apt/openssh & new DVD playing doc | K68: On Tue, 2002-10-08 at 10:36, Matthias Saou wrote: > Hi there, > > Two new things today : > > 1) I've had to install a Red Hat Linux 6.2 server because of an old > proprietary IVR software that doesn't work on newer releases :-( So I've > recompiled both the latest apt and openssh packages for it, and they are > now available with a complete "os, updates & freshrpms" apt repository at > apt.freshrpms.net, for those who might be interested. Gack. Did you try 7.3 with the compat-glibc first? Or does it require an antique kernel? -- Chris Kloiber _______________________________________________ RPM-List mailing list <RPM-List@freshrpms.net> http://lists.freshrpms.net/mailman/listinfo/rpm-list | L68: http://lists.freshrpms.net/mailman/listinfo/rpm-list
A69: EMAIL_0037 | B69: Afrikaans | C69: Translation | D69: 0 | E69: legitimate | F69: SpamAssassin | G69: Chris Kloiber <ckloiber@ckloiber.com> | H69: rpm-zzzlist@freshrpms.net | I69: Tue, 08 Oct 2002 23:27:10 -0400 | J69: Re: Zoot apt/openssh en nuwe dokument oor DVD-speel | K69: Op Di, 2002-10-08 om 10:36 het Matthias Saou geskryf: > Hallo daar, > > Twee nuwe dinge vandag: > > 1) Ek moes 'n Red Hat Linux 6.2-bediener installeer weens 'n ou > eiendomlike IVR-sagteware wat nie op nuwer weergawes werk nie :-( Ek het dus > die nuutste apt- en openssh-pakkette daarvoor hersaamgestel, en hulle is > nou beskikbaar met 'n volledige "os, updates & freshrpms"-apt-bewaarplek by > apt.freshrpms.net, vir diegene wat dalk belangstel. Gits. Het jy eers 7.3 met die compat-glibc probeer? Of vereis dit 'n antieke kern? -- Chris Kloiber _______________________________________________ RPM-List-poslys <RPM-List@freshrpms.net> http://lists.freshrpms.net/mailman/listinfo/rpm-list | L69: http://lists.freshrpms.net/mailman/listinfo/rpm-list | M69: 3 | N69: 3
A70: EMAIL_0037 | B70: isiXhosa | C70: Translation | D70: 0 | E70: legitimate | F70: SpamAssassin | G70: Chris Kloiber <ckloiber@ckloiber.com> | H70: rpm-zzzlist@freshrpms.net | I70: Tue, 08 Oct 2002 23:27:10 -0400 | J70: Re: Zoot apt/openssh kunye noxwebhu olutsha lokudlala i-DVD | K70: NgoLwesibini, 2002-10-08 ngo-10:36 uMatthias Saou wabhala: > Molo apho, > > Izinto ezimbini ezintsha namhlanje: > > 1) Bekufuneka ndifakele iseva ye-Red Hat Linux 6.2 ngenxa yesoftware > endala ye-IVR yobunini engasebenziyo kwiinguqulelo ezintsha :-( Ke ngoko ndiphinde > ndadibanisa iipakheji zamva nje ze-apt kunye ne-openssh zayo, kwaye ngoku > ziyafumaneka nendawo yokugcina epheleleyo ye-"os, updates & freshrpms" apt e- > apt.freshrpms.net, kwabo banomdla. Yhoo. Ukhe wazama i-7.3 ene-compat-glibc kuqala? Okanye ngaba ifuna i-kernel eyakudala kakhulu? -- Chris Kloiber _______________________________________________ Uluhlu lwemeyile lwe-RPM-List <RPM-List@freshrpms.net> http://lists.freshrpms.net/mailman/listinfo/rpm-list | L70: http://lists.freshrpms.net/mailman/listinfo/rpm-list
A71: EMAIL_0038 | B71: English | C71: Original | D71: 0 | E71: legitimate | F71: SpamAssassin | G71: Matthias Saou <matthias@rpmforge.net> | H71: rpm-zzzlist@freshrpms.net | I71: Tue, 01 Oct 2002 15:11:27 +0200 | J71: Re: Gabber packages for 8.0 (was: All set for Red Hat Linux 8.0) | K71: Once upon a time, Matthias wrote : > I'm facing another problem right now. It looks like libsigc++ is no > longer included in the distribution, and gtkmm won't compile without it > :-/ I guess I'll have to repackage it myself for 8.0 (assuming it's > possible). Well, I've made an updated libsigc++ 1.0.4 package. It rebuilds cleanly on 7.3 but the *.so* libraries are missing when trying to rebuild on 8.0 (the .a and .la files and everything else is though). Do you have an idea of what the problem may be? Julian : Do you want the .src.rpm to try to find the cause? Matthias -- Clean custom Red Hat Linux rpm packages : http://freshrpms.net/ Red Hat Linux release 7.3 (Valhalla) running Linux kernel 2.4.18-10acpi Load : 0.19 0.15 0.16 _______________________________________________ RPM-List mailing list <RPM-List@freshrpms.net> http://lists.freshrpms.net/mailman/listinfo/rpm-list | L71: http://freshrpms.net/, http://lists.freshrpms.net/mailman/listinfo/rpm-list
A72: EMAIL_0038 | B72: isiNdebele | C72: Translation | D72: 0 | E72: legitimate | F72: SpamAssassin | G72: Matthias Saou <matthias@rpmforge.net> | H72: rpm-zzzlist@freshrpms.net | I72: Tue, 01 Oct 2002 15:11:27 +0200 | J72: Re: Gabber packages for 8.0 (was: All set for Red Hat Linux 8.0) | K72: Ngesinye isikhathi, u-Mathias watlola: > Ngiqalene nomunye umraro njenganje. Kubonakala ngasuthi i-libsigc++ ayikho > isikhathi eside sifakwe ekusabalalisweni, begodu i-gtkmm angeze yahlanganisa ngaphandle kwayo > :-/ Ngicabanga bona kuzokufanela bona ngiyiphakethe kabutjha ngokwami ​​nge-8.0 (ngicabanga bona > kungenzeka). Kulungile, ngenze iphakheji ye-libsigc++ 1.0.4 evuselelweko. Yakha kabutjha ngokuhlanzeka 7.3 kodwana amalayibhrari *.so* alahlekile lokha nawulinga ukwakha kabutjha ku-8.0 (i .a kanye .la amafayela nakho koke okunye kodwana). Ingabe unombono wokuthi kungaba yini umraro? U-Julian: Ingabe ufuna .src.rpm ukulinga ukuthola imbangela? U-Mathias -- Hlanza amaphakheji we-Red Hat Linux rpm : http://freshrpms.net/ I-Red Hat Linux release 7.3 (Valhalla) esebenzisa i-Linux kernel 2.4.18-10acpi Umthwalo: 0.19 0.15 0.16 _______________________________________________________ RPM-List mailing list <RPM-List@freshrpms.net> http://lists.freshrpms.net/mailman/listinfo/rpm-list | L72: http://freshrpms.net/, http://lists.freshrpms.net/mailman/listinfo/rpm-list
A73: EMAIL_0039 | B73: English | C73: Original | D73: 0 | E73: legitimate | F73: SpamAssassin | G73: Robin Lynn Frank <rlfrank@paradigm-omega.com> | H73: spamassassin-talk@example.sourceforge.net | I73: Wed, 28 Aug 2002 13:50:07 -0700 | J73: Re: [SAtalk] O.T. Habeus -- Why? | K73: -----BEGIN PGP SIGNED MESSAGE----- Hash: SHA1 On Wednesday 28 August 2002 01:34 pm, Brian McNett wrote: > > Uh... the reason is simple. Habeas runs something called the > "Habeas Infringers List", and if you use their trademark without > their permission, you'll end up on it. Then, when you send spam > with the misappropriated header, users of SA (2.40 supports > this) will tag your mail as spam, rather than let it through. > This may be done independantly of your IP address, so be > prepared to constantly change domain names, and move your > servers as fast as you send spam. > > Also, that little haiku is a copyrighted work, so not only CAN > Habeas sue, they MUST sue to protect their copyright. And since > it's a trademark as well, that's a double-whammy. Habeas has > some pretty high-powered legal people, who will gladly go to > town on violators. > > The whole point here is to give them the legal leverage they > need to put spammers out of business, and not only block mail > from them, but allow through the things that really AREN'T spam. > > --B > And if a spammer forges headers??? - -- - ------------------------------------------------------------------------ Robin Lynn Frank---Director of Operations---Paradigm, Omega, LLC http://paradigm-omega.com http://paradigm-omega.net © 2002. All rights reserved. No duplication/dissemination permitted. Use of PGP/GPG encrypted mail preferred. No HTML/attachments accepted. Fingerprint: 08E0 567C 63CC 5642 DB6D D490 0F98 D7D3 77EA 3714 Key Server: http://paradigm-omega.com/keymaster.html - ------------------------------------------------------------------------ -----BEGIN PGP SIGNATURE----- Version: GnuPG v1.0.7 (GNU/Linux) iD8DBQE9bTeHD5jX03fqNxQRArMEAJ4l1p6ToRVaG4j+Dy3R2tzfD9FNvgCfRhU3 kZo/MbYBSLyI/m1vsN4ZYmM= =miJB -----END PGP SIGNATURE----- ------------------------------------------------------- This sf.net email is sponsored by: Jabber - The world's fastest growing real-time communications platform! Don't just IM. Build it in! http://www.jabber.com/osdn/xim _______________________________________________ Spamassassin-talk mailing list Spamassassin-talk@lists.sourceforge.net https://lists.sourceforge.net/lists/listinfo/spamassassin-talk | L73: http://paradigm-omega.com, http://paradigm-omega.com/keymaster.html, http://paradigm-omega.net, http://www.jabber.com/osdn/xim, https://lists.sourceforge.net/lists/listinfo/spamassassin-talk
A74: EMAIL_0039 | B74: isiNdebele | C74: Translation | D74: 0 | E74: legitimate | F74: SpamAssassin | G74: Robin Lynn Frank <rlfrank@paradigm-omega.com> | H74: spamassassin-talk@example.sourceforge.net | I74: Wed, 28 Aug 2002 13:50:07 -0700 | J74: Re: [SAtalk] O.T. Habeus -- Why? | K74: -----THOMA UMLAYEZO OSAYINIWEKO we-PGP----- I-Hash: SHA1 NgeLesithathu mhlazi-28 kuRhoboyi wee-2002 nge-01:34 ntambama, u-Brian McNett watlola: > > Uh... isizathu silula. U-Habeas uphethe into ebizwa nge- > "I-Habeas Infringers List", begodu nangabe usebenzisa itshwayo labo ngaphandle > imvumo yabo, uzokugcina kiyo. Bese, lokha nawuthumela i-spam > ngehloko engakalungi, abasebenzisi be-SA (2.40 isekela > lokhu) kuzokuthega imeyili yakho njenge-spam, kunokuthi ivumele bona idlule. > Lokhu kungenziwa ngaphandle kwekheli lakho le-IP, yeke > ulungele ukutjhugulula amagama wesizinda, begodu utjhugulule > amaseva msinya njengombana uthumela i-spam. > > Godu, i-haiku encani leyo ngumsebenzi onelungelo lokutlola, njeke ingasi kwaphela > Ama-habeas amangalela, KUFANELE amangalele ukuvikela ilungelo labo lokutlola. Begodu kusukela > liphawu lokurhweba, lokho kuyinto ephindwe kabili. U-Habeas unayo > abanye abantu abanegunya eliphezulu lomthetho, abazokuya ngokuthaba > idorobha ebantwini abaphula umthetho. > > Iphuzu elipheleleko lapha kukubanikela amandla womthetho > kutlhogeka bona sikhiphe abathumeli be-spam ebhizinisini, ingasi ukuvimba i-imeyili kwaphela > ukusuka kibo, kodwana vumela izinto ezingezizo i-spam. > > --B > Begodu nangabe umthumeli we-spam wenza ama-header??? - -- - ---------------------------------------------------------------------- U-Robin Lynn Frank---Umnqophisi wezeMisebenzi---I-Paradigm, Omega, LLC http://paradigm-omega.com http://paradigm-omega.net © 2002. Woke amalungelo agcinwe. Akukavunyelwa ukuphinda/ukusabalalisa. Kukhethwa ukusebenzisa i-imeyili efihlekileko ye-PGP/GPG. Akukho HTML/ama-attachment amukelwako. Iminwe: 08E0 567C 63CC 5642 DB6D D490 0F98 D7D3 77EA 3714 Iseva eqakathekileko: http://paradigm-omega.com/keymaster.html - ---------------------------------------------------------------------- -----QALA UKUTHINTA I-PGP----- Inguqulo: GnuPG v1.0.7 (GNU/Linux) iD8DBQE9bTeHD5jX03fqNxQRArMEAJ4l1p6ToRVaG4j+Dy3R2tzfD9FNvgCfRhU3 kZo/MbYBSLyI/m1vsN4ZYmM= =miJB -----END PGP SIGNATURE----- ------------------------------------------------------ I-imeyili ye-sf.net ixhaswe ngu: Jabber - I-ephasini ekhula msinyana khulu iplatifomu yokuthintana yesikhathi sangempela! Ungabi yi-IM kwaphela. Yenza ngaphakathi! http://www.jabber.com/osdn/xim _______________________________________________________ Irhelo lokuthunyelwa kwe-Spamassassin-talk Spamassassin-talk@lists.sourceforge.net https://lists.sourceforge.net/lists/listinfo/spamassassin-talk | L74: http://paradigm-omega.com, http://paradigm-omega.com/keymaster.html, http://paradigm-omega.net, http://www.jabber.com/osdn/xim, https://lists.sourceforge.net/lists/listinfo/spamassassin-talk
A75: EMAIL_0040 | B75: English | C75: Original | D75: 0 | E75: legitimate | F75: SpamAssassin | G75: Andy <andy@r2-dvd.org> | H75: "'zzzzteana@yahoogroups.com'" <zzzzteana@yahoogroups.com> | I75: Wed, 28 Aug 2002 13:54:36 +0100 | J75: [zzzzteana] Betamax finally laid to rest | K75: Not fortean, but a moment in time all the same... http://news.bbc.co.uk/1/hi/entertainment/film/2220972.stm Betamax video recorders are finally being phased out almost 20 years after losing the battle for dominance of the home video market to VHS. Betamax's manufacturer, Sony, has announced that it will make only 2,000 more machines for the Japanese market. They have not been on sale in the rest of the world since 1998. VHS became the dominant format by the mid-1980s Betamax was launched in 1975, and won many fans who said it was better quality than its VHS rival. Some 2.3 million Betamax machines were sold worldwide in its peak year, 1984, but it soon went downhill as VHS became the format of choice for the film rental industry and in homes. Just 2,800 machines were sold in the 12 months to March 2002. "With digital machines and other new recording formats taking hold in the market, demand has continued to decline and it has become difficult to secure parts," Sony said in a statement. Sony said it would continue to offer repairs and manufacture tapes for the format. The professional Betamax format, Betacam, is still widely used in the television and film industries and will be unaffected. But the recent rise of DVDs seems to have put the final nail in the coffin for Betamax home players. In the 1980s, many video rental chains preferred the VHS format. Betamax lovers became so passionate about the format in the face of competition from VHS that they set up the Betaphile Club in 1988. The picture and sound quality of Beta was superior to VHS, Betaphiles say, although VHS tapes had a longer duration. A total of 18 million Betamax machines were sold around the world, but no new ones will be made after the end of 2002. Sony is now planning to focus its efforts on new digital technologies. See also: ------------------------ Yahoo! Groups Sponsor ---------------------~--> Kwick Pick Portable Lock Pick - Opens Almost Any Lock! Locked out? Try the Kwick Pick. For $17.95, you can open car doors, desk drawers, padlocks, and much more! Never get locked out again! http://us.click.yahoo.com/O2sPyA/p6kEAA/MVfIAA/7gSolB/TM ---------------------------------------------------------------------~-> To unsubscribe from this group, send an email to: forteana-unsubscribe@egroups.com Your use of Yahoo! Groups is subject to http://docs.yahoo.com/info/terms/ | L75: http://docs.yahoo.com/info/terms/, http://news.bbc.co.uk/1/hi/entertainment/film/2220972.stm, http://us.click.yahoo.com/O2sPyA/p6kEAA/MVfIAA/7gSolB/TM
A76: EMAIL_0040 | B76: isiNdebele | C76: Translation | D76: 0 | E76: legitimate | F76: SpamAssassin | G76: Andy <andy@r2-dvd.org> | H76: "'zzzzteana@yahoogroups.com'" <zzzzteana@yahoogroups.com> | I76: Wed, 28 Aug 2002 13:54:36 +0100 | J76: [zzzzteana] Betamax finally laid to rest | K76: Ingasi iqiniso, kodwana umzuzwana ngesikhathi... http://news.bbc.co.uk/1/hi/entertainment/film/2220972.stm Iinqophiso zevidiyo ze-Betamax ekugcineni ziqedwa ngemva kweminyaka ema-20 ukulahlekelwa yipi yokubusa imakethe yamavidiyo wekhaya ku-VHS. Umkhiqizi we-Betamax, u-Sony, umemezele bona uzokwenza i-2,000 kwaphela imitjhini eminengi yemakethe ye-Japan. Bezingathengiswa ephasini loke kusukela ngo-1998. I-VHS yaba yindlela ejayelekileko phakathi kwabo-1980 I-Betamax yathonywa ngo-1975, begodu yazuza abalandeli abanengi ebebathi ingcono ikhwalithi ukudlula imbangi yayo ye-VHS. Imitjhini engaba ziingidi ezi-2.3 ze-Betamax zathengiswa ephasini loke ngomnyaka wayo ophakemeko, 1984, kodwana msinyana yehla njengombana i-VHS yaba yifomethi yokukhetha ibubulo lokuqatjha amafilimu kanye namakhaya. Kwathengiswa imitjhini ema-2,800 eenyangeni ezili-12 ukuya kuNtaka 2002. "Ngemitjhini yedijithali namanye amafomethi amatjha wokurekhoda athatha indawo imakethe, ukufunwa kuragela phambili nokwehla begodu sekunzima ukwenza iingcenye ezivikelekileko," kutsho u-Sony esitatimendeni. I-Sony ithe izakuragela phambili nokulungisa nokwenza amatheyiphu ifomethi. Ifomethi ye-Betamax, i-Betacam, isasetjenziswa khulu amabubulo wethelevishini namafilimu begodu angeze athinteka. Kodwana ukukhuphuka kwama-DVD kwamuva nje kubonakala ngasuthi kubeke isikhonkwane sokugcina ebhokisini kubadlali bekhaya be-Betamax. Ngabo-1980, amaketani amanengi wokuqatjha amavidiyo akhetha ifomethi ye-VHS. Abathandi be-Betamax baba nethando elikhulu ngefomethi ebusweni umncintiswano ovela ku-VHS ukuthi basungula i-Betaphile Club ngo-1988. Ikhwalithi yesithombe netjhada ye-Beta beyiphezulu kune-VHS, ama-Betaphiles athi, nanyana amatheyiphu we-VHS bekanesikhathi eside. Inani elipheleleko lemitjhini ye-Betamax eyi-18 yezigidi ithengiswe ephasini loke, kodwana ayikho ezitjha zizokwenziwa ngemva kokuphela kwaka-2002. I-Sony nje ihlela ukutjheja imizamo yayo ebuchwephesheni obutjha bedijithali. Qala godu: ------------------------ Yahoo! Iinqhema ezixhasako ---------------------~--> I-Kwick Pick Portable Lock Pick - Ivula Pheze nanyana ngiyiphi iLokhi! Ivalelwe ngaphandle? Linga i-Kwick Pick. Nge-$17.95, ungavula iminyango yeenkoloyi, amakhabethe wedeski, amalokhi, nokunye okunengi! Ungaphinde uvalelwe ngaphandle godu! http://us.click.yahoo.com/O2sPyA/p6kEAA/MVfIAA/7gSolB/TM -----------------------------------------------------------------~-> Ukuzikhupha esiqhemeni lesi, thumela i-imeyili ku: forteana-unsubscribe@egroups.com Ukusebenzisa kwakho i-Yahoo! Amaqembu angaphansi kwe-http://docs.yahoo.com/info/terms/ | L76: http://docs.yahoo.com/info/terms/, http://news.bbc.co.uk/1/hi/entertainment/film/2220972.stm, http://us.click.yahoo.com/O2sPyA/p6kEAA/MVfIAA/7gSolB/TM
A77: EMAIL_0041 | B77: English | C77: Original | D77: 0 | E77: legitimate | F77: SpamAssassin | G77: Chris Garrigues <cwg-exmh@DeepEddy.Com> | H77: Scott Lipcon <slipcon@mercea.net> | I77: Tue, 24 Sep 2002 12:29:35 -0500 | J77: Re: traceback in new exmh | K77: > From: Scott Lipcon <slipcon@mercea.net> > Date: Mon, 23 Sep 2002 22:35:05 -0400 > > The speed is a problem for sure - It takes a long time to do the > rescanning of sequences (I associate it with hitting the 'flist' > button, or when my background flist goes off). I'm running on a > pretty fast system (Athlon 1700+, 512Mb RAM, 10k RPM ultra SCSI disk) > and hitting flist used to take no more than a second. The big > difference might just be perception, because the the old code just > updated all the folders (count + color) all at once, instead of making > it look like there is 0 unseen, then counting its way back up. > > I doubt I'll have much time in the immediate future to hack at this, > but if I do - can you suggest areas that might be the best to > optimize? If not, do you think we can put in some preferences to > disable some of the more intensive features? I'd rather disable all > the sequence support (except unseen, of course) and have reasonable > speed. I suspect people on slow machines would find the current > state unusable. If I knew where the problem was, I'd fix it myself. Finding it is probably more work than the actual fix. > > > > This is because of your Hook_MsgShow_update_unseen which is calling a fun > ctio > > n > > which no longer exists. > > > > I suspect you need > > Seq_Del $exmh(folder) unseen $msgid > > now instead of > > Mh_MarkSeen $exmh(folder) $msgid > > > > Thanks. I'm not sure I'll need it with the new sequence code, but I > might. Does your new code commit sequences immediately? The old code > didn't, so I put that in to help keep my mh and exmh windows in sync. Yes it does. Chris -- Chris Garrigues http://www.DeepEddy.Com/~cwg/ virCIO http://www.virCIO.Com 716 Congress, Suite 200 Austin, TX 78701 +1 512 374 0500 World War III: The Wrong-Doers Vs. the Evil-Doers. | L77: http://www.DeepEddy.Com/~cwg/, http://www.virCIO.Com
A78: EMAIL_0041 | B78: Afrikaans | C78: Translation | D78: 0 | E78: legitimate | F78: SpamAssassin | G78: Chris Garrigues <cwg-exmh@DeepEddy.Com> | H78: Scott Lipcon <slipcon@mercea.net> | I78: Tue, 24 Sep 2002 12:29:35 -0500 | J78: Re: traceback in nuwe exmh | K78: > Van: Scott Lipcon <slipcon@mercea.net> > Datum: Ma, 23 Sep 2002 22:35:05 -0400 > > Die spoed is beslis 'n probleem. Dit neem lank om die > reekse weer te skandeer (ek assosieer dit met 'n druk op die 'flist'- > knoppie, of wanneer my agtergrond-flist afgaan). Ek werk op 'n > redelik vinnige stelsel (Athlon 1700+, 512Mb RAM, 10k RPM ultra SCSI-skyf) > en 'n druk op flist het vroeër nie meer as 'n sekonde geneem nie. Die groot > verskil is dalk net persepsie, want die ou kode het net > al die vouers (telling + kleur) gelyk bygewerk, in plaas daarvan om dit > te laat lyk asof daar 0 ongesiene is en dan weer op te tel. > > Ek twyfel of ek in die nabye toekoms baie tyd sal hê om hieraan te werk, > maar as ek wel het, kan jy areas voorstel wat die beste sal wees om > te optimaliseer? Indien nie, dink jy ons kan 'n paar voorkeure insit om > van die meer intensiewe funksies af te skakel? Ek sal eerder al > die reeksondersteuning (behalwe ongesien, natuurlik) afskakel en redelike > spoed hê. Ek vermoed mense op stadige masjiene sal die huidige > toestand onbruikbaar vind. As ek geweet het waar die probleem is, sou ek dit self reggemaak het. Om dit te vind, is waarskynlik meer werk as die werklike regstelling. > > > > Dit is as gevolg van jou Hook_MsgShow_update_unseen wat 'n funksie > > roep > > wat nie meer bestaan nie. > > > > Ek vermoed jy het nou > > Seq_Del $exmh(folder) unseen $msgid > > nodig in plaas van > > Mh_MarkSeen $exmh(folder) $msgid > > > > Dankie. Ek is nie seker of ek dit met die nuwe reekskode nodig sal hê nie, maar ek > sal dalk. Skryf jou nuwe kode die reekse onmiddellik weg? Die ou kode het nie, > so ek het dit ingesit om my mh- en exmh-vensters gesinkroniseer te hou. Ja, dit doen. Chris -- Chris Garrigues http://www.DeepEddy.Com/~cwg/ virCIO http://www.virCIO.Com 716 Congress, Suite 200 Austin, TX 78701 +1 512 374 0500 Derde Wêreldoorlog: Die Kwaaddoeners teen die Boosdoeners. | L78: http://www.DeepEddy.Com/~cwg/, http://www.virCIO.Com | M78: 3 | N78: 2
A79: EMAIL_0041 | B79: isiXhosa | C79: Translation | D79: 0 | E79: legitimate | F79: SpamAssassin | G79: Chris Garrigues <cwg-exmh@DeepEddy.Com> | H79: Scott Lipcon <slipcon@mercea.net> | I79: Tue, 24 Sep 2002 12:29:35 -0500 | J79: Re: umkhondo we-traceback kwi-exmh entsha | K79: > Isuka ku: Scott Lipcon <slipcon@mercea.net> > Umhla: Mgo, 23 Sep 2002 22:35:05 -0400 > > Isantya siyinkinga ngokuqinisekileyo - Kuthatha ixesha elide ukwenza > ukuskena kwakhona kolandelelwano (ndikudibanisa nokucofa iqhosha le-'flist', > okanye xa i-flist yangasemva icima). Ndisebenza kwinkqubo > ekhawulezayo (Athlon 1700+, 512Mb RAM, 10k RPM ultra SCSI disk) > kwaye ukucofa i-flist bekungathathi ngaphezulu kwesekhondi ngaphambili. Umahluko > omkhulu usenokuba yimbono nje, kuba ikhowudi endala ibihlaziya > zonke iifolda (inani + umbala) zonke ngaxeshanye, endaweni yokwenza > kubonakale ngathi kukho 0 engabonwanga, emva koko ibala inyuka kwakhona. > > Ndiyathandabuza ukuba ndiza kuba nexesha elininzi kwiinjongo ezikufuphi zokulungisa oku, > kodwa ukuba ndinalo - ungaphakamisa iindawo ezinokuba zezona zilungileyo > zokuphuculwa? Ukuba akunjalo, ucinga ukuba singafaka izikhethwa ezithile > zokucima ezinye zeempawu ezisebenza kakhulu? Ndingakhetha ukucima lonke > uxhaso lolandelelwano (ngaphandle kokungabonwanga, ngokuqinisekileyo) kwaye ndibe nesantya > esifanelekileyo. Ndikrokrela ukuba abantu abakoomatshini abacothayo baya kufumanisa le meko > yangoku ingasebenziseki. Ukuba bendiyazi apho ikhona ingxaki, ngendimayilungisa ngokwam. Ukuyifumana mhlawumbi kungumsebenzi omkhulu kunolungiso olwenyani. > > > > Oku kungenxa ye-Hook_MsgShow_update_unseen yakho ebiza umsebenzi > > ongasekhoyo. > > > > Ndikrokrela ukuba ufuna > > Seq_Del $exmh(folder) unseen $msgid > > ngoku endaweni ye > > Mh_MarkSeen $exmh(folder) $msgid > > > > Enkosi. Andiqinisekanga ukuba ndiza kuyidinga nekhowudi entsha yolandelelwano, kodwa > ndingayifuna. Ingaba ikhowudi yakho entsha iwenza usebenze umsebenzi ngoko nangoko? Ikhowudi endala > ayizange, ngoko ke ndiyifakele ukugcina iifestile zam ze-mh kunye ne-exmh zilungelelanisiwe. Ewe, iyenza njalo. Chris -- Chris Garrigues http://www.DeepEddy.Com/~cwg/ virCIO http://www.virCIO.Com 716 Congress, Suite 200 Austin, TX 78701 +1 512 374 0500 Imfazwe Yesithathu Yehlabathi: Abenzi Bokubi ngokuchasene Naboni. | L79: http://www.DeepEddy.Com/~cwg/, http://www.virCIO.Com
A80: EMAIL_0042 | B80: English | C80: Original | D80: 0 | E80: legitimate | F80: SpamAssassin | G80: Jørgen Thomsen <list@jth.net> | H80: razor-users@example.sourceforge.net | I80: Fri, 26 Jul 2002 08:41:23 +0200 | J80: [Razor-users] Re: Content-Type: message/rfc822 supported ? | K80: Thu, 25 Jul 2002 18:33:15 -0700 skrev du: > Not sure what you're asking. I just want to be sure, that forwarding an email to my own spamtrap address which performs a razor-report on the entire received email is not waste of time, because the contents of the forwarded email is not recognized as equal to the email originally received. The forwarded email has a new set of headerlines, which should be discarded and instead the headerlines of the original message are in the body of this new message and should be recognized as such and treated properly. An ordinary Forward Unquoted in Agent is subject to character set conversions and does not depict the received spam in its original form. I hope this clarifies my concerns. - Jørgen ------------------------------------------------------- This sf.net email is sponsored by:ThinkGeek Welcome to geek heaven. http://thinkgeek.com/sf _______________________________________________ Razor-users mailing list Razor-users@lists.sourceforge.net https://lists.sourceforge.net/lists/listinfo/razor-users | L80: http://thinkgeek.com/sf, https://lists.sourceforge.net/lists/listinfo/razor-users
A81: EMAIL_0042 | B81: isiZulu | C81: Translation | D81: 0 | E81: legitimate | F81: SpamAssassin | G81: Jørgen Thomsen <list@jth.net> | H81: razor-users@example.sourceforge.net | I81: Fri, 26 Jul 2002 08:41:23 +0200 | J81: [Razor-users] Mayelana ne: Content-Type: message/rfc822 iyasekelwa? | K81: NgoLwesine, mhla zingama-25 kuJulayi 2002 ngo-18:33:15 -0700 ubhale wathi: > Angiqiniseki ukuthi ubuza ngani. Ngifuna nje ukuqiniseka ukuthi ukudlulisela i-imeyili ekhelini lami le-spamtrap (eliklanyelwe ukubamba ama-spam) — elenza umsebenzi wokubika nge-Razor kuyo yonke i-imeyili etholakele — akuyona imfucuza yesikhathi ngenxa yokuthi okuqukethwe yileyo meyili edluliselweyo akubonakali njengokufana ncamashi ne-imeyili eyamukelwe ekuqaleni. I-imeyili edluliselweyo iba nohlu olusha lwemigqa ye-header (imininingwane yomlayezo), okufanele ilahlwe; kunalokho, imigqa ye-header yomlayezo wokuqala iba ngaphakathi emzimbeni walo mlayezo omusha, futhi kufanele ibonakale njengaleyo futhi iphathwe ngendlela efanele. Isenzo esijwayelekile sokudlulisela umlayezo (Forward Unquoted) kuhlelo i-Agent sithinteka ekuguqulweni kohlobo lwezinhlamvu (character set conversions) futhi asiwukhombisi umlayezo we-spam otholakele ngesimo sawo sokuqala. Ngiyethemba ukuthi lokhu kuyakucacisa lokho engikhathazekile ngakho. - Jørgen ------------------------------------------------------- Le-imeyili ye-sf.net ixhaswe yi: ThinkGeek Siyakwamukela ezweni lamaphupho labathandi bobuchwepheshe (geek heaven). http://thinkgeek.com/sf _______________________________________________ Uhlu lokuxhumana lwabasebenzisi be-Razor Razor-users@lists.sourceforge.net https://lists.sourceforge.net/lists/listinfo/razor-users | L81: http://thinkgeek.com/sf, https://lists.sourceforge.net/lists/listinfo/razor-users
A82: EMAIL_0044 | B82: English | C82: Original | D82: 0 | E82: legitimate | F82: SpamAssassin | G82: Gary Lawrence Murphy <garym@canada.com> | H82: gbolcer@endeavors.com | I82: Mon, 19 Aug 2002 00:22:57 -0400 | J82: Re: warchalking | K82: >>>>> "G" == Gregory Alan Bolcer <gbolcer@endeavors.com> writes: G> ... Can you imagine threatening someone to get your wireless? Well ... considering they happily cashed my $2000 cheque almost a month ago and I'm /still/ using crippled auracom dialup, yes, I can imagine this, quite vividly; I will be beta-testing it sometime early next week if dsisp.net don't get my antenna rigged and guy-wired pdq. I'm paying /interest/ on that $2k! -- Gary Lawrence Murphy <garym@teledyn.com> TeleDynamics Communications Inc Business Advantage through Community Software : http://www.teledyn.com "Computers are useless. They can only give you answers."(Pablo Picasso) http://xent.com/mailman/listinfo/fork | L82: http://www.teledyn.com, http://xent.com/mailman/listinfo/fork
A83: EMAIL_0044 | B83: isiNdebele | C83: Translation | D83: 0 | E83: legitimate | F83: SpamAssassin | G83: Gary Lawrence Murphy <garym@canada.com> | H83: gbolcer@endeavors.com | I83: Mon, 19 Aug 2002 00:22:57 -0400 | J83: Re: warchalking | K83: >>>>> "G" == U-Gregory Alan Bolcer <gbolcer@endeavors.com> utlola: G> ... Ungacabanga ukuthusela omunye umuntu bona athathe i-wireless yakho? Kuhlekuhle ... nawucabanga bona bathengise isheke lami le-$2000 ngethabo ngenyanga eyadlulako begodu ngisasebenzisa i-auracom dialup, iye, ngingakghona cabanga ngalokhu, ngokukhanyako; Ngizobe ngiyihlola i-beta ngesinye isikhathi ekuthomeni ngeveke ezako nangabe i-dsisp.net ingatholi i-antenna yami elungisiweko ne-guy-wired pdq. Ngibhadela /inzalo/ kileyo $2k! -- U-Gary Lawrence Murphy <garym@teledyn.com> TeleDynamics Communications Inc Inzuzo yezebhiznisi ngokusebenzisa isofthiwe yomphakathi: http://www.teledyn.com "Amakhomphyutha awasizi ngalitho. Angakupha iimpendulo kwaphela." (Pablo Picasso) http://xent.com/mailman/listinfo/fork | L83: http://www.teledyn.com, http://xent.com/mailman/listinfo/fork
A84: EMAIL_0045 | B84: English | C84: Original | D84: 0 | E84: legitimate | F84: SpamAssassin | G84: zawodny <rssfeeds@example.com> | H84: yyyy@example.com | I84: Thu, 03 Oct 2002 08:02:40 -0000 | J84: Perl. It's just a language. | K84: URL: http://jeremy.zawodny.com/blog/archives/000218.html Date: 2002-10-02T22:52:53-08:00 I realized something the other day. I've been programming in Perl for roughly seven or eight years now. Maybe nine. It's hard to remember for sure. But at some point it lost its shine. It used to be a lot... | L84: http://jeremy.zawodny.com/blog/archives/000218.html
A85: EMAIL_0045 | B85: isiZulu | C85: Translation | D85: 0 | E85: legitimate | F85: SpamAssassin | G85: zawodny <rssfeeds@example.com> | H85: yyyy@example.com | I85: Thu, 03 Oct 2002 08:02:40 -0000 | J85: I-Perl. Kumane kuwulimi. | K85: URL: http://jeremy.zawodny.com/blog/archives/000218.html Usuku: 2002-10-02T22:52:53-08:00 Kukhona engakubona ngelinye ilanga. Sengineminyaka ecishe ibe yisikhombisa noma eyisishiyagalombili ngibhala izinhlelo zekhompyutha ngisebenzisa u-Perl. Mhlawumbe eyisishiyagalolunye. Kunzima ukukhumbula kahle. Kodwa ngesikhathi esithile, kwaphela lowo moya wokujabulela ukukusebenzisa. Kwakuyinto... | L85: http://jeremy.zawodny.com/blog/archives/000218.html
A86: EMAIL_0047 | B86: English | C86: Original | D86: 0 | E86: legitimate | F86: SpamAssassin | G86: "Hunt, Bryan" <B.Hunt@emuse-tech.com> | H86: "'ilug@linux.ie'" <ilug@linux.ie> | I86: Fri, 02 Aug 2002 10:07:17 +0100 | J86: RE: [ILUG] Dell GX260 V Redhat 7.3 | K86: When I get a box I don't want any of that integrated chipset crap whether its for winblows or linux. Its just like IBM (mwave dsp chip ?) (shared video/main memory ?)in the old days. I know you can flip a mboard jumper switch to turn crap off and install your own cards but why bother ? To clarify my point is this .... Dell makes excellent machines and I would recomend their machines and their aftersales support over any other manufacturer that I can think of. However if you want that box for linux and you have a life and you dont want to spend a week of it fucking arround and googling to get that box working properly be damned sure you do your research before you buy it. And this especially applies to their budget machines. And this isn't taking a swing at you John but ... >>Just a bad thing for those that hope a distro will work out of >>the box. A lot of the time the reason that you encounter this is cause someone has such a box and they say to you "hey can you install that linux code that I got from the guy in the internet cafe" :-) and you say sure and you go to their house (without a net connection/56k modem). And the machine has got this crap windoze only hardware and eventually you shrug in frustration and they say "well I didn't expect much from something thats free anyhow" When Dell were squabbling with Windows and it looked as though there might be a Dell/Redhat alliance my Inspiron 4000 was produced ... it worked a treat, now that dell doesn't give a shit about linux all their new cheap boxes are linux incompatable in small ways. --B -----Original Message----- From: John P. Looney [mailto:valen@tuatha.org] Sent: 02 August 2002 09:42 To: ilug@linux.ie Subject: Re: [ILUG] Dell GX260 V Redhat 7.3 On Fri, Aug 02, 2002 at 09:28:57AM +0100, Hunt, Bryan mentioned: > I'm not knocking dell in general, my next machine is going to be a dell. > But buying a random dell box is likely to result in much tearing out of > hair. Buying any new machine is going to cause problems with a six month old set of drivers. Same happens in windows - you have to go get your drivers. Yes, dell use the most recent stuff they can, to save money. That's not a bad thing. Just a bad thing for those that hope a distro will work out of the box. Kate -- Irish Linux Users' Group: ilug@linux.ie http://www.linux.ie/mailman/listinfo/ilug for (un)subscription information. List maintainer: listmaster@linux.ie -- Irish Linux Users' Group: ilug@linux.ie http://www.linux.ie/mailman/listinfo/ilug for (un)subscription information. List maintainer: listmaster@linux.ie | L86: http://www.linux.ie/mailman/listinfo/ilug
A87: EMAIL_0047 | B87: isiNdebele | C87: Translation | D87: 0 | E87: legitimate | F87: SpamAssassin | G87: "Hunt, Bryan" <B.Hunt@emuse-tech.com> | H87: "'ilug@linux.ie'" <ilug@linux.ie> | I87: Fri, 02 Aug 2002 10:07:17 +0100 | J87: RE: [ILUG] Dell GX260 V Redhat 7.3 | K87: When I get a box I don't want any of that integrated chipset crap whether its for winblows or linux. Its just like IBM (mwave dsp chip ?) (shared video/main memory ?)in the old days. I know you can flip a mboard jumper switch to turn crap off and install your own cards but why bother ? To clarify my point is this .... Dell makes excellent machines and I would recomend their machines and their aftersales support over any other manufacturer that I can think of. However if you want that box for linux and you have a life and you dont want to spend a week of it fucking arround and googling to get that box working properly be damned sure you do your research before you buy it. And this especially applies to their budget machines. And this isn't taking a swing at you John but ... >>Just a bad thing for those that hope a distro will work out of >>the box. A lot of the time the reason that you encounter this is cause someone has such a box and they say to you "hey can you install that linux code that I got from the guy in the internet cafe" :-) and you say sure and you go to their house (without a net connection/56k modem). And the machine has got this crap windoze only hardware and eventually you shrug in frustration and they say "well I didn't expect much from something thats free anyhow" When Dell were squabbling with Windows and it looked as though there might be a Dell/Redhat alliance my Inspiron 4000 was produced ... it worked a treat, now that dell doesn't give a shit about linux all their new cheap boxes are linux incompatable in small ways. --B -----Original Message----- From: John P. Looney [mailto:valen@tuatha.org] Sent: 02 August 2002 09:42 To: ilug@linux.ie Subject: Re: [ILUG] Dell GX260 V Redhat 7.3 On Fri, Aug 02, 2002 at 09:28:57AM +0100, Hunt, Bryan mentioned: > I'm not knocking dell in general, my next machine is going to be a dell. > But buying a random dell box is likely to result in much tearing out of > hair. Buying any new machine is going to cause problems with a six month old set of drivers. Same happens in windows - you have to go get your drivers. Yes, dell use the most recent stuff they can, to save money. That's not a bad thing. Just a bad thing for those that hope a distro will work out of the box. Kate -- Irish Linux Users' Group: ilug@linux.ie http://www.linux.ie/mailman/listinfo/ilug for (un)subscription information. List maintainer: listmaster@linux.ie -- Irish Linux Users' Group: ilug@linux.ie http://www.linux.ie/mailman/listinfo/ilug for (un)subscription information. List maintainer: listmaster@linux.ie | L87: http://www.linux.ie/mailman/listinfo/ilug
A88: EMAIL_0048 | B88: English | C88: Original | D88: 0 | E88: legitimate | F88: SpamAssassin | G88: guardian <rssfeeds@example.com> | H88: yyyy@example.com | I88: Tue, 08 Oct 2002 08:01:05 -0000 | J88: Boy shot at school gate | K88: URL: http://www.newsisfree.com/click/-2,8655711,215/ Date: 2002-10-08T03:30:55+01:00 *Gun violence in America: *A 13-year-old boy was shot in the chest and critically wounded outside of his school in Maryland becoming the latest victim of a sniper who has already killed six people. | L88: http://www.newsisfree.com/click/-2,8655711,215/
A89: EMAIL_0048 | B89: isiNdebele | C89: Translation | D89: 0 | E89: legitimate | F89: SpamAssassin | G89: guardian <rssfeeds@example.com> | H89: yyyy@example.com | I89: Tue, 08 Oct 2002 08:01:05 -0000 | J89: Boy shot at school gate | K89: I-URL: http://www.newsisfree.com/click/-2,8655711,215/ Ilanga: 2002-10-08T03:30:55+01:00 *Udlame lwezibhamu e-Amerikha: *Umsana oneminyaka eli-13 wadutshulwa esifubeni begodu ulimele khulu ngaphandle kwesikolo sakhe e-Maryland waba sisulu sakamuva we-sniper osele abulale abantu abasithandathu. | L89: http://www.newsisfree.com/click/-2,8655711,215/
A90: EMAIL_0050 | B90: English | C90: Original | D90: 0 | E90: legitimate | F90: SpamAssassin | G90: "Tabor J. Wells" <razor-users@fsckit.net> | H90: razor-users@example.sourceforge.net | I90: Fri, 09 Aug 2002 09:40:06 -0400 | J90: Re: [Razor-users] Re: What's wrong with the Razor servers now? | K90: On Thu, Aug 08, 2002 at 08:00:00PM -0700, Jehan <nahor@bravobrava.com> is thought to have said: > Actually you would be inaccurate in your action in a way. The correct > behavior would be to unsubscribe razor-users@fsckit.net from the mailing > list. Wow. I think a majority of the anti-spam community out there would disagree with you. It makes no difference what the list is, whether it's run by ZDNet or Empire Towers, whether it uses open proxies and relays or a MLM like mailman or Lyris. In either case I was added to a list against my will to receive unsolicited bulk email. I shouldn't have to 'just unsubscribe from the list' any more than I should have to send email with the subject REMOVE to removemeblahblah1234@yahoo.com or go to http://www.centralremovelist.com/ to 'unsubscribe' from some viagra spam. Or are you advocating that as well? > But in any case, you have to understand that you and him would not be > the only one involved. As I said in a another thread, you probably get > hurt only if you are against the majority of people (which makes sense). > If you are with the majority, you get a bonus (which also makes sense). > If there is no majority, nobody wins or lose. That's fine. But my point is that neither person in my example was committing an inherently untrustworthy act. Yet someone's TES would likely fall because of it. > Razor is designed for the betterment of most people, i.e. the majority, > not for the individual. If one doesn't agree with the majority, he > should use the razor-whitelist or create a blacklist (BTW, why doesn't > razor provide a razor-blacklist too?) Hmm. Good point about razor-whitelist. I'd forgotten about that. -- -------------------------------------------------------------------- Tabor J. Wells twells@fsckit.net Fsck It! Just another victim of the ambient morality ------------------------------------------------------- This sf.net email is sponsored by:ThinkGeek Welcome to geek heaven. http://thinkgeek.com/sf _______________________________________________ Razor-users mailing list Razor-users@lists.sourceforge.net https://lists.sourceforge.net/lists/listinfo/razor-users | L90: http://thinkgeek.com/sf, http://www.centralremovelist.com/, https://lists.sourceforge.net/lists/listinfo/razor-users
... A93: EMAIL_0051 | B93: isiNdebele | C93: Translation | D93: 0 | E93: legitimate | F93: SpamAssassin | G93: James Rogers <jamesr@best.com> | H93: fork@spamassassin.taint.org | I93: Fri, 09 Aug 2002 10:13:43 -0700 | J93: Re: Re[2]: Bukkake | K93: NgeLes'hlanu, 2002-08-09 nge-08:20, i-bitbitch@magnesium.net yatlola: > I-Smegma, kwenzeka bona iyintandokazi yomuntu mathupha. Eminyakeni eyadlulako, eminyakeni yami emihlanu > ingqondo yobudala, ubaba bekajayele ukungazisa bona ngine-'smegma' emzimbeni wami > iso, begodu uzokuragela phambili nokulikhipha. Angicabangi bona kunegama elithileko ngesiNgisi elithi eye goop. Kodwana, lokha nangifunda isiTagalog, ngafunda bona kune igama elithileko ngelimi lelo (nofana bekungelinye ilimi?) lalo: muta, ebizwa ngokuthi "MOO-ta". Nanyana i-Tagalog yami sele iphelile khulu, mina sebenzisa igama elithi "eye goop" lokha nawukhuluma isiNgisi (njani kanengi lokho kwenzeka?), khulukhulu ngombana kubonakala ngasuthi kugcwalise umgodi welimi ebuchotjhweni bami begodu ngalokho wazifaka unomphela isilulumagama sami. Akusi kukuthi lokhu kuqakathekile, kodwana ngokungazi ngamukele "muta" inguqulo yami yelimi lesiNgisi njengegama elithi "eye goop". Ngokuphikisako ngcono kune-"smegma" nanyana kunjalo. (Ngokuqinisekileko ngoLesihlanu...) -James Rogers jamesr@best.com http://xent.com/mailman/listinfo/fork | L93: http://xent.com/mailman/listinfo/fork
A94: EMAIL_0052 | B94: English | C94: Original | D94: 0 | E94: legitimate | F94: SpamAssassin | G94: Jim Whitehead <ejw@cse.ucsc.edu> | H94: fork@example.com | I94: Wed, 11 Sep 2002 08:35:31 -0700 | J94: RE: Microsoft buys XDegress - more of a p2p/distributed data thing... | K94: XDegrees was at the WebDAV Interoperability Testing Event last year, so there may be some DAV under the hood there someplace. - Jim > -----Original Message----- > From: fork-admin@xent.com [mailto:fork-admin@xent.com]On Behalf Of > Gordon Mohr > Sent: Wednesday, September 11, 2002 12:00 AM > To: fork@example.com > Subject: Re: Microsoft buys XDegress - more of a p2p/distributed data > thing... > > > Mr. FoRK writes: > > "Files can be cached on multiple systems randomly scattered around the > > Internet, as with Napster or Freenet. In fact, the caching in > XDegrees is > > more sophisticated than it is on those systems: users with high > bandwidth > > connections can download portions, or "stripes," of a file from several > > cached locations simultaneously. The XDegrees software then reassembles > > these stripes into the whole file and uses digital signatures > to verify that > > the downloaded file is the same as the original. A key component of this > > digital signature is a digest of the file, which is stored as > an HTTP header > > for the file." > > This "more sophisticated than [Napster or Freenet]" part seems > to be the same behavior implemented in many other P2P CDNs, > such as: > > - Kazaa > - EDonkey/Overnet > - BitTorrent > - Gnutella (with HUGE extensions) > - OnionNetworks WebRAID > > ...though the quality of the "digest" used by each system varies > wildly. > > - Gordon >
A95: EMAIL_0052 | B95: isiNdebele | C95: Translation | D95: 0 | E95: legitimate | F95: SpamAssassin | G95: Jim Whitehead <ejw@cse.ucsc.edu> | H95: fork@example.com | I95: Wed, 11 Sep 2002 08:35:31 -0700 | J95: RE: Microsoft buys XDegress - more of a p2p/distributed data thing... | K95: I-XDegrees beyise-WebDAV Interoperability Testing Event ngonyaka odlulileko, yeke kungenzeka kube ne-DAV ngaphasi kwe-hood lapho. - U-Jim > -----Umlayezo wekuthomeni----- > Ukusuka: fork-admin@xent.com [mailto:fork-admin@xent.com]Egameni lika > Gordon Mohr > Ithunyelwe: ngoLwesithathu, mhlana ali-11 kuNobayeni wee-2002 12:00 ekuseni > Ku: fork@example.com > Isihloko: Re: I-Microsoft ithenga i-XDegress - idatha enengi ye-p2p/distributed > into... > > > UMnu. FoRK utlola: > > "Amafayela angagcinwa eenhlelweni ezinengi ezihlakazeke ngokungakahleleki eduze kwe > > I-Inthanethi, njenge-Napster nofana i-Freenet. Kuhlekuhle, ukugcina > I-XDegrees > > eyinkimbinkimbi ukudlula lezo zinhlelo: abasebenzisi abanezinga eliphezulu > ububanzi bebhendi > > ukuxhumana kungadawuniloda iingcenye, nofana "imitjhini," yefayela elivela eendaweni ezinengi > > iindawo ezifihliweko ngasikhathi sinye. Isofthiwe ye-XDegrees ibuye ihlanganise > > imigqa le ibe yifayela loke begodu isebenzisa amasayini wedijithali > ukuqinisekisa bona > > ifayela elidawunilodiweko lifana nelokuthoma. Ingcenye eqakathekileko yalokhu > > isiginetjha yedijithali yi-digest yefayela, egcinwe njenge > ihloko ye-HTTP > > yefayela." > > Ingcenye "eyinkimbinkimbi ukudlula [i-Napster nofana i-Freenet]" ibonakala > ukuba nokuziphatha okufanako okusetjenziswe kezinye ii-P2P CDN ezinengi, > ezifana: > > - Kazaa > - EDonkey/Overnet > - BitTorrent > - I-Gnutella (eneenngezelelo ezinkulu) > - OnionNetworks WebRAID > > ...nanyana ikhwalithi "yokugaya" esetjenziswa yisistimu ngayinye ihluka > ngokungakajayeleki. > > - Gordon >
A96: EMAIL_0053 | B96: English | C96: Original | D96: 0 | E96: legitimate | F96: SpamAssassin | G96: James Rogers <jamesr@best.com> | H96: fork@example.com | I96: Tue, 24 Sep 2002 08:40:17 -0700 | J96: RE: liberal defnitions | K96: This situation wouldn't have happened in the first place if California didn't have economically insane regulations. They created a regulatory climate that facilitated this. So yes, it is the product of over-regulation. -James Rogers jamesr@best.com On Tue, 2002-09-24 at 05:17, Geege Schuman wrote: > from slate's "today's papers": > The New York Times and Los Angeles Times both lead with word that > a federal judge ruled yesterday that the nation's largest > national gas pipeline company, El Paso, illegally withheld gas > from the market during California's energy squeeze in 2000-01. > The judge concluded that El Paso left 21 percent of its capacity > in the state off-line, thus driving up the price of gas and > helping to induce rolling blackouts. > > and this is the product of overregulation?
A97: EMAIL_0053 | B97: isiNdebele | C97: Translation | D97: 0 | E97: legitimate | F97: SpamAssassin | G97: James Rogers <jamesr@best.com> | H97: fork@example.com | I97: Tue, 24 Sep 2002 08:40:17 -0700 | J97: RE: liberal defnitions | K97: Isimo lesi besingekhe senzeke ekuthomeni nangabe i-California beyinganayo imithetho engakajayeleki kwezomnotho. Bakha umthetho ubujamo bezulu okwenze bona lokhu kube lula. Njeke iye, mkhiqizo we ukulawulwa ngokweqileko. -James Rogers jamesr@best.com NgoLwesibili, 2002-09-24 nge-05:17, u-Geege Schuman watlola: > ukusuka "emaphepheni wanamhlanjesi" we-slate: > I-New York Times ne-Los Angeles Times zombili zidosa phambili ngokuthi > ijaji lefederali linqume izolo bona isiqunto esikhulu kunazo zoke enarheni > inkampani yamapayipi wegesi weentjhabatjhaba, i-El Paso, ibambe igesi ngokungasimthethweni > ukusuka emakethe ngesikhathi sokugandeleleka kwamandla we-California ngo-2000-01. > Ijaji laphetha ngokuthi i-El Paso itjhiye amaphesente ama-21 wamandla wayo > ebujameni obungekho emthethweni, lokho kukhuphula intengo yegesi begodu > ukusiza ukubanga ukucima kwamandla. > > begodu lokhu kungumkhiqizo wokulawulwa ngokweqileko?
A98: EMAIL_0054 | B98: English | C98: Original | D98: 0 | E98: legitimate | F98: SpamAssassin | G98: Patrick <patrick@stealthgeeks.net> | H98: Vipul Ved Prakash <mail@vipul.net> | I98: Wed, 14 Aug 2002 14:47:02 -0700 | J98: Re: [Razor-users] Re: What's wrong with the Razor servers now? | K98: On Mon, 12 Aug 2002, Vipul Ved Prakash wrote: > On Mon, Aug 12, 2002 at 10:38:44AM -0700, Craig R . Hughes wrote: > > This is, I think the biggest fallacy here. You don't have to > > block jack shit to get a high trust rating, you just have to > > confirm Razor's existing opinion on a large number of messages: > > > > if(check() == spam) then submit() else revoke() > > > > That algorithm boosts trust, but reduces the information in > > SpamNet by damping. > > Again, this is not true. Only certain events (reports/revokes) for a spam > are rewarded and the algorithm for picking these up is based on many > different factors. And those would be???? Is there a point that you plan on releasing detailed information about TeS, so we can stop engaging in idle speculation? It's not my desire to second-guess you Vipul(however much my missives may appear otherwise) or question the hard work you and the other developers have put into the system, however it seems that every request for such information has been met with silence. Thanks. /\/\/\/\/\/\/\/\/\/\/\/\/\/\/\/\/\/\/\/\/\/\/\/\/\/\/\/\/\/\/\/\/\/\/\/\/\/\/\ Patrick Greenwell Asking the wrong questions is the leading cause of wrong answers \/\/\/\/\/\/\/\/\/\/\/\/\/\/\/\/\/\/\/\/\/\/\/\/\/\/\/\/\/\/\/\/\/\/\/\/\/\/\/ ------------------------------------------------------- This sf.net email is sponsored by: Dice - The leading online job board for high-tech professionals. Search and apply for tech jobs today! http://seeker.dice.com/seeker.epl?rel_code=31 _______________________________________________ Razor-users mailing list Razor-users@lists.sourceforge.net https://lists.sourceforge.net/lists/listinfo/razor-users | L98: http://seeker.dice.com/seeker.epl?rel_code=31, https://lists.sourceforge.net/lists/listinfo/razor-users
A99: EMAIL_0054 | B99: isiZulu | C99: Translation | D99: 0 | E99: legitimate | F99: SpamAssassin | G99: Patrick <patrick@stealthgeeks.net> | H99: Vipul Ved Prakash <mail@vipul.net> | I99: Wed, 14 Aug 2002 14:47:02 -0700 | J99: Mayelana: [Razor-users] Mayelana: Yini inkinga ngamaseva e-Razor manje? | K99: NgoMsombuluko, mhla ziyi-12 ku-Agasti 2002, uVipul Ved Prakash wabhala: > NgoMsombuluko, mhla ziyi-12 ku-Agasti 2002 ngo-10:38:44 ekuseni -0700, uCraig R. Hughes wabhala: > > Ngicabanga ukuthi lokhu yiphutha elikhulu kunazo zonke lapha. Awudingi > > ukuvimba lutho nhlobo ukuze uthole izinga eliphezulu lokwethenjwa, udinga nje > > ukuqinisekisa umbono we-Razor osele ukhona mayelana nenqwaba yemiyalezo: > > > > if(check() == spam) then submit() else revoke() > > > > Leyo ndlela yokusebenza (algorithm) ikhuphula ukwethenjwa, kodwa inciphisa ulwazi > > oluku-SpamNet ngokulunciphisa amandla (damping). > > Futhi, lokhu akulona iqiniso. Izenzakalo ezithile kuphela (imibiko/ukuhoxiswa kwemibiko) > mayelana ne-spam ezithola umvuzo, futhi indlela yokukhetha lezi zinto isekelwe ezintweni > eziningi ezahlukene. Futhi lezo zinto kungaba yini???? Ingabe ikhona indlela yokuthi uhlele ukukhipha ulwazi oluningiliziwe mayelana ne-TeS, ukuze siyeke ukuqagela nje okungenasisekelo? Angifuni ukungabaza izinqumo zakho Vipul (kungakhathaliseki ukuthi imiyalezo yami ingase ibonakale kanjani) noma ukungabaza umsebenzi onzima wena nabanye onjiniyela eniwufake kulolu hlelo, nokho kubonakala sengathi zonke izicelo zalolo lwazi ziphendulwa ngokuthula. Ngiyabonga. /\/\/\/\/\/\/\/\/\/\/\/\/\/\/\/\/\/\/\/\/\/\/\/\/\/\/\/\/\/\/\/\/\/\/\/\/\/\/\ Patrick Greenwell Ukubuza imibuzo engalungile yisona sizathu esikhulu sezimpendulo ezingalungile \/\/\/\/\/\/\/\/\/\/\/\/\/\/\/\/\/\/\/\/\/\/\/\/\/\/\/\/\/\/\/\/\/\/\/\/\/\/\/ ------------------------------------------------------- Le-imeyili ye-sf.net ixhaswe yi: Dice - Inkundla ehamba phambili ye-inthanethi yokuthola imisebenzi yochwepheshe bezobuchwepheshe obuphambili (high-tech). Sesha futhi ufake izicelo zemisebenzi yezobuchwepheshe namuhla! http://seeker.dice.com/seeker.epl?rel_code=31 _______________________________________________ Uhlu lwabasebenzisi be-Razor (Razor-users mailing list) Razor-users@lists.sourceforge.net https://lists.sourceforge.net/lists/listinfo/razor-users | L99: http://seeker.dice.com/seeker.epl?rel_code=31, https://lists.sourceforge.net/lists/listinfo/razor-users
A100: EMAIL_0055 | B100: English | C100: Original | D100: 0 | E100: legitimate | F100: SpamAssassin | G100: harley@argote.ch | H100: fork@spamassassin.taint.org | I100: Wed, 28 Aug 2002 18:59:37 +0200 | J100: Re: Java is for kiddies | K100: GLM wrote: >And a Java program, due to the extensive class libraries, will weigh >in at 10% the number of lines of the equivalent C program. QED. Quod erat not demonstrandum at all. There are massive amounts of libraries for C, Fortran and so on. To pick an obvious example., if you want to do linear algebra, then Java isn't a serious candidate at all. Furthermore, plenty of bugs occur in the libraries too, at a lower rate due to more users having been bitten by them, but they are much harder for you to fix than in your own code. Why do so many people outside of Sun's marketing department consider Java to be "Write Once, Debug Everywhere" ? R
A101: EMAIL_0055 | B101: isiZulu | C101: Translation | D101: 0 | E101: legitimate | F101: SpamAssassin | G101: harley@argote.ch | H101: fork@spamassassin.taint.org | I101: Wed, 28 Aug 2002 18:59:37 +0200 | J101: Mayelana nokuthi i-Java yeyezingane | K101: U-GLM wabhala: >Futhi uhlelo lwe-Java, ngenxa yemitapo yolwazi yekilasi ebanzi, luzoba nesisindo >ku-10% yenani lemigqa yohlelo olulinganayo C. QED. I-Quod erat ayiyona i-demonstrandum nhlobo. Kunenani elikhulu lemitapo yolwazi ye-C, Fortran njalonjalo. Ukukhetha isibonelo esisobala., uma ufuna ukwenza i-algebra yomugqa, ke I-Java ayilona ikhandidethi elibalulekile nhlobo. Ngaphezu kwalokho, izimbungulu eziningi zenzeka emitapo yolwazi, kancane izinga ngenxa yabasebenzisi abaningi abalunywe yibo, kodwa baningi okunzima kakhulu ukuba ukulungise kunekhodi yakho siqu. Kungani abantu abaningi abangaphandle komnyango wezokukhangisa we-Sun becabanga I-Java izoba "Bhala Kanye, Lungisa Iphutha Yonke Indawo" ? R
A102: EMAIL_0056 | B102: English | C102: Original | D102: 0 | E102: legitimate | F102: SpamAssassin | G102: Nick Murtagh <nickm@go2.ie> | H102: ilug@linux.ie | I102: Sun, 11 Aug 2002 00:55:10 +0100 | J102: Re: [ILUG] SUSE 8 disks? (was [ILUG] ILUG newsgroup(s)?) | K102: On Fri, 2002-08-09 at 19:13, Paul Linehan wrote: > I'm looking for the disks for SUSE 8. Does anybody > have them for a reasonable price? First you complain about the supposed lack of threading in Internet Mail, and then you reply to one of the messages in that thread on an unrelated topic, messing things up for those of us with threading turned on? Even Outlook Express does threading! Sigh... Nick -- Irish Linux Users' Group: ilug@linux.ie http://www.linux.ie/mailman/listinfo/ilug for (un)subscription information. List maintainer: listmaster@linux.ie | L102: http://www.linux.ie/mailman/listinfo/ilug
A103: EMAIL_0056 | B103: Afrikaans | C103: Translation | D103: 0 | E103: legitimate | F103: SpamAssassin | G103: Nick Murtagh <nickm@go2.ie> | H103: ilug@linux.ie | I103: Sun, 11 Aug 2002 00:55:10 +0100 | J103: Re: [ILUG] SUSE 8-skywe? (was [ILUG] ILUG-nuusgroep(e)?) | K103: Op Vr, 2002-08-09 om 19:13 het Paul Linehan geskryf: > Ek soek die skywe vir SUSE 8. Het iemand > hulle teen 'n redelike prys? Eers kla jy oor die vermeende gebrek aan draadsortering in Internet Mail, en dan antwoord jy op een van die boodskappe in daardie draad oor 'n onverwante onderwerp, en krap dinge deurmekaar vir diegene van ons wat draadsortering aangeskakel het? Selfs Outlook Express doen draadsortering! Sug... Nick -- Ierse Linux-gebruikersgroep: ilug@linux.ie http://www.linux.ie/mailman/listinfo/ilug vir inligting oor in- en uitskrywing. Lysbestuurder: listmaster@linux.ie | L103: http://www.linux.ie/mailman/listinfo/ilug | M103: 3 | N103: 2
A104: EMAIL_0056 | B104: isiXhosa | C104: Translation | D104: 0 | E104: legitimate | F104: SpamAssassin | G104: Nick Murtagh <nickm@go2.ie> | H104: ilug@linux.ie | I104: Sun, 11 Aug 2002 00:55:10 +0100 | J104: Re: [ILUG] Iidiski ze-SUSE 8? (bekuyi [ILUG] Amaqela eendaba e-ILUG?) | K104: NgoLwesihlanu, 2002-08-09 ngo-19:13, uPaul Linehan wabhala: > Ndikhangela iidiski ze-SUSE 8. Ingaba ukhona umntu > onazo ngexabiso elifanelekileyo? Kuqala ukhalaza ngokungabikho koluhlu lweentambo kwi-Internet Mail, kwaye emva koko uphendula komnye wemiyalezo ekule ntambo ngomxholo ongahambelaniyo, uphazamisa izinto kwabo bethu abanomsebenzi wokulandelelanisa iintambo uvuliwe? Nantoni ne-Outlook Express iyakwenza ukulandelelanisa iintambo! Kuyancwinwa... Nick -- Iqela labasebenzisi be-Linux base-Ireland: ilug@linux.ie http://www.linux.ie/mailman/listinfo/ilug ngolwazi malunga nokurhoxisa/ukubhalisa. Umlawuli woluhlu: listmaster@linux.ie | L104: http://www.linux.ie/mailman/listinfo/ilug
A105: EMAIL_0057 | B105: English | C105: Original | D105: 0 | E105: legitimate | F105: SpamAssassin | G105: gkm@petting-zoo.net | H105: 0xdeadbeef@petting-zoo.net | I105: Tue, 17 Sep 2002 15:15:57 -0700 | J105: Virgin's latest airliner. | K105: Forwarded-by: William Knowles <wk@c4i.org> http://www.thesun.co.uk/article/0,,2-2002430339,00.html By PAUL CROSBIE Sep 16, 2002 VIRGIN'S latest airliner is being revamped after randy passengers discovered a tiny cabin was just the place to join the Mile High Club. The �130million Airbus 340-600 is fitted with a 5ft x 4ft mother and baby room with a plastic table meant for changing nappies. But couples keep wrecking it by sneaking in for a quick bonk. Virgin has replaced the table several times even though the plane only came into service a few weeks ago. It is named Claudia Nine after sexy model Claudia Schiffer, 32, who launched it in July. Now Virgin bosses have asked Airbus to build a stronger table. At first, German engineers responsible for the jet's interior were baffled by the problem. The table is designed to take the weight of a mum and baby. One Airbus worker said: "We couldn't work it out. Then the penny dropped. It didn't occur to the Germans that this might happen. It caused great amusement." The firm say the cost of strengthening the tables will be about �200. A Virgin spokeswoman said: "Those determined to join the Mile High Club will do so despite the lack of comforts. "We don't mind couples having a good time but this is not something that we would encourage because of air regulations." The new Airbus is the world's longest airliner, with teasing slogan "Mine is bigger than yours". Virgin is using it on flights to the Far East and the US. | L105: http://www.thesun.co.uk/article/0,,2-2002430339,00.html
...

Sheet Coverage
A1: email_id | B1: label | C1: source_dataset | D1: master_id | E1: Afrikaans | F1: isiXhosa | G1: isiZulu | H1: isiNdebele | I1: languages | J1: subject
A2: EMAIL_0001 | B2: legitimate | C2: SpamAssassin | D2: M03265 | E2: yes | F2: yes | I2: 2 | J2: Re: [ILUG-Social] Anyone in Limerick want to help?
A3: EMAIL_0005 | B3: legitimate | C3: SpamAssassin | D3: M01562 | H3: yes | I3: 1 | J3: [Razor-users] Preproc erasing message
A4: EMAIL_0006 | B4: legitimate | C4: SpamAssassin | D4: M03924 | G4: yes | I4: 1 | J4: Re: spam maps
A5: EMAIL_0007 | B5: legitimate | C5: SpamAssassin | D5: M01297 | G5: yes | I5: 1 | J5: Re: transcode build problem (was: RH 8 no DMA for DVD drive)
A6: EMAIL_0008 | B6: legitimate | C6: SpamAssassin | D6: M01421 | H6: yes | I6: 1 | J6: Re: Storing passwords
A7: EMAIL_0011 | B7: legitimate | C7: SpamAssassin | D7: M01903 | G7: yes | I7: 1 | J7: Jeremy Bowers: "None of the trackback mechanisms has reached the critical m
A8: EMAIL_0013 | B8: legitimate | C8: SpamAssassin | D8: M01561 | G8: yes | I8: 1 | J8: Re[2]: [Razor-users] Reducing impact from tons of email
A9: EMAIL_0014 | B9: legitimate | C9: SpamAssassin | D9: M01512 | G9: yes | I9: 1 | J9: [SAdev] [Bug 886] Add a rule to detect Content-type message/partial
A10: EMAIL_0015 | B10: legitimate | C10: SpamAssassin | D10: M02051 | G10: yes | I10: 1 | J10: Mice born from rat-matured eggs
A11: EMAIL_0016 | B11: legitimate | C11: SpamAssassin | D11: M03301 | H11: yes | I11: 1 | J11: Re: [ILUG] Optimising for PentiumMMX?
A12: EMAIL_0017 | B12: legitimate | C12: SpamAssassin | D12: M00651 | E12: yes | F12: yes | I12: 2 | J12: Re: Slaughter in the Name of God
A13: EMAIL_0018 | B13: legitimate | C13: SpamAssassin | D13: M00189 | E13: yes | F13: yes | I13: 2 | J13: Re: a problem with apt-get
A14: EMAIL_0019 | B14: legitimate | C14: SpamAssassin | D14: M00851 | G14: yes | I14: 1 | J14: Re: EBusiness Webforms: cluetrain has left the station
A15: EMAIL_0020 | B15: legitimate | C15: SpamAssassin | D15: M01117 | E15: yes | F15: yes | I15: 2 | J15: creating rpms with subdirs (install command)
A16: EMAIL_0021 | B16: legitimate | C16: SpamAssassin | D16: M02138 | G16: yes | I16: 1 | J16: FreeBSD or Linux for your MySQL Server?
A17: EMAIL_0023 | B17: legitimate | C17: SpamAssassin | D17: M01611 | H17: yes | I17: 1 | J17: RE: [Razor-users] Fire.cloudmark.com is having issues
A18: EMAIL_0024 | B18: legitimate | C18: SpamAssassin | D18: M01373 | G18: yes | I18: 1 | J18: Re: [SAdev] 2.40: ready for release? *NO*
A19: EMAIL_0025 | B19: legitimate | C19: SpamAssassin | D19: M03919 | G19: yes | I19: 1 | J19: PATCH (was: Re: Another bug)
A20: EMAIL_0026 | B20: legitimate | C20: SpamAssassin | D20: M01136 | G20: yes | I20: 1 | J20: Re: Apt problems
A21: EMAIL_0027 | B21: legitimate | C21: SpamAssassin | D21: M02342 | E21: yes | F21: yes | I21: 2 | J21: Tory leader risks all on 80s revival
A22: EMAIL_0028 | B22: legitimate | C22: SpamAssassin | D22: M01397 | E22: yes | F22: yes | I22: 2 | J22: Re: [SAtalk] O.T. Habeus -- Why?
A23: EMAIL_0029 | B23: legitimate | C23: SpamAssassin | D23: M01125 | G23: yes | I23: 1 | J23: Re: About apt, kernel updates and dist-upgrade
A24: EMAIL_0030 | B24: legitimate | C24: SpamAssassin | D24: M04154 | G24: yes | I24: 1 | J24: Re: What's cool about doing nothing
A25: EMAIL_0031 | B25: legitimate | C25: SpamAssassin | D25: M01301 | G25: yes | I25: 1 | J25: Re: RH 8 no DMA for DVD drive
A26: EMAIL_0032 | B26: legitimate | C26: SpamAssassin | D26: M00810 | H26: yes | I26: 1 | J26: liberal defnitions
A27: EMAIL_0033 | B27: legitimate | C27: SpamAssassin | D27: M03775 | E27: yes | F27: yes | I27: 2 | J27: Re: [Razor-users] False Positives on EFF Messages
A28: EMAIL_0034 | B28: legitimate | C28: SpamAssassin | D28: M00330 | H28: yes | I28: 1 | J28: Re: RedHat 8.0 and his own freetype
A29: EMAIL_0035 | B29: legitimate | C29: SpamAssassin | D29: M04232 | E29: yes | F29: yes | I29: 2 | J29: RE: David Friedman: Mail Me the Money!
A30: EMAIL_0036 | B30: legitimate | C30: SpamAssassin | D30: M00711 | G30: yes | I30: 1 | J30: Re: Hanson's Sept 11 message in the National Review
A31: EMAIL_0037 | B31: legitimate | C31: SpamAssassin | D31: M00340 | E31: yes | F31: yes | I31: 2 | J31: Re: Zoot apt/openssh & new DVD playing doc
A32: EMAIL_0038 | B32: legitimate | C32: SpamAssassin | D32: M01237 | H32: yes | I32: 1 | J32: Re: Gabber packages for 8.0 (was: All set for Red Hat Linux 8.0)
A33: EMAIL_0039 | B33: legitimate | C33: SpamAssassin | D33: M01375 | H33: yes | I33: 1 | J33: Re: [SAtalk] O.T. Habeus -- Why?
A34: EMAIL_0040 | B34: legitimate | C34: SpamAssassin | D34: M00288 | H34: yes | I34: 1 | J34: [zzzzteana] Betamax finally laid to rest
A35: EMAIL_0041 | B35: legitimate | C35: SpamAssassin | D35: M01170 | E35: yes | F35: yes | I35: 2 | J35: Re: traceback in new exmh
A36: EMAIL_0042 | B36: legitimate | C36: SpamAssassin | D36: M03764 | G36: yes | I36: 1 | J36: [Razor-users] Re: Content-Type: message/rfc822 supported ?
A37: EMAIL_0044 | B37: legitimate | C37: SpamAssassin | D37: M04000 | H37: yes | I37: 1 | J37: Re: warchalking
A38: EMAIL_0045 | B38: legitimate | C38: SpamAssassin | D38: M02208 | G38: yes | I38: 1 | J38: Perl. It's just a language.
A39: EMAIL_0047 | B39: legitimate | C39: SpamAssassin | D39: M03438 | H39: yes | I39: 1 | J39: RE: [ILUG] Dell GX260 V Redhat 7.3
A40: EMAIL_0048 | B40: legitimate | C40: SpamAssassin | D40: M02358 | H40: yes | I40: 1 | J40: Boy shot at school gate
A41: EMAIL_0050 | B41: legitimate | C41: SpamAssassin | D41: M03803 | H41: yes | I41: 1 | J41: Re: [Razor-users] Re: What's wrong with the Razor servers now?
A42: EMAIL_0051 | B42: legitimate | C42: SpamAssassin | D42: M04194 | H42: yes | I42: 1 | J42: Re: Re[2]: Bukkake
A43: EMAIL_0052 | B43: legitimate | C43: SpamAssassin | D43: M00610 | H43: yes | I43: 1 | J43: RE: Microsoft buys XDegress - more of a p2p/distributed data thing...
A44: EMAIL_0053 | B44: legitimate | C44: SpamAssassin | D44: M00818 | H44: yes | I44: 1 | J44: RE: liberal defnitions
A45: EMAIL_0054 | B45: legitimate | C45: SpamAssassin | D45: M03859 | G45: yes | I45: 1 | J45: Re: [Razor-users] Re: What's wrong with the Razor servers now?
A46: EMAIL_0055 | B46: legitimate | C46: SpamAssassin | D46: M00405 | G46: yes | I46: 1 | J46: Re: Java is for kiddies
A47: EMAIL_0056 | B47: legitimate | C47: SpamAssassin | D47: M03546 | E47: yes | F47: yes | I47: 2 | J47: Re: [ILUG] SUSE 8 disks? (was [ILUG] ILUG newsgroup(s)?)
A48: EMAIL_0057 | B48: legitimate | C48: SpamAssassin | D48: M01798 | E48: yes | F48: yes | I48: 2 | J48: Virgin's latest airliner.
A49: EMAIL_0059 | B49: legitimate | C49: SpamAssassin | D49: M00268 | H49: yes | I49: 1 | J49: Re: [ILUG] find the biggest file
A50: EMAIL_0060 | B50: legitimate | C50: SpamAssassin | D50: M03217 | E50: yes | F50: yes | I50: 2 | J50: Re: New Sequences Window
A51: EMAIL_0061 | B51: legitimate | C51: SpamAssassin | D51: M04112 | E51: yes | F51: yes | I51: 2 | J51: Re: Asteroids anyone ?
A52: EMAIL_0062 | B52: legitimate | C52: SpamAssassin | D52: M00798 | E52: yes | F52: yes | I52: 2 | J52: Pluck and Luck
A53: EMAIL_0063 | B53: legitimate | C53: SpamAssassin | D53: M01431 | E53: yes | F53: yes | I53: 2 | J53: [Spambayes] all but one testing
A54: EMAIL_0064 | B54: legitimate | C54: SpamAssassin | D54: M00982 | H54: yes | I54: 1 | J54: Fwd: [POLITICOS] Re: "Bowling for Columbine," Opens This Friday
A55: EMAIL_0065 | B55: legitimate | C55: SpamAssassin | D55: M00717 | G55: yes | I55: 1 | J55: Re: Hanson's Sept 11 message in the National Review
A56: EMAIL_0066 | B56: legitimate | C56: SpamAssassin | D56: M03530 | G56: yes | I56: 1 | J56: Re: [ILUG] TMDA (WAS --> slashdot EW Dijkstra humor]
A57: EMAIL_0067 | B57: legitimate | C57: SpamAssassin | D57: M00899 | G57: yes | I57: 1 | J57: ActiveBuddy
A58: EMAIL_0068 | B58: legitimate | C58: SpamAssassin | D58: M00131 | H58: yes | I58: 1 | J58: [ILUG] freeserve in the uk?
A59: EMAIL_0069 | B59: legitimate | C59: SpamAssassin | D59: M00890 | E59: yes | F59: yes | I59: 2 | J59: RE: MIT OpenCourseWare
A60: EMAIL_0070 | B60: legitimate | C60: SpamAssassin | D60: M01691 | H60: yes | I60: 1 | J60: [Spambayes] understanding high false negative rate
A61: EMAIL_0071 | B61: legitimate | C61: SpamAssassin | D61: M02365 | E61: yes | F61: yes | I61: 2 | J61: City Planning Funnies
A62: EMAIL_0072 | B62: legitimate | C62: SpamAssassin | D62: M00527 | G62: yes | I62: 1 | J62: RE: Re[2]: Selling Wedded Bliss (was Re: Ouch...)
A63: EMAIL_0073 | B63: legitimate | C63: SpamAssassin | D63: M03511 | H63: yes | I63: 1 | J63: [ILUG] Digital Cameras
A64: EMAIL_0074 | B64: legitimate | C64: SpamAssassin | D64: M03984 | E64: yes | F64: yes | I64: 2 | J64: Re: inbox mail notification broken
A65: EMAIL_0075 | B65: legitimate | C65: SpamAssassin | D65: M02391 | G65: yes | I65: 1 | J65: Neutrino and X-ray physicists win Nobel Prize
A66: EMAIL_0076 | B66: legitimate | C66: SpamAssassin | D66: M03513 | H66: yes | I66: 1 | J66: Re: [ILUG] Digital Cameras
A67: EMAIL_0077 | B67: legitimate | C67: SpamAssassin | D67: M02244 | E67: yes | F67: yes | I67: 2 | J67: History of the tilde
A68: EMAIL_0078 | B68: legitimate | C68: SpamAssassin | D68: M00210 | G68: yes | I68: 1 | J68: [ILUG] cups question
A69: EMAIL_0079 | B69: legitimate | C69: SpamAssassin | D69: M02218 | E69: yes | F69: yes | I69: 2 | J69: Marriage makes both sexes happy
A70: EMAIL_0081 | B70: legitimate | C70: SpamAssassin | D70: M00015 | H70: yes | I70: 1 | J70: [SAdev] Party in San Francisco tonight
A71: EMAIL_0082 | B71: legitimate | C71: SpamAssassin | D71: M00980 | E71: yes | F71: yes | I71: 2 | J71: RE: The Disappearing Alliance
A72: EMAIL_0083 | B72: legitimate | C72: SpamAssassin | D72: M03628 | E72: yes | F72: yes | I72: 2 | J72: Re: [ILUG] Optimizing for Pentium Pt.2
A73: EMAIL_0084 | B73: legitimate | C73: SpamAssassin | D73: M01951 | E73: yes | F73: yes | I73: 2 | J73: A Non-Integer Power Function on the Pixel Shader
A74: EMAIL_0085 | B74: legitimate | C74: SpamAssassin | D74: M01197 | G74: yes | I74: 1 | J74: Re: Ringing bell on other computer
A75: EMAIL_0087 | B75: legitimate | C75: SpamAssassin | D75: M00466 | E75: yes | F75: yes | I75: 2 | J75: InfoWorld profile of Max Levchin
A76: EMAIL_0088 | B76: legitimate | C76: SpamAssassin | D76: M01286 | E76: yes | F76: yes | I76: 2 | J76: xine src package
A77: EMAIL_0089 | B77: legitimate | C77: SpamAssassin | D77: M00697 | H77: yes | I77: 1 | J77: Re: AA Meetings the Hottest Place to Meet Women With Big Bucks
A78: EMAIL_0092 | B78: legitimate | C78: SpamAssassin | D78: M00173 | G78: yes | I78: 1 | J78: Iran Pushes UN Intervention Against US
A79: EMAIL_0093 | B79: legitimate | C79: SpamAssassin | D79: M00654 | E79: yes | F79: yes | I79: 2 | J79: FW: Wanna buy a nuke?
A80: EMAIL_0095 | B80: legitimate | C80: SpamAssassin | D80: M04496 | E80: yes | F80: yes | I80: 2 | J80: Re: [SAtalk] http://www.spamassassin.org
A81: EMAIL_0096 | B81: legitimate | C81: SpamAssassin | D81: M01834 | H81: yes | I81: 1 | J81: Turning junk computers into activist gold
A82: EMAIL_0097 | B82: legitimate | C82: SpamAssassin | D82: M00041 | E82: yes | F82: yes | I82: 2 | J82: Re: lifegem
A83: EMAIL_0098 | B83: legitimate | C83: SpamAssassin | D83: M00848 | E83: yes | F83: yes | I83: 2 | J83: RE: The Big Jump
A84: EMAIL_0100 | B84: legitimate | C84: SpamAssassin | D84: M03724 | G84: yes | I84: 1 | J84: linux.ie mailing list memberships reminder
A85: EMAIL_0101 | B85: legitimate | C85: SpamAssassin | D85: M01273 | E85: yes | F85: yes | I85: 2 | J85: Re: Alsa/Redhat 8 compatability
A86: EMAIL_0102 | B86: legitimate | C86: SpamAssassin | D86: M01230 | G86: yes | I86: 1 | J86: Re: apt 0.5.7 on RH 7.x
A87: EMAIL_0103 | B87: legitimate | C87: SpamAssassin | D87: M01300 | H87: yes | I87: 1 | J87: Re: transcode build problem (was: RH 8 no DMA for DVD drive)
A88: EMAIL_0104 | B88: legitimate | C88: SpamAssassin | D88: M00187 | H88: yes | I88: 1 | J88: Human handshake opens data stream
A89: EMAIL_0105 | B89: legitimate | C89: SpamAssassin | D89: M00019 | H89: yes | I89: 1 | J89: The case for spam
A90: EMAIL_0106 | B90: legitimate | C90: SpamAssassin | D90: M01069 | E90: yes | F90: yes | I90: 2 | J90: Re: Linking message [was: Re: Patch to complete a change...]
A91: EMAIL_0108 | B91: legitimate | C91: SpamAssassin | D91: M01722 | H91: yes | I91: 1 | J91: [Spambayes] testing results
A92: EMAIL_0109 | B92: legitimate | C92: SpamAssassin | D92: M03932 | E92: yes | F92: yes | I92: 2 | J92: Re: PATCH (was: Re: Another bug)
A93: EMAIL_0111 | B93: legitimate | C93: SpamAssassin | D93: M03571 | E93: yes | F93: yes | I93: 2 | J93: Re: [ILUG] SUSE 8 disks? (thread changed slightly)
A94: EMAIL_0113 | B94: legitimate | C94: SpamAssassin | D94: M00284 | G94: yes | I94: 1 | J94: /home/dude
A95: EMAIL_0114 | B95: legitimate | C95: SpamAssassin | D95: M04237 | G95: yes | I95: 1 | J95: Re: NYTimes.com Article: Bigger Bar Code Inches Up on Retailers
A96: EMAIL_0117 | B96: legitimate | C96: SpamAssassin | D96: M02350 | H96: yes | I96: 1 | J96: Apple: Heinous DVD Pirates
A97: EMAIL_0118 | B97: legitimate | C97: SpamAssassin | D97: M02225 | H97: yes | I97: 1 | J97: Wed. OSXCon Keynote -- Jordan Hubbard
A98: EMAIL_0119 | B98: legitimate | C98: SpamAssassin | D98: M01007 | G98: yes | I98: 1 | J98: Re: New Sequences Window
A99: EMAIL_0121 | B99: legitimate | C99: SpamAssassin | D99: M01138 | G99: yes | I99: 1 | J99: Re: Apt problems
A100: EMAIL_0122 | B100: legitimate | C100: SpamAssassin | D100: M00370 | H100: yes | I100: 1 | J100: Re: The GOv gets tough on Net Users.....er Pirates..
...

Sheet Issues
A1: severity | B1: language | C1: email_id | D1: label | E1: issue
A2: Fix before testing | B2: isiNdebele | C2: EMAIL_0047 | D2: legitimate | E2: Body not translated (identical to English)
A3: Fix before testing | B3: isiNdebele | C3: EMAIL_0169 | D3: legitimate | E3: Translation is a copy of EMAIL_0179's translation, not this email
A4: Fix before testing | B4: isiNdebele | C4: EMAIL_0266 | D4: phishing | E4: Spanish footer with two Scotiabank links left out of the translation
A5: Fix before testing | B5: isiNdebele | C5: EMAIL_0374 | D5: phishing | E5: Body not translated (identical to English)
A6: Fix before testing | B6: isiNdebele | C6: EMAIL_0445 | D6: phishing | E6: Body not translated (identical to English)
A7: Fix before testing | B7: isiNdebele | C7: all 120 | D7: both | E7: Subjects not translated: subject_nr holds the English subject for now
A8: Fix before testing | B8: isiZulu | C8: EMAIL_0143 | D8: legitimate | E8: Body not translated (identical to English)
A9: Check | B9: Afrikaans | C9: EMAIL_0069 | D9: legitimate | E9: Subject not translated
A10: Check | B10: Afrikaans | C10: EMAIL_0095 | D10: legitimate | E10: Subject not translated
A11: Check | B11: Afrikaans | C11: EMAIL_0426 | D11: phishing | E11: Subject not translated
A12: Check | B12: isiNdebele | C12: EMAIL_0050 | D12: legitimate | E12: Later part of the email left out (removeme address missing)
... A26: OK | B26: isiZulu | C26: EMAIL_0368 | D26: phishing | E26: English body is empty, nothing to translate

Sheet Changes made
A1: language | B1: email_id | C1: column | D1: was | E1: now | F1: why
A2: isiXhosa | B2: EMAIL_0432 | C2: body_t | D2: monkey.org? valid=sign_back_in | E2: monkey.org?valid=sign_back_in | F2: Space inserted inside the link; link restored exactly as in English
A3: isiNdebele | B3: EMAIL_0271 | C3: body_t | D3: Jose@monkey.org | E3: jose@monkey.org | F3: Email address capitalised; restored exactly as in English
A4: isiNdebele | B4: EMAIL_0290 | C4: body_t | D4: Jose@monkey.org | E4: jose@monkey.org | F4: Email address capitalised; restored exactly as in English
A5: isiXhosa | B5: EMAIL_0193 | C5: body_t | D5: http://www.newsisfree.com/click/-0.8365765.1440/ | E5: http://www.newsisfree.com/click/-0,8365765,1440/ | F5: Link changed during translation; restored exactly as in English
A6: isiXhosa | B6: EMAIL_0165 | C6: body_t | D6: http://www.timesonline.co.uk/printFriendly/0,,,1-43-351083,00.html | E6: http://www.timesonline.co.uk/printFriendly/0,,1-43-351083,00.html | F6: Link changed during translation; restored exactly as in English
A7: isiXhosa | B7: EMAIL_0079 | C7: body_t | D7: http://www.newsisfree.com/click/-3.8483157.1440/ | E7: http://www.newsisfree.com/click/-3,8483157,1440/ | F7: Link changed during translation; restored exactly as in English
A8: isiNdebele | B8: EMAIL_0309 | C8: body_t | D8: https://nofyerushalaim.com/americanexpress.com/communication/requiredLB5uEfjPEeTB0WvjKy2Ro7aPho86kOl2JjfaHKWoUhAbeYxmwFz | E8: https://nofyerushalaim.com/americanexpress.com/communication/requiredLB5uEfjPEeTB0WvjKy2Ro7aPho86kOl2JjfaHKWoUhAbeYxmwFz | F8: Link changed during translation; restored exactly as in English
